Workbook

Sheet northwind_orders
A1: order_id | B1: customer_id | C1: employee_id | D1: order_date | E1: required_date | F1: shipped_date | G1: ship_via | H1: freight | I1: ship_name | J1: ship_address | K1: ship_city | L1: ship_region | M1: ship_postal_code | N1: ship_country | O1: delivery
A2: 10248 | B2: VINET | C2: 5 | D2: 35250 | E2: 35278 | F2: 35262 | G2: 3 | H2: 32.38 | I2: Vins et alcools Chevalier | J2: 59 rue de l'Abbaye | K2: Reims | M2: 51100 | N2: France | O2: =IF(northwind_orders[[#This Row],[required_date]]-northwind_orders[[#This Row],[shipped_date]]>0,"Faster",IF(northwind_orders[[#This Row],[required_date]]-northwind_orders[[#This Row],[shipped_date]]=0,"In Time","Slower")) -> Faster
A3: 10249 | B3: TOMSP | C3: 6 | D3: 35251 | E3: 35293 | F3: 35256 | G3: 1 | H3: 11.61 | I3: Toms SpezialitГ¤ten | J3: Luisenstr. 48 | K3: MГјnster | M3: 44087 | N3: Germany | O3: =IF(northwind_orders[[#This Row],[required_date]]-northwind_orders[[#This Row],[shipped_date]]>0,"Faster",IF(northwind_orders[[#This Row],[required_date]]-northwind_orders[[#This Row],[shipped_date]]=0,"In Time","Slower")) -> Faster
A4: 10250 | B4: HANAR | C4: 4 | D4: 35254 | E4: 35282 | F4: 35258 | G4: 2 | H4: 65.83 | I4: Hanari Carnes | J4: Rua do PaГ§o, 67 | K4: Rio de Janeiro | L4: RJ | M4: 05454-876 | N4: Brazil | O4: =IF(northwind_orders[[#This Row],[required_date]]-northwind_orders[[#This Row],[shipped_date]]>0,"Faster",IF(northwind_orders[[#This Row],[required_date]]-northwind_orders[[#This Row],[shipped_date]]=0,"In Time","Slower")) -> Faster
A5: 10251 | B5: VICTE | C5: 3 | D5: 35254 | E5: 35282 | F5: 35261 | G5: 1 | H5: 41.34 | I5: Victuailles en stock | J5: 2, rue du Commerce | K5: Lyon | M5: 69004 | N5: France | O5: =IF(northwind_orders[[#This Row],[required_date]]-northwind_orders[[#This Row],[shipped_date]]>0,"Faster",IF(northwind_orders[[#This Row],[required_date]]-northwind_orders[[#This Row],[shipped_date]]=0,"In Time","Slower")) -> Faster
A6: 10252 | B6: SUPRD | C6: 4 | D6: 35255 | E6: 35283 | F6: 35257 | G6: 2 | H6: 51.3 | I6: SuprГЄmes dГ©lices | J6: Boulevard Tirou, 255 | K6: Charleroi | M6: B-6000 | N6: Belgium | O6: =IF(northwind_orders[[#This Row],[required_date]]-northwind_orders[[#This Row],[shipped_date]]>0,"Faster",IF(northwind_orders[[#This Row],[required_date]]-northwind_orders[[#This Row],[shipped_date]]=0,"In Time","Slower")) -> Faster
A7: 10253 | B7: HANAR | C7: 3 | D7: 35256 | E7: 35270 | F7: 35262 | G7: 2 | H7: 58.17 | I7: Hanari Carnes | J7: Rua do PaГ§o, 67 | K7: Rio de Janeiro | L7: RJ | M7: 05454-876 | N7: Brazil | O7: =IF(northwind_orders[[#This Row],[required_date]]-northwind_orders[[#This Row],[shipped_date]]>0,"Faster",IF(northwind_orders[[#This Row],[required_date]]-northwind_orders[[#This Row],[shipped_date]]=0,"In Time","Slower")) -> Faster
A8: 10254 | B8: CHOPS | C8: 5 | D8: 35257 | E8: 35285 | F8: 35269 | G8: 2 | H8: 22.98 | I8: Chop-suey Chinese | J8: Hauptstr. 31 | K8: Bern | M8: 3012 | N8: Switzerland | O8: =IF(northwind_orders[[#This Row],[required_date]]-northwind_orders[[#This Row],[shipped_date]]>0,"Faster",IF(northwind_orders[[#This Row],[required_date]]-northwind_orders[[#This Row],[shipped_date]]=0,"In Time","Slower")) -> Faster
A9: 10255 | B9: RICSU | C9: 9 | D9: 35258 | E9: 35286 | F9: 35261 | G9: 3 | H9: 148.33 | I9: Richter Supermarkt | J9: Starenweg 5 | K9: GenГЁve | M9: 1204 | N9: Switzerland | O9: =IF(northwind_orders[[#This Row],[required_date]]-northwind_orders[[#This Row],[shipped_date]]>0,"Faster",IF(northwind_orders[[#This Row],[required_date]]-northwind_orders[[#This Row],[shipped_date]]=0,"In Time","Slower")) -> Faster
A10: 10256 | B10: WELLI | C10: 3 | D10: 35261 | E10: 35289 | F10: 35263 | G10: 2 | H10: 13.97 | I10: Wellington Importadora | J10: Rua do Mercado, 12 | K10: Resende | L10: SP | M10: 08737-363 | N10: Brazil | O10: =IF(northwind_orders[[#This Row],[required_date]]-northwind_orders[[#This Row],[shipped_date]]>0,"Faster",IF(northwind_orders[[#This Row],[required_date]]-northwind_orders[[#This Row],[shipped_date]]=0,"In Time","Slower")) -> Faster
A11: 10257 | B11: HILAA | C11: 4 | D11: 35262 | E11: 35290 | F11: 35268 | G11: 3 | H11: 81.91 | I11: HILARION-Abastos | J11: Carrera 22 con Ave. Carlos Soublette #8-35 | K11: San CristГіbal | L11: TГЎchira | M11: 5022 | N11: Venezuela | O11: =IF(northwind_orders[[#This Row],[required_date]]-northwind_orders[[#This Row],[shipped_date]]>0,"Faster",IF(northwind_orders[[#This Row],[required_date]]-northwind_orders[[#This Row],[shipped_date]]=0,"In Time","Slower")) -> Faster
A12: 10258 | B12: ERNSH | C12: 1 | D12: 35263 | E12: 35291 | F12: 35269 | G12: 1 | H12: 140.51 | I12: Ernst Handel | J12: Kirchgasse 6 | K12: Graz | M12: 8010 | N12: Austria | O12: =IF(northwind_orders[[#This Row],[required_date]]-northwind_orders[[#This Row],[shipped_date]]>0,"Faster",IF(northwind_orders[[#This Row],[required_date]]-northwind_orders[[#This Row],[shipped_date]]=0,"In Time","Slower")) -> Faster
A13: 10259 | B13: CENTC | C13: 4 | D13: 35264 | E13: 35292 | F13: 35271 | G13: 3 | H13: 3.25 | I13: Centro comercial Moctezuma | J13: Sierras de Granada 9993 | K13: MГ©xico D.F. | M13: 05022 | N13: Mexico | O13: =IF(northwind_orders[[#This Row],[required_date]]-northwind_orders[[#This Row],[shipped_date]]>0,"Faster",IF(northwind_orders[[#This Row],[required_date]]-northwind_orders[[#This Row],[shipped_date]]=0,"In Time","Slower")) -> Faster
A14: 10260 | B14: OTTIK | C14: 4 | D14: 35265 | E14: 35293 | F14: 35275 | G14: 1 | H14: 55.09 | I14: Ottilies KГ¤seladen | J14: Mehrheimerstr. 369 | K14: KГ¶ln | M14: 50739 | N14: Germany | O14: =IF(northwind_orders[[#This Row],[required_date]]-northwind_orders[[#This Row],[shipped_date]]>0,"Faster",IF(northwind_orders[[#This Row],[required_date]]-northwind_orders[[#This Row],[shipped_date]]=0,"In Time","Slower")) -> Faster
A15: 10261 | B15: QUEDE | C15: 4 | D15: 35265 | E15: 35293 | F15: 35276 | G15: 2 | H15: 3.05 | I15: Que DelГ­cia | J15: Rua da Panificadora, 12 | K15: Rio de Janeiro | L15: RJ | M15: 02389-673 | N15: Brazil | O15: =IF(northwind_orders[[#This Row],[required_date]]-northwind_orders[[#This Row],[shipped_date]]>0,"Faster",IF(northwind_orders[[#This Row],[required_date]]-northwind_orders[[#This Row],[shipped_date]]=0,"In Time","Slower")) -> Faster
A16: 10262 | B16: RATTC | C16: 8 | D16: 35268 | E16: 35296 | F16: 35271 | G16: 3 | H16: 48.29 | I16: Rattlesnake Canyon Grocery | J16: 2817 Milton Dr. | K16: Albuquerque | L16: NM | M16: 87110 | N16: USA | O16: =IF(northwind_orders[[#This Row],[required_date]]-northwind_orders[[#This Row],[shipped_date]]>0,"Faster",IF(northwind_orders[[#This Row],[required_date]]-northwind_orders[[#This Row],[shipped_date]]=0,"In Time","Slower")) -> Faster
A17: 10263 | B17: ERNSH | C17: 9 | D17: 35269 | E17: 35297 | F17: 35277 | G17: 3 | H17: 146.06 | I17: Ernst Handel | J17: Kirchgasse 6 | K17: Graz | M17: 8010 | N17: Austria | O17: =IF(northwind_orders[[#This Row],[required_date]]-northwind_orders[[#This Row],[shipped_date]]>0,"Faster",IF(northwind_orders[[#This Row],[required_date]]-northwind_orders[[#This Row],[shipped_date]]=0,"In Time","Slower")) -> Faster
A18: 10264 | B18: FOLKO | C18: 6 | D18: 35270 | E18: 35298 | F18: 35300 | G18: 3 | H18: 3.67 | I18: Folk och fГ¤ HB | J18: Г…kergatan 24 | K18: BrГ¤cke | M18: S-844 67 | N18: Sweden | O18: =IF(northwind_orders[[#This Row],[required_date]]-northwind_orders[[#This Row],[shipped_date]]>0,"Faster",IF(northwind_orders[[#This Row],[required_date]]-northwind_orders[[#This Row],[shipped_date]]=0,"In Time","Slower")) -> Slower
A19: 10265 | B19: BLONP | C19: 2 | D19: 35271 | E19: 35299 | F19: 35289 | G19: 1 | H19: 55.28 | I19: Blondel pГЁre et fils | J19: 24, place KlГ©ber | K19: Strasbourg | M19: 67000 | N19: France | O19: =IF(northwind_orders[[#This Row],[required_date]]-northwind_orders[[#This Row],[shipped_date]]>0,"Faster",IF(northwind_orders[[#This Row],[required_date]]-northwind_orders[[#This Row],[shipped_date]]=0,"In Time","Slower")) -> Faster
A20: 10266 | B20: WARTH | C20: 3 | D20: 35272 | E20: 35314 | F20: 35277 | G20: 3 | H20: 25.73 | I20: Wartian Herkku | J20: Torikatu 38 | K20: Oulu | M20: 90110 | N20: Finland | O20: =IF(northwind_orders[[#This Row],[required_date]]-northwind_orders[[#This Row],[shipped_date]]>0,"Faster",IF(northwind_orders[[#This Row],[required_date]]-northwind_orders[[#This Row],[shipped_date]]=0,"In Time","Slower")) -> Faster
A21: 10267 | B21: FRANK | C21: 4 | D21: 35275 | E21: 35303 | F21: 35283 | G21: 1 | H21: 208.58 | I21: Frankenversand | J21: Berliner Platz 43 | K21: MГјnchen | M21: 80805 | N21: Germany | O21: =IF(northwind_orders[[#This Row],[required_date]]-northwind_orders[[#This Row],[shipped_date]]>0,"Faster",IF(northwind_orders[[#This Row],[required_date]]-northwind_orders[[#This Row],[shipped_date]]=0,"In Time","Slower")) -> Faster
A22: 10268 | B22: GROSR | C22: 8 | D22: 35276 | E22: 35304 | F22: 35279 | G22: 3 | H22: 66.29 | I22: GROSELLA-Restaurante | J22: 5ВЄ Ave. Los Palos Grandes | K22: Caracas | L22: DF | M22: 1081 | N22: Venezuela | O22: =IF(northwind_orders[[#This Row],[required_date]]-northwind_orders[[#This Row],[shipped_date]]>0,"Faster",IF(northwind_orders[[#This Row],[required_date]]-northwind_orders[[#This Row],[shipped_date]]=0,"In Time","Slower")) -> Faster
A23: 10269 | B23: WHITC | C23: 5 | D23: 35277 | E23: 35291 | F23: 35286 | G23: 1 | H23: 4.56 | I23: White Clover Markets | J23: 1029 - 12th Ave. S. | K23: Seattle | L23: WA | M23: 98124 | N23: USA | O23: =IF(northwind_orders[[#This Row],[required_date]]-northwind_orders[[#This Row],[shipped_date]]>0,"Faster",IF(northwind_orders[[#This Row],[required_date]]-northwind_orders[[#This Row],[shipped_date]]=0,"In Time","Slower")) -> Faster
A24: 10270 | B24: WARTH | C24: 1 | D24: 35278 | E24: 35306 | F24: 35279 | G24: 1 | H24: 136.54 | I24: Wartian Herkku | J24: Torikatu 38 | K24: Oulu | M24: 90110 | N24: Finland | O24: =IF(northwind_orders[[#This Row],[required_date]]-northwind_orders[[#This Row],[shipped_date]]>0,"Faster",IF(northwind_orders[[#This Row],[required_date]]-northwind_orders[[#This Row],[shipped_date]]=0,"In Time","Slower")) -> Faster
A25: 10271 | B25: SPLIR | C25: 6 | D25: 35278 | E25: 35306 | F25: 35307 | G25: 2 | H25: 4.54 | I25: Split Rail Beer & Ale | J25: P.O. Box 555 | K25: Lander | L25: WY | M25: 82520 | N25: USA | O25: =IF(northwind_orders[[#This Row],[required_date]]-northwind_orders[[#This Row],[shipped_date]]>0,"Faster",IF(northwind_orders[[#This Row],[required_date]]-northwind_orders[[#This Row],[shipped_date]]=0,"In Time","Slower")) -> Slower
A26: 10272 | B26: RATTC | C26: 6 | D26: 35279 | E26: 35307 | F26: 35283 | G26: 2 | H26: 98.03 | I26: Rattlesnake Canyon Grocery | J26: 2817 Milton Dr. | K26: Albuquerque | L26: NM | M26: 87110 | N26: USA | O26: =IF(northwind_orders[[#This Row],[required_date]]-northwind_orders[[#This Row],[shipped_date]]>0,"Faster",IF(northwind_orders[[#This Row],[required_date]]-northwind_orders[[#This Row],[shipped_date]]=0,"In Time","Slower")) -> Faster
A27: 10273 | B27: QUICK | C27: 3 | D27: 35282 | E27: 35310 | F27: 35289 | G27: 3 | H27: 76.07 | I27: QUICK-Stop | J27: TaucherstraГџe 10 | K27: Cunewalde | M27: 01307 | N27: Germany | O27: =IF(northwind_orders[[#This Row],[required_date]]-northwind_orders[[#This Row],[shipped_date]]>0,"Faster",IF(northwind_orders[[#This Row],[required_date]]-northwind_orders[[#This Row],[shipped_date]]=0,"In Time","Slower")) -> Faster
A28: 10274 | B28: VINET | C28: 6 | D28: 35283 | E28: 35311 | F28: 35293 | G28: 1 | H28: 6.01 | I28: Vins et alcools Chevalier | J28: 59 rue de l'Abbaye | K28: Reims | M28: 51100 | N28: France | O28: =IF(northwind_orders[[#This Row],[required_date]]-northwind_orders[[#This Row],[shipped_date]]>0,"Faster",IF(northwind_orders[[#This Row],[required_date]]-northwind_orders[[#This Row],[shipped_date]]=0,"In Time","Slower")) -> Faster
A29: 10275 | B29: MAGAA | C29: 1 | D29: 35284 | E29: 35312 | F29: 35286 | G29: 1 | H29: 26.93 | I29: Magazzini Alimentari Riuniti | J29: Via Ludovico il Moro 22 | K29: Bergamo | M29: 24100 | N29: Italy | O29: =IF(northwind_orders[[#This Row],[required_date]]-northwind_orders[[#This Row],[shipped_date]]>0,"Faster",IF(northwind_orders[[#This Row],[required_date]]-northwind_orders[[#This Row],[shipped_date]]=0,"In Time","Slower")) -> Faster
A30: 10276 | B30: TORTU | C30: 8 | D30: 35285 | E30: 35299 | F30: 35291 | G30: 3 | H30: 13.84 | I30: Tortuga Restaurante | J30: Avda. Azteca 123 | K30: MГ©xico D.F. | M30: 05033 | N30: Mexico | O30: =IF(northwind_orders[[#This Row],[required_date]]-northwind_orders[[#This Row],[shipped_date]]>0,"Faster",IF(northwind_orders[[#This Row],[required_date]]-northwind_orders[[#This Row],[shipped_date]]=0,"In Time","Slower")) -> Faster
A31: 10277 | B31: MORGK | C31: 2 | D31: 35286 | E31: 35314 | F31: 35290 | G31: 3 | H31: 125.77 | I31: Morgenstern Gesundkost | J31: Heerstr. 22 | K31: Leipzig | M31: 04179 | N31: Germany | O31: =IF(northwind_orders[[#This Row],[required_date]]-northwind_orders[[#This Row],[shipped_date]]>0,"Faster",IF(northwind_orders[[#This Row],[required_date]]-northwind_orders[[#This Row],[shipped_date]]=0,"In Time","Slower")) -> Faster
A32: 10278 | B32: BERGS | C32: 8 | D32: 35289 | E32: 35317 | F32: 35293 | G32: 2 | H32: 92.69 | I32: Berglunds snabbkГ¶p | J32: BerguvsvГ¤gen 8 | K32: LuleГҐ | M32: S-958 22 | N32: Sweden | O32: =IF(northwind_orders[[#This Row],[required_date]]-northwind_orders[[#This Row],[shipped_date]]>0,"Faster",IF(northwind_orders[[#This Row],[required_date]]-northwind_orders[[#This Row],[shipped_date]]=0,"In Time","Slower")) -> Faster
A33: 10279 | B33: LEHMS | C33: 8 | D33: 35290 | E33: 35318 | F33: 35293 | G33: 2 | H33: 25.83 | I33: Lehmanns Marktstand | J33: Magazinweg 7 | K33: Frankfurt a.M. | M33: 60528 | N33: Germany | O33: =IF(northwind_orders[[#This Row],[required_date]]-northwind_orders[[#This Row],[shipped_date]]>0,"Faster",IF(northwind_orders[[#This Row],[required_date]]-northwind_orders[[#This Row],[shipped_date]]=0,"In Time","Slower")) -> Faster
A34: 10280 | B34: BERGS | C34: 2 | D34: 35291 | E34: 35319 | F34: 35320 | G34: 1 | H34: 8.98 | I34: Berglunds snabbkГ¶p | J34: BerguvsvГ¤gen 8 | K34: LuleГҐ | M34: S-958 22 | N34: Sweden | O34: =IF(northwind_orders[[#This Row],[required_date]]-northwind_orders[[#This Row],[shipped_date]]>0,"Faster",IF(northwind_orders[[#This Row],[required_date]]-northwind_orders[[#This Row],[shipped_date]]=0,"In Time","Slower")) -> Slower
A35: 10281 | B35: ROMEY | C35: 4 | D35: 35291 | E35: 35305 | F35: 35298 | G35: 1 | H35: 2.94 | I35: Romero y tomillo | J35: Gran VГ­a, 1 | K35: Madrid | M35: 28001 | N35: Spain | O35: =IF(northwind_orders[[#This Row],[required_date]]-northwind_orders[[#This Row],[shipped_date]]>0,"Faster",IF(northwind_orders[[#This Row],[required_date]]-northwind_orders[[#This Row],[shipped_date]]=0,"In Time","Slower")) -> Faster
A36: 10282 | B36: ROMEY | C36: 4 | D36: 35292 | E36: 35320 | F36: 35298 | G36: 1 | H36: 12.69 | I36: Romero y tomillo | J36: Gran VГ­a, 1 | K36: Madrid | M36: 28001 | N36: Spain | O36: =IF(northwind_orders[[#This Row],[required_date]]-northwind_orders[[#This Row],[shipped_date]]>0,"Faster",IF(northwind_orders[[#This Row],[required_date]]-northwind_orders[[#This Row],[shipped_date]]=0,"In Time","Slower")) -> Faster
A37: 10283 | B37: LILAS | C37: 3 | D37: 35293 | E37: 35321 | F37: 35300 | G37: 3 | H37: 84.81 | I37: LILA-Supermercado | J37: Carrera 52 con Ave. BolГ­var #65-98 Llano Largo | K37: Barquisimeto | L37: Lara | M37: 3508 | N37: Venezuela | O37: =IF(northwind_orders[[#This Row],[required_date]]-northwind_orders[[#This Row],[shipped_date]]>0,"Faster",IF(northwind_orders[[#This Row],[required_date]]-northwind_orders[[#This Row],[shipped_date]]=0,"In Time","Slower")) -> Faster
A38: 10284 | B38: LEHMS | C38: 4 | D38: 35296 | E38: 35324 | F38: 35304 | G38: 1 | H38: 76.56 | I38: Lehmanns Marktstand | J38: Magazinweg 7 | K38: Frankfurt a.M. | M38: 60528 | N38: Germany | O38: =IF(northwind_orders[[#This Row],[required_date]]-northwind_orders[[#This Row],[shipped_date]]>0,"Faster",IF(northwind_orders[[#This Row],[required_date]]-northwind_orders[[#This Row],[shipped_date]]=0,"In Time","Slower")) -> Faster
A39: 10285 | B39: QUICK | C39: 1 | D39: 35297 | E39: 35325 | F39: 35303 | G39: 2 | H39: 76.83 | I39: QUICK-Stop | J39: TaucherstraГџe 10 | K39: Cunewalde | M39: 01307 | N39: Germany | O39: =IF(northwind_orders[[#This Row],[required_date]]-northwind_orders[[#This Row],[shipped_date]]>0,"Faster",IF(northwind_orders[[#This Row],[required_date]]-northwind_orders[[#This Row],[shipped_date]]=0,"In Time","Slower")) -> Faster
A40: 10286 | B40: QUICK | C40: 8 | D40: 35298 | E40: 35326 | F40: 35307 | G40: 3 | H40: 229.24 | I40: QUICK-Stop | J40: TaucherstraГџe 10 | K40: Cunewalde | M40: 01307 | N40: Germany | O40: =IF(northwind_orders[[#This Row],[required_date]]-northwind_orders[[#This Row],[shipped_date]]>0,"Faster",IF(northwind_orders[[#This Row],[required_date]]-northwind_orders[[#This Row],[shipped_date]]=0,"In Time","Slower")) -> Faster
A41: 10287 | B41: RICAR | C41: 8 | D41: 35299 | E41: 35327 | F41: 35305 | G41: 3 | H41: 12.76 | I41: Ricardo Adocicados | J41: Av. Copacabana, 267 | K41: Rio de Janeiro | L41: RJ | M41: 02389-890 | N41: Brazil | O41: =IF(northwind_orders[[#This Row],[required_date]]-northwind_orders[[#This Row],[shipped_date]]>0,"Faster",IF(northwind_orders[[#This Row],[required_date]]-northwind_orders[[#This Row],[shipped_date]]=0,"In Time","Slower")) -> Faster
A42: 10288 | B42: REGGC | C42: 4 | D42: 35300 | E42: 35328 | F42: 35311 | G42: 1 | H42: 7.45 | I42: Reggiani Caseifici | J42: Strada Provinciale 124 | K42: Reggio Emilia | M42: 42100 | N42: Italy | O42: =IF(northwind_orders[[#This Row],[required_date]]-northwind_orders[[#This Row],[shipped_date]]>0,"Faster",IF(northwind_orders[[#This Row],[required_date]]-northwind_orders[[#This Row],[shipped_date]]=0,"In Time","Slower")) -> Faster
A43: 10289 | B43: BSBEV | C43: 7 | D43: 35303 | E43: 35331 | F43: 35305 | G43: 3 | H43: 22.77 | I43: B's Beverages | J43: Fauntleroy Circus | K43: London | M43: EC2 5NT | N43: UK | O43: =IF(northwind_orders[[#This Row],[required_date]]-northwind_orders[[#This Row],[shipped_date]]>0,"Faster",IF(northwind_orders[[#This Row],[required_date]]-northwind_orders[[#This Row],[shipped_date]]=0,"In Time","Slower")) -> Faster
A44: 10290 | B44: COMMI | C44: 8 | D44: 35304 | E44: 35332 | F44: 35311 | G44: 1 | H44: 79.7 | I44: ComГ©rcio Mineiro | J44: Av. dos LusГ­adas, 23 | K44: Sao Paulo | L44: SP | M44: 05432-043 | N44: Brazil | O44: =IF(northwind_orders[[#This Row],[required_date]]-northwind_orders[[#This Row],[shipped_date]]>0,"Faster",IF(northwind_orders[[#This Row],[required_date]]-northwind_orders[[#This Row],[shipped_date]]=0,"In Time","Slower")) -> Faster
A45: 10291 | B45: QUEDE | C45: 6 | D45: 35304 | E45: 35332 | F45: 35312 | G45: 2 | H45: 6.4 | I45: Que DelГ­cia | J45: Rua da Panificadora, 12 | K45: Rio de Janeiro | L45: RJ | M45: 02389-673 | N45: Brazil | O45: =IF(northwind_orders[[#This Row],[required_date]]-northwind_orders[[#This Row],[shipped_date]]>0,"Faster",IF(northwind_orders[[#This Row],[required_date]]-northwind_orders[[#This Row],[shipped_date]]=0,"In Time","Slower")) -> Faster
A46: 10292 | B46: TRADH | C46: 1 | D46: 35305 | E46: 35333 | F46: 35310 | G46: 2 | H46: 1.35 | I46: TradiГ§ao Hipermercados | J46: Av. InГЄs de Castro, 414 | K46: Sao Paulo | L46: SP | M46: 05634-030 | N46: Brazil | O46: =IF(northwind_orders[[#This Row],[required_date]]-northwind_orders[[#This Row],[shipped_date]]>0,"Faster",IF(northwind_orders[[#This Row],[required_date]]-northwind_orders[[#This Row],[shipped_date]]=0,"In Time","Slower")) -> Faster
A47: 10293 | B47: TORTU | C47: 1 | D47: 35306 | E47: 35334 | F47: 35319 | G47: 3 | H47: 21.18 | I47: Tortuga Restaurante | J47: Avda. Azteca 123 | K47: MГ©xico D.F. | M47: 05033 | N47: Mexico | O47: =IF(northwind_orders[[#This Row],[required_date]]-northwind_orders[[#This Row],[shipped_date]]>0,"Faster",IF(northwind_orders[[#This Row],[required_date]]-northwind_orders[[#This Row],[shipped_date]]=0,"In Time","Slower")) -> Faster
A48: 10294 | B48: RATTC | C48: 4 | D48: 35307 | E48: 35335 | F48: 35313 | G48: 2 | H48: 147.26 | I48: Rattlesnake Canyon Grocery | J48: 2817 Milton Dr. | K48: Albuquerque | L48: NM | M48: 87110 | N48: USA | O48: =IF(northwind_orders[[#This Row],[required_date]]-northwind_orders[[#This Row],[shipped_date]]>0,"Faster",IF(northwind_orders[[#This Row],[required_date]]-northwind_orders[[#This Row],[shipped_date]]=0,"In Time","Slower")) -> Faster
A49: 10295 | B49: VINET | C49: 2 | D49: 35310 | E49: 35338 | F49: 35318 | G49: 2 | H49: 1.15 | I49: Vins et alcools Chevalier | J49: 59 rue de l'Abbaye | K49: Reims | M49: 51100 | N49: France | O49: =IF(northwind_orders[[#This Row],[required_date]]-northwind_orders[[#This Row],[shipped_date]]>0,"Faster",IF(northwind_orders[[#This Row],[required_date]]-northwind_orders[[#This Row],[shipped_date]]=0,"In Time","Slower")) -> Faster
A50: 10296 | B50: LILAS | C50: 6 | D50: 35311 | E50: 35339 | F50: 35319 | G50: 1 | H50: 0.12 | I50: LILA-Supermercado | J50: Carrera 52 con Ave. BolГ­var #65-98 Llano Largo | K50: Barquisimeto | L50: Lara | M50: 3508 | N50: Venezuela | O50: =IF(northwind_orders[[#This Row],[required_date]]-northwind_orders[[#This Row],[shipped_date]]>0,"Faster",IF(northwind_orders[[#This Row],[required_date]]-northwind_orders[[#This Row],[shipped_date]]=0,"In Time","Slower")) -> Faster
A51: 10297 | B51: BLONP | C51: 5 | D51: 35312 | E51: 35354 | F51: 35318 | G51: 2 | H51: 5.74 | I51: Blondel pГЁre et fils | J51: 24, place KlГ©ber | K51: Strasbourg | M51: 67000 | N51: France | O51: =IF(northwind_orders[[#This Row],[required_date]]-northwind_orders[[#This Row],[shipped_date]]>0,"Faster",IF(northwind_orders[[#This Row],[required_date]]-northwind_orders[[#This Row],[shipped_date]]=0,"In Time","Slower")) -> Faster
A52: 10299 | B52: RICAR | C52: 4 | D52: 35314 | E52: 35342 | F52: 35321 | G52: 2 | H52: 29.76 | I52: Ricardo Adocicados | J52: Av. Copacabana, 267 | K52: Rio de Janeiro | L52: RJ | M52: 02389-890 | N52: Brazil | O52: =IF(northwind_orders[[#This Row],[required_date]]-northwind_orders[[#This Row],[shipped_date]]>0,"Faster",IF(northwind_orders[[#This Row],[required_date]]-northwind_orders[[#This Row],[shipped_date]]=0,"In Time","Slower")) -> Faster
A53: 10300 | B53: MAGAA | C53: 2 | D53: 35317 | E53: 35345 | F53: 35326 | G53: 2 | H53: 17.68 | I53: Magazzini Alimentari Riuniti | J53: Via Ludovico il Moro 22 | K53: Bergamo | M53: 24100 | N53: Italy | O53: =IF(northwind_orders[[#This Row],[required_date]]-northwind_orders[[#This Row],[shipped_date]]>0,"Faster",IF(northwind_orders[[#This Row],[required_date]]-northwind_orders[[#This Row],[shipped_date]]=0,"In Time","Slower")) -> Faster
A54: 10301 | B54: WANDK | C54: 8 | D54: 35317 | E54: 35345 | F54: 35325 | G54: 2 | H54: 45.08 | I54: Die Wandernde Kuh | J54: Adenauerallee 900 | K54: Stuttgart | M54: 70563 | N54: Germany | O54: =IF(northwind_orders[[#This Row],[required_date]]-northwind_orders[[#This Row],[shipped_date]]>0,"Faster",IF(northwind_orders[[#This Row],[required_date]]-northwind_orders[[#This Row],[shipped_date]]=0,"In Time","Slower")) -> Faster
A55: 10302 | B55: SUPRD | C55: 4 | D55: 35318 | E55: 35346 | F55: 35347 | G55: 2 | H55: 6.27 | I55: SuprГЄmes dГ©lices | J55: Boulevard Tirou, 255 | K55: Charleroi | M55: B-6000 | N55: Belgium | O55: =IF(northwind_orders[[#This Row],[required_date]]-northwind_orders[[#This Row],[shipped_date]]>0,"Faster",IF(northwind_orders[[#This Row],[required_date]]-northwind_orders[[#This Row],[shipped_date]]=0,"In Time","Slower")) -> Slower
A56: 10303 | B56: GODOS | C56: 7 | D56: 35319 | E56: 35347 | F56: 35326 | G56: 2 | H56: 107.83 | I56: Godos Cocina TГ­pica | J56: C/ Romero, 33 | K56: Sevilla | M56: 41101 | N56: Spain | O56: =IF(northwind_orders[[#This Row],[required_date]]-northwind_orders[[#This Row],[shipped_date]]>0,"Faster",IF(northwind_orders[[#This Row],[required_date]]-northwind_orders[[#This Row],[shipped_date]]=0,"In Time","Slower")) -> Faster
A57: 10304 | B57: TORTU | C57: 1 | D57: 35320 | E57: 35348 | F57: 35325 | G57: 2 | H57: 63.79 | I57: Tortuga Restaurante | J57: Avda. Azteca 123 | K57: MГ©xico D.F. | M57: 05033 | N57: Mexico | O57: =IF(northwind_orders[[#This Row],[required_date]]-northwind_orders[[#This Row],[shipped_date]]>0,"Faster",IF(northwind_orders[[#This Row],[required_date]]-northwind_orders[[#This Row],[shipped_date]]=0,"In Time","Slower")) -> Faster
A58: 10305 | B58: OLDWO | C58: 8 | D58: 35321 | E58: 35349 | F58: 35347 | G58: 3 | H58: 257.62 | I58: Old World Delicatessen | J58: 2743 Bering St. | K58: Anchorage | L58: AK | M58: 99508 | N58: USA | O58: =IF(northwind_orders[[#This Row],[required_date]]-northwind_orders[[#This Row],[shipped_date]]>0,"Faster",IF(northwind_orders[[#This Row],[required_date]]-northwind_orders[[#This Row],[shipped_date]]=0,"In Time","Slower")) -> Faster
A59: 10306 | B59: ROMEY | C59: 1 | D59: 35324 | E59: 35352 | F59: 35331 | G59: 3 | H59: 7.56 | I59: Romero y tomillo | J59: Gran VГ­a, 1 | K59: Madrid | M59: 28001 | N59: Spain | O59: =IF(northwind_orders[[#This Row],[required_date]]-northwind_orders[[#This Row],[shipped_date]]>0,"Faster",IF(northwind_orders[[#This Row],[required_date]]-northwind_orders[[#This Row],[shipped_date]]=0,"In Time","Slower")) -> Faster
A60: 10307 | B60: LONEP | C60: 2 | D60: 35325 | E60: 35353 | F60: 35333 | G60: 2 | H60: 0.56 | I60: Lonesome Pine Restaurant | J60: 89 Chiaroscuro Rd. | K60: Portland | L60: OR | M60: 97219 | N60: USA | O60: =IF(northwind_orders[[#This Row],[required_date]]-northwind_orders[[#This Row],[shipped_date]]>0,"Faster",IF(northwind_orders[[#This Row],[required_date]]-northwind_orders[[#This Row],[shipped_date]]=0,"In Time","Slower")) -> Faster
A61: 10308 | B61: ANATR | C61: 7 | D61: 35326 | E61: 35354 | F61: 35332 | G61: 3 | H61: 1.61 | I61: Ana Trujillo Emparedados y helados | J61: Avda. de la ConstituciГіn 2222 | K61: MГ©xico D.F. | M61: 05021 | N61: Mexico | O61: =IF(northwind_orders[[#This Row],[required_date]]-northwind_orders[[#This Row],[shipped_date]]>0,"Faster",IF(northwind_orders[[#This Row],[required_date]]-northwind_orders[[#This Row],[shipped_date]]=0,"In Time","Slower")) -> Faster
A62: 10310 | B62: THEBI | C62: 8 | D62: 35328 | E62: 35356 | F62: 35335 | G62: 2 | H62: 17.52 | I62: The Big Cheese | J62: 89 Jefferson Way Suite 2 | K62: Portland | L62: OR | M62: 97201 | N62: USA | O62: =IF(northwind_orders[[#This Row],[required_date]]-northwind_orders[[#This Row],[shipped_date]]>0,"Faster",IF(northwind_orders[[#This Row],[required_date]]-northwind_orders[[#This Row],[shipped_date]]=0,"In Time","Slower")) -> Faster
A63: 10311 | B63: DUMON | C63: 1 | D63: 35328 | E63: 35342 | F63: 35334 | G63: 3 | H63: 24.69 | I63: Du monde entier | J63: 67, rue des Cinquante Otages | K63: Nantes | M63: 44000 | N63: France | O63: =IF(northwind_orders[[#This Row],[required_date]]-northwind_orders[[#This Row],[shipped_date]]>0,"Faster",IF(northwind_orders[[#This Row],[required_date]]-northwind_orders[[#This Row],[shipped_date]]=0,"In Time","Slower")) -> Faster
A64: 10312 | B64: WANDK | C64: 2 | D64: 35331 | E64: 35359 | F64: 35341 | G64: 2 | H64: 40.26 | I64: Die Wandernde Kuh | J64: Adenauerallee 900 | K64: Stuttgart | M64: 70563 | N64: Germany | O64: =IF(northwind_orders[[#This Row],[required_date]]-northwind_orders[[#This Row],[shipped_date]]>0,"Faster",IF(northwind_orders[[#This Row],[required_date]]-northwind_orders[[#This Row],[shipped_date]]=0,"In Time","Slower")) -> Faster
A65: 10313 | B65: QUICK | C65: 2 | D65: 35332 | E65: 35360 | F65: 35342 | G65: 2 | H65: 1.96 | I65: QUICK-Stop | J65: TaucherstraГџe 10 | K65: Cunewalde | M65: 01307 | N65: Germany | O65: =IF(northwind_orders[[#This Row],[required_date]]-northwind_orders[[#This Row],[shipped_date]]>0,"Faster",IF(northwind_orders[[#This Row],[required_date]]-northwind_orders[[#This Row],[shipped_date]]=0,"In Time","Slower")) -> Faster
A66: 10314 | B66: RATTC | C66: 1 | D66: 35333 | E66: 35361 | F66: 35342 | G66: 2 | H66: 74.16 | I66: Rattlesnake Canyon Grocery | J66: 2817 Milton Dr. | K66: Albuquerque | L66: NM | M66: 87110 | N66: USA | O66: =IF(northwind_orders[[#This Row],[required_date]]-northwind_orders[[#This Row],[shipped_date]]>0,"Faster",IF(northwind_orders[[#This Row],[required_date]]-northwind_orders[[#This Row],[shipped_date]]=0,"In Time","Slower")) -> Faster
A67: 10315 | B67: ISLAT | C67: 4 | D67: 35334 | E67: 35362 | F67: 35341 | G67: 2 | H67: 41.76 | I67: Island Trading | J67: Garden House Crowther Way | K67: Cowes | L67: Isle of Wight | M67: PO31 7PJ | N67: UK | O67: =IF(northwind_orders[[#This Row],[required_date]]-northwind_orders[[#This Row],[shipped_date]]>0,"Faster",IF(northwind_orders[[#This Row],[required_date]]-northwind_orders[[#This Row],[shipped_date]]=0,"In Time","Slower")) -> Faster
A68: 10316 | B68: RATTC | C68: 1 | D68: 35335 | E68: 35363 | F68: 35346 | G68: 3 | H68: 150.15 | I68: Rattlesnake Canyon Grocery | J68: 2817 Milton Dr. | K68: Albuquerque | L68: NM | M68: 87110 | N68: USA | O68: =IF(northwind_orders[[#This Row],[required_date]]-northwind_orders[[#This Row],[shipped_date]]>0,"Faster",IF(northwind_orders[[#This Row],[required_date]]-northwind_orders[[#This Row],[shipped_date]]=0,"In Time","Slower")) -> Faster
A69: 10317 | B69: LONEP | C69: 6 | D69: 35338 | E69: 35366 | F69: 35348 | G69: 1 | H69: 12.69 | I69: Lonesome Pine Restaurant | J69: 89 Chiaroscuro Rd. | K69: Portland | L69: OR | M69: 97219 | N69: USA | O69: =IF(northwind_orders[[#This Row],[required_date]]-northwind_orders[[#This Row],[shipped_date]]>0,"Faster",IF(northwind_orders[[#This Row],[required_date]]-northwind_orders[[#This Row],[shipped_date]]=0,"In Time","Slower")) -> Faster
A70: 10318 | B70: ISLAT | C70: 8 | D70: 35339 | E70: 35367 | F70: 35342 | G70: 2 | H70: 4.73 | I70: Island Trading | J70: Garden House Crowther Way | K70: Cowes | L70: Isle of Wight | M70: PO31 7PJ | N70: UK | O70: =IF(northwind_orders[[#This Row],[required_date]]-northwind_orders[[#This Row],[shipped_date]]>0,"Faster",IF(northwind_orders[[#This Row],[required_date]]-northwind_orders[[#This Row],[shipped_date]]=0,"In Time","Slower")) -> Faster
A71: 10319 | B71: TORTU | C71: 7 | D71: 35340 | E71: 35368 | F71: 35349 | G71: 3 | H71: 64.5 | I71: Tortuga Restaurante | J71: Avda. Azteca 123 | K71: MГ©xico D.F. | M71: 05033 | N71: Mexico | O71: =IF(northwind_orders[[#This Row],[required_date]]-northwind_orders[[#This Row],[shipped_date]]>0,"Faster",IF(northwind_orders[[#This Row],[required_date]]-northwind_orders[[#This Row],[shipped_date]]=0,"In Time","Slower")) -> Faster
A72: 10320 | B72: WARTH | C72: 5 | D72: 35341 | E72: 35355 | F72: 35356 | G72: 3 | H72: 34.57 | I72: Wartian Herkku | J72: Torikatu 38 | K72: Oulu | M72: 90110 | N72: Finland | O72: =IF(northwind_orders[[#This Row],[required_date]]-northwind_orders[[#This Row],[shipped_date]]>0,"Faster",IF(northwind_orders[[#This Row],[required_date]]-northwind_orders[[#This Row],[shipped_date]]=0,"In Time","Slower")) -> Slower
A73: 10321 | B73: ISLAT | C73: 3 | D73: 35341 | E73: 35369 | F73: 35349 | G73: 2 | H73: 3.43 | I73: Island Trading | J73: Garden House Crowther Way | K73: Cowes | L73: Isle of Wight | M73: PO31 7PJ | N73: UK | O73: =IF(northwind_orders[[#This Row],[required_date]]-northwind_orders[[#This Row],[shipped_date]]>0,"Faster",IF(northwind_orders[[#This Row],[required_date]]-northwind_orders[[#This Row],[shipped_date]]=0,"In Time","Slower")) -> Faster
A74: 10322 | B74: PERIC | C74: 7 | D74: 35342 | E74: 35370 | F74: 35361 | G74: 3 | H74: 0.4 | I74: Pericles Comidas clГЎsicas | J74: Calle Dr. Jorge Cash 321 | K74: MГ©xico D.F. | M74: 05033 | N74: Mexico | O74: =IF(northwind_orders[[#This Row],[required_date]]-northwind_orders[[#This Row],[shipped_date]]>0,"Faster",IF(northwind_orders[[#This Row],[required_date]]-northwind_orders[[#This Row],[shipped_date]]=0,"In Time","Slower")) -> Faster
A75: 10323 | B75: KOENE | C75: 4 | D75: 35345 | E75: 35373 | F75: 35352 | G75: 1 | H75: 4.88 | I75: KГ¶niglich Essen | J75: Maubelstr. 90 | K75: Brandenburg | M75: 14776 | N75: Germany | O75: =IF(northwind_orders[[#This Row],[required_date]]-northwind_orders[[#This Row],[shipped_date]]>0,"Faster",IF(northwind_orders[[#This Row],[required_date]]-northwind_orders[[#This Row],[shipped_date]]=0,"In Time","Slower")) -> Faster
A76: 10324 | B76: SAVEA | C76: 9 | D76: 35346 | E76: 35374 | F76: 35348 | G76: 1 | H76: 214.27 | I76: Save-a-lot Markets | J76: 187 Suffolk Ln. | K76: Boise | L76: ID | M76: 83720 | N76: USA | O76: =IF(northwind_orders[[#This Row],[required_date]]-northwind_orders[[#This Row],[shipped_date]]>0,"Faster",IF(northwind_orders[[#This Row],[required_date]]-northwind_orders[[#This Row],[shipped_date]]=0,"In Time","Slower")) -> Faster
A77: 10325 | B77: KOENE | C77: 1 | D77: 35347 | E77: 35361 | F77: 35352 | G77: 3 | H77: 64.86 | I77: KГ¶niglich Essen | J77: Maubelstr. 90 | K77: Brandenburg | M77: 14776 | N77: Germany | O77: =IF(northwind_orders[[#This Row],[required_date]]-northwind_orders[[#This Row],[shipped_date]]>0,"Faster",IF(northwind_orders[[#This Row],[required_date]]-northwind_orders[[#This Row],[shipped_date]]=0,"In Time","Slower")) -> Faster
A78: 10326 | B78: BOLID | C78: 4 | D78: 35348 | E78: 35376 | F78: 35352 | G78: 2 | H78: 77.92 | I78: BГіlido Comidas preparadas | J78: C/ Araquil, 67 | K78: Madrid | M78: 28023 | N78: Spain | O78: =IF(northwind_orders[[#This Row],[required_date]]-northwind_orders[[#This Row],[shipped_date]]>0,"Faster",IF(northwind_orders[[#This Row],[required_date]]-northwind_orders[[#This Row],[shipped_date]]=0,"In Time","Slower")) -> Faster
A79: 10327 | B79: FOLKO | C79: 2 | D79: 35349 | E79: 35377 | F79: 35352 | G79: 1 | H79: 63.36 | I79: Folk och fГ¤ HB | J79: Г…kergatan 24 | K79: BrГ¤cke | M79: S-844 67 | N79: Sweden | O79: =IF(northwind_orders[[#This Row],[required_date]]-northwind_orders[[#This Row],[shipped_date]]>0,"Faster",IF(northwind_orders[[#This Row],[required_date]]-northwind_orders[[#This Row],[shipped_date]]=0,"In Time","Slower")) -> Faster
A80: 10328 | B80: FURIB | C80: 4 | D80: 35352 | E80: 35380 | F80: 35355 | G80: 3 | H80: 87.03 | I80: Furia Bacalhau e Frutos do Mar | J80: Jardim das rosas n. 32 | K80: Lisboa | M80: 1675 | N80: Portugal | O80: =IF(northwind_orders[[#This Row],[required_date]]-northwind_orders[[#This Row],[shipped_date]]>0,"Faster",IF(northwind_orders[[#This Row],[required_date]]-northwind_orders[[#This Row],[shipped_date]]=0,"In Time","Slower")) -> Faster
A81: 10329 | B81: SPLIR | C81: 4 | D81: 35353 | E81: 35395 | F81: 35361 | G81: 2 | H81: 191.67 | I81: Split Rail Beer & Ale | J81: P.O. Box 555 | K81: Lander | L81: WY | M81: 82520 | N81: USA | O81: =IF(northwind_orders[[#This Row],[required_date]]-northwind_orders[[#This Row],[shipped_date]]>0,"Faster",IF(northwind_orders[[#This Row],[required_date]]-northwind_orders[[#This Row],[shipped_date]]=0,"In Time","Slower")) -> Faster
A82: 10330 | B82: LILAS | C82: 3 | D82: 35354 | E82: 35382 | F82: 35366 | G82: 1 | H82: 12.75 | I82: LILA-Supermercado | J82: Carrera 52 con Ave. BolГ­var #65-98 Llano Largo | K82: Barquisimeto | L82: Lara | M82: 3508 | N82: Venezuela | O82: =IF(northwind_orders[[#This Row],[required_date]]-northwind_orders[[#This Row],[shipped_date]]>0,"Faster",IF(northwind_orders[[#This Row],[required_date]]-northwind_orders[[#This Row],[shipped_date]]=0,"In Time","Slower")) -> Faster
A83: 10331 | B83: BONAP | C83: 9 | D83: 35354 | E83: 35396 | F83: 35359 | G83: 1 | H83: 10.19 | I83: Bon app' | J83: 12, rue des Bouchers | K83: Marseille | M83: 13008 | N83: France | O83: =IF(northwind_orders[[#This Row],[required_date]]-northwind_orders[[#This Row],[shipped_date]]>0,"Faster",IF(northwind_orders[[#This Row],[required_date]]-northwind_orders[[#This Row],[shipped_date]]=0,"In Time","Slower")) -> Faster
A84: 10332 | B84: MEREP | C84: 3 | D84: 35355 | E84: 35397 | F84: 35359 | G84: 2 | H84: 52.84 | I84: MГЁre Paillarde | J84: 43 rue St. Laurent | K84: MontrГ©al | L84: QuГ©bec | M84: H1J 1C3 | N84: Canada | O84: =IF(northwind_orders[[#This Row],[required_date]]-northwind_orders[[#This Row],[shipped_date]]>0,"Faster",IF(northwind_orders[[#This Row],[required_date]]-northwind_orders[[#This Row],[shipped_date]]=0,"In Time","Slower")) -> Faster
A85: 10333 | B85: WARTH | C85: 5 | D85: 35356 | E85: 35384 | F85: 35363 | G85: 3 | H85: 0.59 | I85: Wartian Herkku | J85: Torikatu 38 | K85: Oulu | M85: 90110 | N85: Finland | O85: =IF(northwind_orders[[#This Row],[required_date]]-northwind_orders[[#This Row],[shipped_date]]>0,"Faster",IF(northwind_orders[[#This Row],[required_date]]-northwind_orders[[#This Row],[shipped_date]]=0,"In Time","Slower")) -> Faster
A86: 10334 | B86: VICTE | C86: 8 | D86: 35359 | E86: 35387 | F86: 35366 | G86: 2 | H86: 8.56 | I86: Victuailles en stock | J86: 2, rue du Commerce | K86: Lyon | M86: 69004 | N86: France | O86: =IF(northwind_orders[[#This Row],[required_date]]-northwind_orders[[#This Row],[shipped_date]]>0,"Faster",IF(northwind_orders[[#This Row],[required_date]]-northwind_orders[[#This Row],[shipped_date]]=0,"In Time","Slower")) -> Faster
A87: 10336 | B87: PRINI | C87: 7 | D87: 35361 | E87: 35389 | F87: 35363 | G87: 2 | H87: 15.51 | I87: Princesa Isabel Vinhos | J87: Estrada da saГєde n. 58 | K87: Lisboa | M87: 1756 | N87: Portugal | O87: =IF(northwind_orders[[#This Row],[required_date]]-northwind_orders[[#This Row],[shipped_date]]>0,"Faster",IF(northwind_orders[[#This Row],[required_date]]-northwind_orders[[#This Row],[shipped_date]]=0,"In Time","Slower")) -> Faster
A88: 10337 | B88: FRANK | C88: 4 | D88: 35362 | E88: 35390 | F88: 35367 | G88: 3 | H88: 108.26 | I88: Frankenversand | J88: Berliner Platz 43 | K88: MГјnchen | M88: 80805 | N88: Germany | O88: =IF(northwind_orders[[#This Row],[required_date]]-northwind_orders[[#This Row],[shipped_date]]>0,"Faster",IF(northwind_orders[[#This Row],[required_date]]-northwind_orders[[#This Row],[shipped_date]]=0,"In Time","Slower")) -> Faster
A89: 10338 | B89: OLDWO | C89: 4 | D89: 35363 | E89: 35391 | F89: 35367 | G89: 3 | H89: 84.21 | I89: Old World Delicatessen | J89: 2743 Bering St. | K89: Anchorage | L89: AK | M89: 99508 | N89: USA | O89: =IF(northwind_orders[[#This Row],[required_date]]-northwind_orders[[#This Row],[shipped_date]]>0,"Faster",IF(northwind_orders[[#This Row],[required_date]]-northwind_orders[[#This Row],[shipped_date]]=0,"In Time","Slower")) -> Faster
A90: 10339 | B90: MEREP | C90: 2 | D90: 35366 | E90: 35394 | F90: 35373 | G90: 2 | H90: 15.66 | I90: MГЁre Paillarde | J90: 43 rue St. Laurent | K90: MontrГ©al | L90: QuГ©bec | M90: H1J 1C3 | N90: Canada | O90: =IF(northwind_orders[[#This Row],[required_date]]-northwind_orders[[#This Row],[shipped_date]]>0,"Faster",IF(northwind_orders[[#This Row],[required_date]]-northwind_orders[[#This Row],[shipped_date]]=0,"In Time","Slower")) -> Faster
A91: 10340 | B91: BONAP | C91: 1 | D91: 35367 | E91: 35395 | F91: 35377 | G91: 3 | H91: 166.31 | I91: Bon app' | J91: 12, rue des Bouchers | K91: Marseille | M91: 13008 | N91: France | O91: =IF(northwind_orders[[#This Row],[required_date]]-northwind_orders[[#This Row],[shipped_date]]>0,"Faster",IF(northwind_orders[[#This Row],[required_date]]-northwind_orders[[#This Row],[shipped_date]]=0,"In Time","Slower")) -> Faster
A92: 10341 | B92: SIMOB | C92: 7 | D92: 35367 | E92: 35395 | F92: 35374 | G92: 3 | H92: 26.78 | I92: Simons bistro | J92: VinbГ¦ltet 34 | K92: Kobenhavn | M92: 1734 | N92: Denmark | O92: =IF(northwind_orders[[#This Row],[required_date]]-northwind_orders[[#This Row],[shipped_date]]>0,"Faster",IF(northwind_orders[[#This Row],[required_date]]-northwind_orders[[#This Row],[shipped_date]]=0,"In Time","Slower")) -> Faster
A93: 10342 | B93: FRANK | C93: 4 | D93: 35368 | E93: 35382 | F93: 35373 | G93: 2 | H93: 54.83 | I93: Frankenversand | J93: Berliner Platz 43 | K93: MГјnchen | M93: 80805 | N93: Germany | O93: =IF(northwind_orders[[#This Row],[required_date]]-northwind_orders[[#This Row],[shipped_date]]>0,"Faster",IF(northwind_orders[[#This Row],[required_date]]-northwind_orders[[#This Row],[shipped_date]]=0,"In Time","Slower")) -> Faster
A94: 10343 | B94: LEHMS | C94: 4 | D94: 35369 | E94: 35397 | F94: 35375 | G94: 1 | H94: 110.37 | I94: Lehmanns Marktstand | J94: Magazinweg 7 | K94: Frankfurt a.M. | M94: 60528 | N94: Germany | O94: =IF(northwind_orders[[#This Row],[required_date]]-northwind_orders[[#This Row],[shipped_date]]>0,"Faster",IF(northwind_orders[[#This Row],[required_date]]-northwind_orders[[#This Row],[shipped_date]]=0,"In Time","Slower")) -> Faster
A95: 10344 | B95: WHITC | C95: 4 | D95: 35370 | E95: 35398 | F95: 35374 | G95: 2 | H95: 23.29 | I95: White Clover Markets | J95: 1029 - 12th Ave. S. | K95: Seattle | L95: WA | M95: 98124 | N95: USA | O95: =IF(northwind_orders[[#This Row],[required_date]]-northwind_orders[[#This Row],[shipped_date]]>0,"Faster",IF(northwind_orders[[#This Row],[required_date]]-northwind_orders[[#This Row],[shipped_date]]=0,"In Time","Slower")) -> Faster
A96: 10345 | B96: QUICK | C96: 2 | D96: 35373 | E96: 35401 | F96: 35380 | G96: 2 | H96: 249.06 | I96: QUICK-Stop | J96: TaucherstraГџe 10 | K96: Cunewalde | M96: 01307 | N96: Germany | O96: =IF(northwind_orders[[#This Row],[required_date]]-northwind_orders[[#This Row],[shipped_date]]>0,"Faster",IF(northwind_orders[[#This Row],[required_date]]-northwind_orders[[#This Row],[shipped_date]]=0,"In Time","Slower")) -> Faster
A97: 10346 | B97: RATTC | C97: 3 | D97: 35374 | E97: 35416 | F97: 35377 | G97: 3 | H97: 142.08 | I97: Rattlesnake Canyon Grocery | J97: 2817 Milton Dr. | K97: Albuquerque | L97: NM | M97: 87110 | N97: USA | O97: =IF(northwind_orders[[#This Row],[required_date]]-northwind_orders[[#This Row],[shipped_date]]>0,"Faster",IF(northwind_orders[[#This Row],[required_date]]-northwind_orders[[#This Row],[shipped_date]]=0,"In Time","Slower")) -> Faster
A98: 10347 | B98: FAMIA | C98: 4 | D98: 35375 | E98: 35403 | F98: 35377 | G98: 3 | H98: 3.1 | I98: Familia Arquibaldo | J98: Rua OrГіs, 92 | K98: Sao Paulo | L98: SP | M98: 05442-030 | N98: Brazil | O98: =IF(northwind_orders[[#This Row],[required_date]]-northwind_orders[[#This Row],[shipped_date]]>0,"Faster",IF(northwind_orders[[#This Row],[required_date]]-northwind_orders[[#This Row],[shipped_date]]=0,"In Time","Slower")) -> Faster
A99: 10348 | B99: WANDK | C99: 4 | D99: 35376 | E99: 35404 | F99: 35384 | G99: 2 | H99: 0.78 | I99: Die Wandernde Kuh | J99: Adenauerallee 900 | K99: Stuttgart | M99: 70563 | N99: Germany | O99: =IF(northwind_orders[[#This Row],[required_date]]-northwind_orders[[#This Row],[shipped_date]]>0,"Faster",IF(northwind_orders[[#This Row],[required_date]]-northwind_orders[[#This Row],[shipped_date]]=0,"In Time","Slower")) -> Faster
A100: 10349 | B100: SPLIR | C100: 7 | D100: 35377 | E100: 35405 | F100: 35384 | G100: 1 | H100: 8.63 | I100: Split Rail Beer & Ale | J100: P.O. Box 555 | K100: Lander | L100: WY | M100: 82520 | N100: USA | O100: =IF(northwind_orders[[#This Row],[required_date]]-northwind_orders[[#This Row],[shipped_date]]>0,"Faster",IF(northwind_orders[[#This Row],[required_date]]-northwind_orders[[#This Row],[shipped_date]]=0,"In Time","Slower")) -> Faster
...

Sheet northwind_order_details
A1: order_id | B1: product_id | C1: unit_price | D1: quantity | E1: discount | F1: country | G1: Employee Id | H1: purchase amount | I1: discount amount | J1: Revenue | K1: discount check | L1: Type of Revenue | M1: Price reconciliation | O1: Country | P1: Total Revenue | Q1: Average purchase | R1: Number of orders | S1: Discount Leakage | T1: High | U1: Medium | V1: Low | W1: Match | X1: Mismatch
A2: 10248 | B2: 11 | C2: 14 | D2: 12 | E2: 0 | F2: =_xlfn.XLOOKUP(northwind_order_details[[#This Row],[order_id]],northwind_orders[order_id],northwind_orders[ship_country]) -> France | G2: =INDEX(northwind_orders[],MATCH(northwind_order_details[[#This Row],[order_id]], northwind_orders[order_id], 0), MATCH("employee_id", northwind_orders[#Headers], 0)) -> 5 | H2: =northwind_order_details[[#This Row],[unit_price]]*northwind_order_details[[#This Row],[quantity]] -> 168 | I2: =northwind_order_details[[#This Row],[purchase amount]]*northwind_order_details[[#This Row],[discount]] -> 0 | J2: =northwind_order_details[[#This Row],[purchase amount]]-northwind_order_details[[#This Row],[discount amount]] -> 168 | K2: =IF(northwind_order_details[[#This Row],[discount amount]]>0,"Yes","No") -> No | L2: =IF(northwind_order_details[[#This Row],[Revenue]]>1000,"High",IF(northwind_order_details[[#This Row],[Revenue]]>300,"Medium","Low")) -> Low | M2: =IF(northwind_order_details[[#This Row],[unit_price]]=_xlfn.XLOOKUP(northwind_order_details[[#This Row],[product_id]],'Price Validation'!$D$2:$D$78,'Price Validation'!$E$2:$E$78),"Match","Mismatch") -> Mismatch | O2: {=_xlfn.UNIQUE(northwind_order_details[country])} -> France | P2: =SUMIF(northwind_order_details[country],$O2,northwind_order_details[Revenue]) -> 80529.572 | Q2: =AVERAGEIF(northwind_order_details[country],$O2,northwind_order_details[Revenue]) -> 447.38651 | R2: =COUNTIF(northwind_order_details[country],O2) -> 180 | S2: =ROUND(SUMIF(northwind_order_details[country],$O2,northwind_order_details[discount amount]),2) -> 3867.19 | T2: =COUNTIFS(northwind_order_details[Type of Revenue],T$1,northwind_order_details[country],$O2) -> 21 | U2: =COUNTIFS(northwind_order_details[Type of Revenue],U$1,northwind_order_details[country],$O2) -> 58 | V2: =COUNTIFS(northwind_order_details[Type of Revenue],V$1,northwind_order_details[country],$O2) -> 101 | W2: =COUNTIFS(northwind_order_details[Price reconciliation],"Match",northwind_order_details[country],$O2) -> 53 | X2: =COUNTIFS(northwind_order_details[Price reconciliation],"Mismatch",northwind_order_details[country],$O2) -> 127
A3: 10248 | B3: 42 | C3: 9.8 | D3: 10 | E3: 0 | F3: =_xlfn.XLOOKUP(northwind_order_details[[#This Row],[order_id]],northwind_orders[order_id],northwind_orders[ship_country]) -> France | G3: =INDEX(northwind_orders[],MATCH(northwind_order_details[[#This Row],[order_id]], northwind_orders[order_id], 0), MATCH("employee_id", northwind_orders[#Headers], 0)) -> 5 | H3: =northwind_order_details[[#This Row],[unit_price]]*northwind_order_details[[#This Row],[quantity]] -> 98 | I3: =northwind_order_details[[#This Row],[purchase amount]]*northwind_order_details[[#This Row],[discount]] -> 0 | J3: =northwind_order_details[[#This Row],[purchase amount]]-northwind_order_details[[#This Row],[discount amount]] -> 98 | K3: =IF(northwind_order_details[[#This Row],[discount amount]]>0,"Yes","No") -> No | L3: =IF(northwind_order_details[[#This Row],[Revenue]]>1000,"High",IF(northwind_order_details[[#This Row],[Revenue]]>300,"Medium","Low")) -> Low | M3: =IF(northwind_order_details[[#This Row],[unit_price]]=_xlfn.XLOOKUP(northwind_order_details[[#This Row],[product_id]],'Price Validation'!$D$2:$D$78,'Price Validation'!$E$2:$E$78),"Match","Mismatch") -> Mismatch | O3: Germany | P3: =SUMIF(northwind_order_details[country],$O3,northwind_order_details[Revenue]) -> 227796.66 | Q3: =AVERAGEIF(northwind_order_details[country],$O3,northwind_order_details[Revenue]) -> 709.64691 | R3: =COUNTIF(northwind_order_details[country],O3) -> 321 | S3: =ROUND(SUMIF(northwind_order_details[country],$O3,northwind_order_details[discount amount]),2) -> 14112.47 | T3: =COUNTIFS(northwind_order_details[Type of Revenue],T$1,northwind_order_details[country],$O3) -> 61 | U3: =COUNTIFS(northwind_order_details[Type of Revenue],U$1,northwind_order_details[country],$O3) -> 142 | V3: =COUNTIFS(northwind_order_details[Type of Revenue],V$1,northwind_order_details[country],$O3) -> 118 | W3: =COUNTIFS(northwind_order_details[Price reconciliation],"Match",northwind_order_details[country],$O3) -> 108 | X3: =COUNTIFS(northwind_order_details[Price reconciliation],"Mismatch",northwind_order_details[country],$O3) -> 213
A4: 10248 | B4: 72 | C4: 34.8 | D4: 5 | E4: 0 | F4: =_xlfn.XLOOKUP(northwind_order_details[[#This Row],[order_id]],northwind_orders[order_id],northwind_orders[ship_country]) -> France | G4: =INDEX(northwind_orders[],MATCH(northwind_order_details[[#This Row],[order_id]], northwind_orders[order_id], 0), MATCH("employee_id", northwind_orders[#Headers], 0)) -> 5 | H4: =northwind_order_details[[#This Row],[unit_price]]*northwind_order_details[[#This Row],[quantity]] -> 174 | I4: =northwind_order_details[[#This Row],[purchase amount]]*northwind_order_details[[#This Row],[discount]] -> 0 | J4: =northwind_order_details[[#This Row],[purchase amount]]-northwind_order_details[[#This Row],[discount amount]] -> 174 | K4: =IF(northwind_order_details[[#This Row],[discount amount]]>0,"Yes","No") -> No | L4: =IF(northwind_order_details[[#This Row],[Revenue]]>1000,"High",IF(northwind_order_details[[#This Row],[Revenue]]>300,"Medium","Low")) -> Low | M4: =IF(northwind_order_details[[#This Row],[unit_price]]=_xlfn.XLOOKUP(northwind_order_details[[#This Row],[product_id]],'Price Validation'!$D$2:$D$78,'Price Validation'!$E$2:$E$78),"Match","Mismatch") -> Match | O4: Brazil | P4: =SUMIF(northwind_order_details[country],$O4,northwind_order_details[Revenue]) -> 103060.7 | Q4: =AVERAGEIF(northwind_order_details[country],$O4,northwind_order_details[Revenue]) -> 523.15074 | R4: =COUNTIF(northwind_order_details[country],O4) -> 197 | S4: =ROUND(SUMIF(northwind_order_details[country],$O4,northwind_order_details[discount amount]),2) -> 7684.98 | T4: =COUNTIFS(northwind_order_details[Type of Revenue],T$1,northwind_order_details[country],$O4) -> 21 | U4: =COUNTIFS(northwind_order_details[Type of Revenue],U$1,northwind_order_details[country],$O4) -> 73 | V4: =COUNTIFS(northwind_order_details[Type of Revenue],V$1,northwind_order_details[country],$O4) -> 103 | W4: =COUNTIFS(northwind_order_details[Price reconciliation],"Match",northwind_order_details[country],$O4) -> 62 | X4: =COUNTIFS(northwind_order_details[Price reconciliation],"Mismatch",northwind_order_details[country],$O4) -> 135
A5: 10249 | B5: 14 | C5: 18.6 | D5: 9 | E5: 0 | F5: =_xlfn.XLOOKUP(northwind_order_details[[#This Row],[order_id]],northwind_orders[order_id],northwind_orders[ship_country]) -> Germany | G5: =INDEX(northwind_orders[],MATCH(northwind_order_details[[#This Row],[order_id]], northwind_orders[order_id], 0), MATCH("employee_id", northwind_orders[#Headers], 0)) -> 6 | H5: =northwind_order_details[[#This Row],[unit_price]]*northwind_order_details[[#This Row],[quantity]] -> 167.4 | I5: =northwind_order_details[[#This Row],[purchase amount]]*northwind_order_details[[#This Row],[discount]] -> 0 | J5: =northwind_order_details[[#This Row],[purchase amount]]-northwind_order_details[[#This Row],[discount amount]] -> 167.4 | K5: =IF(northwind_order_details[[#This Row],[discount amount]]>0,"Yes","No") -> No | L5: =IF(northwind_order_details[[#This Row],[Revenue]]>1000,"High",IF(northwind_order_details[[#This Row],[Revenue]]>300,"Medium","Low")) -> Low | M5: =IF(northwind_order_details[[#This Row],[unit_price]]=_xlfn.XLOOKUP(northwind_order_details[[#This Row],[product_id]],'Price Validation'!$D$2:$D$78,'Price Validation'!$E$2:$E$78),"Match","Mismatch") -> Mismatch | O5: Belgium | P5: =SUMIF(northwind_order_details[country],$O5,northwind_order_details[Revenue]) -> 33824.855 | Q5: =AVERAGEIF(northwind_order_details[country],$O5,northwind_order_details[Revenue]) -> 604.01527 | R5: =COUNTIF(northwind_order_details[country],O5) -> 56 | S5: =ROUND(SUMIF(northwind_order_details[country],$O5,northwind_order_details[discount amount]),2) -> 1310.13 | T5: =COUNTIFS(northwind_order_details[Type of Revenue],T$1,northwind_order_details[country],$O5) -> 12 | U5: =COUNTIFS(northwind_order_details[Type of Revenue],U$1,northwind_order_details[country],$O5) -> 26 | V5: =COUNTIFS(northwind_order_details[Type of Revenue],V$1,northwind_order_details[country],$O5) -> 18 | W5: =COUNTIFS(northwind_order_details[Price reconciliation],"Match",northwind_order_details[country],$O5) -> 14 | X5: =COUNTIFS(northwind_order_details[Price reconciliation],"Mismatch",northwind_order_details[country],$O5) -> 42
A6: 10249 | B6: 51 | C6: 42.4 | D6: 40 | E6: 0 | F6: =_xlfn.XLOOKUP(northwind_order_details[[#This Row],[order_id]],northwind_orders[order_id],northwind_orders[ship_country]) -> Germany | G6: =INDEX(northwind_orders[],MATCH(northwind_order_details[[#This Row],[order_id]], northwind_orders[order_id], 0), MATCH("employee_id", northwind_orders[#Headers], 0)) -> 6 | H6: =northwind_order_details[[#This Row],[unit_price]]*northwind_order_details[[#This Row],[quantity]] -> 1696 | I6: =northwind_order_details[[#This Row],[purchase amount]]*northwind_order_details[[#This Row],[discount]] -> 0 | J6: =northwind_order_details[[#This Row],[purchase amount]]-northwind_order_details[[#This Row],[discount amount]] -> 1696 | K6: =IF(northwind_order_details[[#This Row],[discount amount]]>0,"Yes","No") -> No | L6: =IF(northwind_order_details[[#This Row],[Revenue]]>1000,"High",IF(northwind_order_details[[#This Row],[Revenue]]>300,"Medium","Low")) -> High | M6: =IF(northwind_order_details[[#This Row],[unit_price]]=_xlfn.XLOOKUP(northwind_order_details[[#This Row],[product_id]],'Price Validation'!$D$2:$D$78,'Price Validation'!$E$2:$E$78),"Match","Mismatch") -> Mismatch | O6: Switzerland | P6: =SUMIF(northwind_order_details[country],$O6,northwind_order_details[Revenue]) -> 31194.559 | Q6: =AVERAGEIF(northwind_order_details[country],$O6,northwind_order_details[Revenue]) -> 636.62365 | R6: =COUNTIF(northwind_order_details[country],O6) -> 49 | S6: =ROUND(SUMIF(northwind_order_details[country],$O6,northwind_order_details[discount amount]),2) -> 1138.94 | T6: =COUNTIFS(northwind_order_details[Type of Revenue],T$1,northwind_order_details[country],$O6) -> 9 | U6: =COUNTIFS(northwind_order_details[Type of Revenue],U$1,northwind_order_details[country],$O6) -> 26 | V6: =COUNTIFS(northwind_order_details[Type of Revenue],V$1,northwind_order_details[country],$O6) -> 14 | W6: =COUNTIFS(northwind_order_details[Price reconciliation],"Match",northwind_order_details[country],$O6) -> 18 | X6: =COUNTIFS(northwind_order_details[Price reconciliation],"Mismatch",northwind_order_details[country],$O6) -> 31
A7: 10250 | B7: 41 | C7: 7.7 | D7: 10 | E7: 0 | F7: =_xlfn.XLOOKUP(northwind_order_details[[#This Row],[order_id]],northwind_orders[order_id],northwind_orders[ship_country]) -> Brazil | G7: =INDEX(northwind_orders[],MATCH(northwind_order_details[[#This Row],[order_id]], northwind_orders[order_id], 0), MATCH("employee_id", northwind_orders[#Headers], 0)) -> 4 | H7: =northwind_order_details[[#This Row],[unit_price]]*northwind_order_details[[#This Row],[quantity]] -> 77 | I7: =northwind_order_details[[#This Row],[purchase amount]]*northwind_order_details[[#This Row],[discount]] -> 0 | J7: =northwind_order_details[[#This Row],[purchase amount]]-northwind_order_details[[#This Row],[discount amount]] -> 77 | K7: =IF(northwind_order_details[[#This Row],[discount amount]]>0,"Yes","No") -> No | L7: =IF(northwind_order_details[[#This Row],[Revenue]]>1000,"High",IF(northwind_order_details[[#This Row],[Revenue]]>300,"Medium","Low")) -> Low | M7: =IF(northwind_order_details[[#This Row],[unit_price]]=_xlfn.XLOOKUP(northwind_order_details[[#This Row],[product_id]],'Price Validation'!$D$2:$D$78,'Price Validation'!$E$2:$E$78),"Match","Mismatch") -> Mismatch | O7: Venezuela | P7: =SUMIF(northwind_order_details[country],$O7,northwind_order_details[Revenue]) -> 53046.709 | Q7: =AVERAGEIF(northwind_order_details[country],$O7,northwind_order_details[Revenue]) -> 482.24281 | R7: =COUNTIF(northwind_order_details[country],O7) -> 110 | S7: =ROUND(SUMIF(northwind_order_details[country],$O7,northwind_order_details[discount amount]),2) -> 3915.62 | T7: =COUNTIFS(northwind_order_details[Type of Revenue],T$1,northwind_order_details[country],$O7) -> 11 | U7: =COUNTIFS(northwind_order_details[Type of Revenue],U$1,northwind_order_details[country],$O7) -> 45 | V7: =COUNTIFS(northwind_order_details[Type of Revenue],V$1,northwind_order_details[country],$O7) -> 54 | W7: =COUNTIFS(northwind_order_details[Price reconciliation],"Match",northwind_order_details[country],$O7) -> 37 | X7: =COUNTIFS(northwind_order_details[Price reconciliation],"Mismatch",northwind_order_details[country],$O7) -> 73
A8: 10250 | B8: 51 | C8: 42.4 | D8: 35 | E8: 0.15 | F8: =_xlfn.XLOOKUP(northwind_order_details[[#This Row],[order_id]],northwind_orders[order_id],northwind_orders[ship_country]) -> Brazil | G8: =INDEX(northwind_orders[],MATCH(northwind_order_details[[#This Row],[order_id]], northwind_orders[order_id], 0), MATCH("employee_id", northwind_orders[#Headers], 0)) -> 4 | H8: =northwind_order_details[[#This Row],[unit_price]]*northwind_order_details[[#This Row],[quantity]] -> 1484 | I8: =northwind_order_details[[#This Row],[purchase amount]]*northwind_order_details[[#This Row],[discount]] -> 222.6 | J8: =northwind_order_details[[#This Row],[purchase amount]]-northwind_order_details[[#This Row],[discount amount]] -> 1261.4 | K8: =IF(northwind_order_details[[#This Row],[discount amount]]>0,"Yes","No") -> Yes | L8: =IF(northwind_order_details[[#This Row],[Revenue]]>1000,"High",IF(northwind_order_details[[#This Row],[Revenue]]>300,"Medium","Low")) -> High | M8: =IF(northwind_order_details[[#This Row],[unit_price]]=_xlfn.XLOOKUP(northwind_order_details[[#This Row],[product_id]],'Price Validation'!$D$2:$D$78,'Price Validation'!$E$2:$E$78),"Match","Mismatch") -> Mismatch | O8: Austria | P8: =SUMIF(northwind_order_details[country],$O8,northwind_order_details[Revenue]) -> 118104.94 | Q8: =AVERAGEIF(northwind_order_details[country],$O8,northwind_order_details[Revenue]) -> 1000.8893 | R8: =COUNTIF(northwind_order_details[country],O8) -> 118 | S8: =ROUND(SUMIF(northwind_order_details[country],$O8,northwind_order_details[discount amount]),2) -> 11270.19 | T8: =COUNTIFS(northwind_order_details[Type of Revenue],T$1,northwind_order_details[country],$O8) -> 38 | U8: =COUNTIFS(northwind_order_details[Type of Revenue],U$1,northwind_order_details[country],$O8) -> 51 | V8: =COUNTIFS(northwind_order_details[Type of Revenue],V$1,northwind_order_details[country],$O8) -> 29 | W8: =COUNTIFS(northwind_order_details[Price reconciliation],"Match",northwind_order_details[country],$O8) -> 37 | X8: =COUNTIFS(northwind_order_details[Price reconciliation],"Mismatch",northwind_order_details[country],$O8) -> 81
A9: 10250 | B9: 65 | C9: 16.8 | D9: 15 | E9: 0.15 | F9: =_xlfn.XLOOKUP(northwind_order_details[[#This Row],[order_id]],northwind_orders[order_id],northwind_orders[ship_country]) -> Brazil | G9: =INDEX(northwind_orders[],MATCH(northwind_order_details[[#This Row],[order_id]], northwind_orders[order_id], 0), MATCH("employee_id", northwind_orders[#Headers], 0)) -> 4 | H9: =northwind_order_details[[#This Row],[unit_price]]*northwind_order_details[[#This Row],[quantity]] -> 252 | I9: =northwind_order_details[[#This Row],[purchase amount]]*northwind_order_details[[#This Row],[discount]] -> 37.8 | J9: =northwind_order_details[[#This Row],[purchase amount]]-northwind_order_details[[#This Row],[discount amount]] -> 214.2 | K9: =IF(northwind_order_details[[#This Row],[discount amount]]>0,"Yes","No") -> Yes | L9: =IF(northwind_order_details[[#This Row],[Revenue]]>1000,"High",IF(northwind_order_details[[#This Row],[Revenue]]>300,"Medium","Low")) -> Low | M9: =IF(northwind_order_details[[#This Row],[unit_price]]=_xlfn.XLOOKUP(northwind_order_details[[#This Row],[product_id]],'Price Validation'!$D$2:$D$78,'Price Validation'!$E$2:$E$78),"Match","Mismatch") -> Mismatch | O9: Mexico | P9: =SUMIF(northwind_order_details[country],$O9,northwind_order_details[Revenue]) -> 23282.078 | Q9: =AVERAGEIF(northwind_order_details[country],$O9,northwind_order_details[Revenue]) -> 332.60111 | R9: =COUNTIF(northwind_order_details[country],O9) -> 70 | S9: =ROUND(SUMIF(northwind_order_details[country],$O9,northwind_order_details[discount amount]),2) -> 491.37 | T9: =COUNTIFS(northwind_order_details[Type of Revenue],T$1,northwind_order_details[country],$O9) -> 2 | U9: =COUNTIFS(northwind_order_details[Type of Revenue],U$1,northwind_order_details[country],$O9) -> 27 | V9: =COUNTIFS(northwind_order_details[Type of Revenue],V$1,northwind_order_details[country],$O9) -> 41 | W9: =COUNTIFS(northwind_order_details[Price reconciliation],"Match",northwind_order_details[country],$O9) -> 23 | X9: =COUNTIFS(northwind_order_details[Price reconciliation],"Mismatch",northwind_order_details[country],$O9) -> 47
A10: 10251 | B10: 22 | C10: 16.8 | D10: 6 | E10: 0.05 | F10: =_xlfn.XLOOKUP(northwind_order_details[[#This Row],[order_id]],northwind_orders[order_id],northwind_orders[ship_country]) -> France | G10: =INDEX(northwind_orders[],MATCH(northwind_order_details[[#This Row],[order_id]], northwind_orders[order_id], 0), MATCH("employee_id", northwind_orders[#Headers], 0)) -> 3 | H10: =northwind_order_details[[#This Row],[unit_price]]*northwind_order_details[[#This Row],[quantity]] -> 100.8 | I10: =northwind_order_details[[#This Row],[purchase amount]]*northwind_order_details[[#This Row],[discount]] -> 5.04 | J10: =northwind_order_details[[#This Row],[purchase amount]]-northwind_order_details[[#This Row],[discount amount]] -> 95.76 | K10: =IF(northwind_order_details[[#This Row],[discount amount]]>0,"Yes","No") -> Yes | L10: =IF(northwind_order_details[[#This Row],[Revenue]]>1000,"High",IF(northwind_order_details[[#This Row],[Revenue]]>300,"Medium","Low")) -> Low | M10: =IF(northwind_order_details[[#This Row],[unit_price]]=_xlfn.XLOOKUP(northwind_order_details[[#This Row],[product_id]],'Price Validation'!$D$2:$D$78,'Price Validation'!$E$2:$E$78),"Match","Mismatch") -> Mismatch | O10: USA | P10: =SUMIF(northwind_order_details[country],$O10,northwind_order_details[Revenue]) -> 243618.89 | Q10: =AVERAGEIF(northwind_order_details[country],$O10,northwind_order_details[Revenue]) -> 749.59658 | R10: =COUNTIF(northwind_order_details[country],O10) -> 325 | S10: =ROUND(SUMIF(northwind_order_details[country],$O10,northwind_order_details[discount amount]),2) -> 17863.49 | T10: =COUNTIFS(northwind_order_details[Type of Revenue],T$1,northwind_order_details[country],$O10) -> 67 | U10: =COUNTIFS(northwind_order_details[Type of Revenue],U$1,northwind_order_details[country],$O10) -> 133 | V10: =COUNTIFS(northwind_order_details[Type of Revenue],V$1,northwind_order_details[country],$O10) -> 125 | W10: =COUNTIFS(northwind_order_details[Price reconciliation],"Match",northwind_order_details[country],$O10) -> 126 | X10: =COUNTIFS(northwind_order_details[Price reconciliation],"Mismatch",northwind_order_details[country],$O10) -> 199
A11: 10251 | B11: 57 | C11: 15.6 | D11: 15 | E11: 0.05 | F11: =_xlfn.XLOOKUP(northwind_order_details[[#This Row],[order_id]],northwind_orders[order_id],northwind_orders[ship_country]) -> France | G11: =INDEX(northwind_orders[],MATCH(northwind_order_details[[#This Row],[order_id]], northwind_orders[order_id], 0), MATCH("employee_id", northwind_orders[#Headers], 0)) -> 3 | H11: =northwind_order_details[[#This Row],[unit_price]]*northwind_order_details[[#This Row],[quantity]] -> 234 | I11: =northwind_order_details[[#This Row],[purchase amount]]*northwind_order_details[[#This Row],[discount]] -> 11.7 | J11: =northwind_order_details[[#This Row],[purchase amount]]-northwind_order_details[[#This Row],[discount amount]] -> 222.3 | K11: =IF(northwind_order_details[[#This Row],[discount amount]]>0,"Yes","No") -> Yes | L11: =IF(northwind_order_details[[#This Row],[Revenue]]>1000,"High",IF(northwind_order_details[[#This Row],[Revenue]]>300,"Medium","Low")) -> Low | M11: =IF(northwind_order_details[[#This Row],[unit_price]]=_xlfn.XLOOKUP(northwind_order_details[[#This Row],[product_id]],'Price Validation'!$D$2:$D$78,'Price Validation'!$E$2:$E$78),"Match","Mismatch") -> Mismatch | O11: Sweden | P11: =SUMIF(northwind_order_details[country],$O11,northwind_order_details[Revenue]) -> 54495.14 | Q11: =AVERAGEIF(northwind_order_details[country],$O11,northwind_order_details[Revenue]) -> 561.80557 | R11: =COUNTIF(northwind_order_details[country],O11) -> 97 | S11: =ROUND(SUMIF(northwind_order_details[country],$O11,northwind_order_details[discount amount]),2) -> 5028.56 | T11: =COUNTIFS(northwind_order_details[Type of Revenue],T$1,northwind_order_details[country],$O11) -> 11 | U11: =COUNTIFS(northwind_order_details[Type of Revenue],U$1,northwind_order_details[country],$O11) -> 34 | V11: =COUNTIFS(northwind_order_details[Type of Revenue],V$1,northwind_order_details[country],$O11) -> 52 | W11: =COUNTIFS(northwind_order_details[Price reconciliation],"Match",northwind_order_details[country],$O11) -> 36 | X11: =COUNTIFS(northwind_order_details[Price reconciliation],"Mismatch",northwind_order_details[country],$O11) -> 61
A12: 10251 | B12: 65 | C12: 16.8 | D12: 20 | E12: 0 | F12: =_xlfn.XLOOKUP(northwind_order_details[[#This Row],[order_id]],northwind_orders[order_id],northwind_orders[ship_country]) -> France | G12: =INDEX(northwind_orders[],MATCH(northwind_order_details[[#This Row],[order_id]], northwind_orders[order_id], 0), MATCH("employee_id", northwind_orders[#Headers], 0)) -> 3 | H12: =northwind_order_details[[#This Row],[unit_price]]*northwind_order_details[[#This Row],[quantity]] -> 336 | I12: =northwind_order_details[[#This Row],[purchase amount]]*northwind_order_details[[#This Row],[discount]] -> 0 | J12: =northwind_order_details[[#This Row],[purchase amount]]-northwind_order_details[[#This Row],[discount amount]] -> 336 | K12: =IF(northwind_order_details[[#This Row],[discount amount]]>0,"Yes","No") -> No | L12: =IF(northwind_order_details[[#This Row],[Revenue]]>1000,"High",IF(northwind_order_details[[#This Row],[Revenue]]>300,"Medium","Low")) -> Medium | M12: =IF(northwind_order_details[[#This Row],[unit_price]]=_xlfn.XLOOKUP(northwind_order_details[[#This Row],[product_id]],'Price Validation'!$D$2:$D$78,'Price Validation'!$E$2:$E$78),"Match","Mismatch") -> Mismatch | O12: Finland | P12: =SUMIF(northwind_order_details[country],$O12,northwind_order_details[Revenue]) -> 18810.052 | Q12: =AVERAGEIF(northwind_order_details[country],$O12,northwind_order_details[Revenue]) -> 348.33431 | R12: =COUNTIF(northwind_order_details[country],O12) -> 54 | S12: =ROUND(SUMIF(northwind_order_details[country],$O12,northwind_order_details[discount amount]),2) -> 968.4 | T12: =COUNTIFS(northwind_order_details[Type of Revenue],T$1,northwind_order_details[country],$O12) -> 3 | U12: =COUNTIFS(northwind_order_details[Type of Revenue],U$1,northwind_order_details[country],$O12) -> 22 | V12: =COUNTIFS(northwind_order_details[Type of Revenue],V$1,northwind_order_details[country],$O12) -> 29 | W12: =COUNTIFS(northwind_order_details[Price reconciliation],"Match",northwind_order_details[country],$O12) -> 14 | X12: =COUNTIFS(northwind_order_details[Price reconciliation],"Mismatch",northwind_order_details[country],$O12) -> 40
A13: 10252 | B13: 20 | C13: 64.8 | D13: 40 | E13: 0.05 | F13: =_xlfn.XLOOKUP(northwind_order_details[[#This Row],[order_id]],northwind_orders[order_id],northwind_orders[ship_country]) -> Belgium | G13: =INDEX(northwind_orders[],MATCH(northwind_order_details[[#This Row],[order_id]], northwind_orders[order_id], 0), MATCH("employee_id", northwind_orders[#Headers], 0)) -> 4 | H13: =northwind_order_details[[#This Row],[unit_price]]*northwind_order_details[[#This Row],[quantity]] -> 2592 | I13: =northwind_order_details[[#This Row],[purchase amount]]*northwind_order_details[[#This Row],[discount]] -> 129.6 | J13: =northwind_order_details[[#This Row],[purchase amount]]-northwind_order_details[[#This Row],[discount amount]] -> 2462.4 | K13: =IF(northwind_order_details[[#This Row],[discount amount]]>0,"Yes","No") -> Yes | L13: =IF(northwind_order_details[[#This Row],[Revenue]]>1000,"High",IF(northwind_order_details[[#This Row],[Revenue]]>300,"Medium","Low")) -> High | M13: =IF(northwind_order_details[[#This Row],[unit_price]]=_xlfn.XLOOKUP(northwind_order_details[[#This Row],[product_id]],'Price Validation'!$D$2:$D$78,'Price Validation'!$E$2:$E$78),"Match","Mismatch") -> Mismatch | O13: Italy | P13: =SUMIF(northwind_order_details[country],$O13,northwind_order_details[Revenue]) -> 15363.755 | Q13: =AVERAGEIF(northwind_order_details[country],$O13,northwind_order_details[Revenue]) -> 301.2501 | R13: =COUNTIF(northwind_order_details[country],O13) -> 51 | S13: =ROUND(SUMIF(northwind_order_details[country],$O13,northwind_order_details[discount amount]),2) -> 833.4 | T13: =COUNTIFS(northwind_order_details[Type of Revenue],T$1,northwind_order_details[country],$O13) -> 1 | U13: =COUNTIFS(northwind_order_details[Type of Revenue],U$1,northwind_order_details[country],$O13) -> 19 | V13: =COUNTIFS(northwind_order_details[Type of Revenue],V$1,northwind_order_details[country],$O13) -> 31 | W13: =COUNTIFS(northwind_order_details[Price reconciliation],"Match",northwind_order_details[country],$O13) -> 15 | X13: =COUNTIFS(northwind_order_details[Price reconciliation],"Mismatch",northwind_order_details[country],$O13) -> 36
A14: 10252 | B14: 33 | C14: 2 | D14: 25 | E14: 0.05 | F14: =_xlfn.XLOOKUP(northwind_order_details[[#This Row],[order_id]],northwind_orders[order_id],northwind_orders[ship_country]) -> Belgium | G14: =INDEX(northwind_orders[],MATCH(northwind_order_details[[#This Row],[order_id]], northwind_orders[order_id], 0), MATCH("employee_id", northwind_orders[#Headers], 0)) -> 4 | H14: =northwind_order_details[[#This Row],[unit_price]]*northwind_order_details[[#This Row],[quantity]] -> 50 | I14: =northwind_order_details[[#This Row],[purchase amount]]*northwind_order_details[[#This Row],[discount]] -> 2.5 | J14: =northwind_order_details[[#This Row],[purchase amount]]-northwind_order_details[[#This Row],[discount amount]] -> 47.5 | K14: =IF(northwind_order_details[[#This Row],[discount amount]]>0,"Yes","No") -> Yes | L14: =IF(northwind_order_details[[#This Row],[Revenue]]>1000,"High",IF(northwind_order_details[[#This Row],[Revenue]]>300,"Medium","Low")) -> Low | M14: =IF(northwind_order_details[[#This Row],[unit_price]]=_xlfn.XLOOKUP(northwind_order_details[[#This Row],[product_id]],'Price Validation'!$D$2:$D$78,'Price Validation'!$E$2:$E$78),"Match","Mismatch") -> Mismatch | O14: Spain | P14: =SUMIF(northwind_order_details[country],$O14,northwind_order_details[Revenue]) -> 17983.2 | Q14: =AVERAGEIF(northwind_order_details[country],$O14,northwind_order_details[Revenue]) -> 333.02222 | R14: =COUNTIF(northwind_order_details[country],O14) -> 54 | S14: =ROUND(SUMIF(northwind_order_details[country],$O14,northwind_order_details[discount amount]),2) -> 1448.69 | T14: =COUNTIFS(northwind_order_details[Type of Revenue],T$1,northwind_order_details[country],$O14) -> 4 | U14: =COUNTIFS(northwind_order_details[Type of Revenue],U$1,northwind_order_details[country],$O14) -> 12 | V14: =COUNTIFS(northwind_order_details[Type of Revenue],V$1,northwind_order_details[country],$O14) -> 38 | W14: =COUNTIFS(northwind_order_details[Price reconciliation],"Match",northwind_order_details[country],$O14) -> 15 | X14: =COUNTIFS(northwind_order_details[Price reconciliation],"Mismatch",northwind_order_details[country],$O14) -> 39
A15: 10252 | B15: 60 | C15: 27.2 | D15: 40 | E15: 0 | F15: =_xlfn.XLOOKUP(northwind_order_details[[#This Row],[order_id]],northwind_orders[order_id],northwind_orders[ship_country]) -> Belgium | G15: =INDEX(northwind_orders[],MATCH(northwind_order_details[[#This Row],[order_id]], northwind_orders[order_id], 0), MATCH("employee_id", northwind_orders[#Headers], 0)) -> 4 | H15: =northwind_order_details[[#This Row],[unit_price]]*northwind_order_details[[#This Row],[quantity]] -> 1088 | I15: =northwind_order_details[[#This Row],[purchase amount]]*northwind_order_details[[#This Row],[discount]] -> 0 | J15: =northwind_order_details[[#This Row],[purchase amount]]-northwind_order_details[[#This Row],[discount amount]] -> 1088 | K15: =IF(northwind_order_details[[#This Row],[discount amount]]>0,"Yes","No") -> No | L15: =IF(northwind_order_details[[#This Row],[Revenue]]>1000,"High",IF(northwind_order_details[[#This Row],[Revenue]]>300,"Medium","Low")) -> High | M15: =IF(northwind_order_details[[#This Row],[unit_price]]=_xlfn.XLOOKUP(northwind_order_details[[#This Row],[product_id]],'Price Validation'!$D$2:$D$78,'Price Validation'!$E$2:$E$78),"Match","Mismatch") -> Mismatch | O15: UK | P15: =SUMIF(northwind_order_details[country],$O15,northwind_order_details[Revenue]) -> 58971.31 | Q15: =AVERAGEIF(northwind_order_details[country],$O15,northwind_order_details[Revenue]) -> 436.82452 | R15: =COUNTIF(northwind_order_details[country],O15) -> 135 | S15: =ROUND(SUMIF(northwind_order_details[country],$O15,northwind_order_details[discount amount]),2) -> 1645.2 | T15: =COUNTIFS(northwind_order_details[Type of Revenue],T$1,northwind_order_details[country],$O15) -> 14 | U15: =COUNTIFS(northwind_order_details[Type of Revenue],U$1,northwind_order_details[country],$O15) -> 49 | V15: =COUNTIFS(northwind_order_details[Type of Revenue],V$1,northwind_order_details[country],$O15) -> 72 | W15: =COUNTIFS(northwind_order_details[Price reconciliation],"Match",northwind_order_details[country],$O15) -> 31 | X15: =COUNTIFS(northwind_order_details[Price reconciliation],"Mismatch",northwind_order_details[country],$O15) -> 104
A16: 10253 | B16: 31 | C16: 10 | D16: 20 | E16: 0 | F16: =_xlfn.XLOOKUP(northwind_order_details[[#This Row],[order_id]],northwind_orders[order_id],northwind_orders[ship_country]) -> Brazil | G16: =INDEX(northwind_orders[],MATCH(northwind_order_details[[#This Row],[order_id]], northwind_orders[order_id], 0), MATCH("employee_id", northwind_orders[#Headers], 0)) -> 3 | H16: =northwind_order_details[[#This Row],[unit_price]]*northwind_order_details[[#This Row],[quantity]] -> 200 | I16: =northwind_order_details[[#This Row],[purchase amount]]*northwind_order_details[[#This Row],[discount]] -> 0 | J16: =northwind_order_details[[#This Row],[purchase amount]]-northwind_order_details[[#This Row],[discount amount]] -> 200 | K16: =IF(northwind_order_details[[#This Row],[discount amount]]>0,"Yes","No") -> No | L16: =IF(northwind_order_details[[#This Row],[Revenue]]>1000,"High",IF(northwind_order_details[[#This Row],[Revenue]]>300,"Medium","Low")) -> Low | M16: =IF(northwind_order_details[[#This Row],[unit_price]]=_xlfn.XLOOKUP(northwind_order_details[[#This Row],[product_id]],'Price Validation'!$D$2:$D$78,'Price Validation'!$E$2:$E$78),"Match","Mismatch") -> Mismatch | O16: Portugal | P16: =SUMIF(northwind_order_details[country],$O16,northwind_order_details[Revenue]) -> 11472.362 | Q16: =AVERAGEIF(northwind_order_details[country],$O16,northwind_order_details[Revenue]) -> 382.41208 | R16: =COUNTIF(northwind_order_details[country],O16) -> 30 | S16: =ROUND(SUMIF(northwind_order_details[country],$O16,northwind_order_details[discount amount]),2) -> 996.29 | T16: =COUNTIFS(northwind_order_details[Type of Revenue],T$1,northwind_order_details[country],$O16) -> 2 | U16: =COUNTIFS(northwind_order_details[Type of Revenue],U$1,northwind_order_details[country],$O16) -> 11 | V16: =COUNTIFS(northwind_order_details[Type of Revenue],V$1,northwind_order_details[country],$O16) -> 17 | W16: =COUNTIFS(northwind_order_details[Price reconciliation],"Match",northwind_order_details[country],$O16) -> 5 | X16: =COUNTIFS(northwind_order_details[Price reconciliation],"Mismatch",northwind_order_details[country],$O16) -> 25
A17: 10253 | B17: 39 | C17: 14.4 | D17: 42 | E17: 0 | F17: =_xlfn.XLOOKUP(northwind_order_details[[#This Row],[order_id]],northwind_orders[order_id],northwind_orders[ship_country]) -> Brazil | G17: =INDEX(northwind_orders[],MATCH(northwind_order_details[[#This Row],[order_id]], northwind_orders[order_id], 0), MATCH("employee_id", northwind_orders[#Headers], 0)) -> 3 | H17: =northwind_order_details[[#This Row],[unit_price]]*northwind_order_details[[#This Row],[quantity]] -> 604.8 | I17: =northwind_order_details[[#This Row],[purchase amount]]*northwind_order_details[[#This Row],[discount]] -> 0 | J17: =northwind_order_details[[#This Row],[purchase amount]]-northwind_order_details[[#This Row],[discount amount]] -> 604.8 | K17: =IF(northwind_order_details[[#This Row],[discount amount]]>0,"Yes","No") -> No | L17: =IF(northwind_order_details[[#This Row],[Revenue]]>1000,"High",IF(northwind_order_details[[#This Row],[Revenue]]>300,"Medium","Low")) -> Medium | M17: =IF(northwind_order_details[[#This Row],[unit_price]]=_xlfn.XLOOKUP(northwind_order_details[[#This Row],[product_id]],'Price Validation'!$D$2:$D$78,'Price Validation'!$E$2:$E$78),"Match","Mismatch") -> Mismatch | O17: Canada | P17: =SUMIF(northwind_order_details[country],$O17,northwind_order_details[Revenue]) -> 48886.79 | Q17: =AVERAGEIF(northwind_order_details[country],$O17,northwind_order_details[Revenue]) -> 669.68205 | R17: =COUNTIF(northwind_order_details[country],O17) -> 73 | S17: =ROUND(SUMIF(northwind_order_details[country],$O17,northwind_order_details[discount amount]),2) -> 5137.81 | T17: =COUNTIFS(northwind_order_details[Type of Revenue],T$1,northwind_order_details[country],$O17) -> 12 | U17: =COUNTIFS(northwind_order_details[Type of Revenue],U$1,northwind_order_details[country],$O17) -> 29 | V17: =COUNTIFS(northwind_order_details[Type of Revenue],V$1,northwind_order_details[country],$O17) -> 32 | W17: =COUNTIFS(northwind_order_details[Price reconciliation],"Match",northwind_order_details[country],$O17) -> 15 | X17: =COUNTIFS(northwind_order_details[Price reconciliation],"Mismatch",northwind_order_details[country],$O17) -> 58
A18: 10253 | B18: 49 | C18: 16 | D18: 40 | E18: 0 | F18: =_xlfn.XLOOKUP(northwind_order_details[[#This Row],[order_id]],northwind_orders[order_id],northwind_orders[ship_country]) -> Brazil | G18: =INDEX(northwind_orders[],MATCH(northwind_order_details[[#This Row],[order_id]], northwind_orders[order_id], 0), MATCH("employee_id", northwind_orders[#Headers], 0)) -> 3 | H18: =northwind_order_details[[#This Row],[unit_price]]*northwind_order_details[[#This Row],[quantity]] -> 640 | I18: =northwind_order_details[[#This Row],[purchase amount]]*northwind_order_details[[#This Row],[discount]] -> 0 | J18: =northwind_order_details[[#This Row],[purchase amount]]-northwind_order_details[[#This Row],[discount amount]] -> 640 | K18: =IF(northwind_order_details[[#This Row],[discount amount]]>0,"Yes","No") -> No | L18: =IF(northwind_order_details[[#This Row],[Revenue]]>1000,"High",IF(northwind_order_details[[#This Row],[Revenue]]>300,"Medium","Low")) -> Medium | M18: =IF(northwind_order_details[[#This Row],[unit_price]]=_xlfn.XLOOKUP(northwind_order_details[[#This Row],[product_id]],'Price Validation'!$D$2:$D$78,'Price Validation'!$E$2:$E$78),"Match","Mismatch") -> Mismatch | O18: Denmark | P18: =SUMIF(northwind_order_details[country],$O18,northwind_order_details[Revenue]) -> 32428.938 | Q18: =AVERAGEIF(northwind_order_details[country],$O18,northwind_order_details[Revenue]) -> 720.64306 | R18: =COUNTIF(northwind_order_details[country],O18) -> 45 | S18: =ROUND(SUMIF(northwind_order_details[country],$O18,northwind_order_details[discount amount]),2) -> 2109.01 | T18: =COUNTIFS(northwind_order_details[Type of Revenue],T$1,northwind_order_details[country],$O18) -> 6 | U18: =COUNTIFS(northwind_order_details[Type of Revenue],U$1,northwind_order_details[country],$O18) -> 19 | V18: =COUNTIFS(northwind_order_details[Type of Revenue],V$1,northwind_order_details[country],$O18) -> 20 | W18: =COUNTIFS(northwind_order_details[Price reconciliation],"Match",northwind_order_details[country],$O18) -> 12 | X18: =COUNTIFS(northwind_order_details[Price reconciliation],"Mismatch",northwind_order_details[country],$O18) -> 33
A19: 10254 | B19: 24 | C19: 3.6 | D19: 15 | E19: 0.15 | F19: =_xlfn.XLOOKUP(northwind_order_details[[#This Row],[order_id]],northwind_orders[order_id],northwind_orders[ship_country]) -> Switzerland | G19: =INDEX(northwind_orders[],MATCH(northwind_order_details[[#This Row],[order_id]], northwind_orders[order_id], 0), MATCH("employee_id", northwind_orders[#Headers], 0)) -> 5 | H19: =northwind_order_details[[#This Row],[unit_price]]*northwind_order_details[[#This Row],[quantity]] -> 54 | I19: =northwind_order_details[[#This Row],[purchase amount]]*northwind_order_details[[#This Row],[discount]] -> 8.1 | J19: =northwind_order_details[[#This Row],[purchase amount]]-northwind_order_details[[#This Row],[discount amount]] -> 45.9 | K19: =IF(northwind_order_details[[#This Row],[discount amount]]>0,"Yes","No") -> Yes | L19: =IF(northwind_order_details[[#This Row],[Revenue]]>1000,"High",IF(northwind_order_details[[#This Row],[Revenue]]>300,"Medium","Low")) -> Low | M19: =IF(northwind_order_details[[#This Row],[unit_price]]=_xlfn.XLOOKUP(northwind_order_details[[#This Row],[product_id]],'Price Validation'!$D$2:$D$78,'Price Validation'!$E$2:$E$78),"Match","Mismatch") -> Mismatch | O19: Poland | P19: =SUMIF(northwind_order_details[country],$O19,northwind_order_details[Revenue]) -> 3531.95 | Q19: =AVERAGEIF(northwind_order_details[country],$O19,northwind_order_details[Revenue]) -> 220.74687 | R19: =COUNTIF(northwind_order_details[country],O19) -> 16 | S19: =ROUND(SUMIF(northwind_order_details[country],$O19,northwind_order_details[discount amount]),2) -> 0 | T19: =COUNTIFS(northwind_order_details[Type of Revenue],T$1,northwind_order_details[country],$O19) -> 0 | U19: =COUNTIFS(northwind_order_details[Type of Revenue],U$1,northwind_order_details[country],$O19) -> 3 | V19: =COUNTIFS(northwind_order_details[Type of Revenue],V$1,northwind_order_details[country],$O19) -> 13 | W19: =COUNTIFS(northwind_order_details[Price reconciliation],"Match",northwind_order_details[country],$O19) -> 7 | X19: =COUNTIFS(northwind_order_details[Price reconciliation],"Mismatch",northwind_order_details[country],$O19) -> 9
A20: 10254 | B20: 55 | C20: 19.2 | D20: 21 | E20: 0.15 | F20: =_xlfn.XLOOKUP(northwind_order_details[[#This Row],[order_id]],northwind_orders[order_id],northwind_orders[ship_country]) -> Switzerland | G20: =INDEX(northwind_orders[],MATCH(northwind_order_details[[#This Row],[order_id]], northwind_orders[order_id], 0), MATCH("employee_id", northwind_orders[#Headers], 0)) -> 5 | H20: =northwind_order_details[[#This Row],[unit_price]]*northwind_order_details[[#This Row],[quantity]] -> 403.2 | I20: =northwind_order_details[[#This Row],[purchase amount]]*northwind_order_details[[#This Row],[discount]] -> 60.48 | J20: =northwind_order_details[[#This Row],[purchase amount]]-northwind_order_details[[#This Row],[discount amount]] -> 342.72 | K20: =IF(northwind_order_details[[#This Row],[discount amount]]>0,"Yes","No") -> Yes | L20: =IF(northwind_order_details[[#This Row],[Revenue]]>1000,"High",IF(northwind_order_details[[#This Row],[Revenue]]>300,"Medium","Low")) -> Medium | M20: =IF(northwind_order_details[[#This Row],[unit_price]]=_xlfn.XLOOKUP(northwind_order_details[[#This Row],[product_id]],'Price Validation'!$D$2:$D$78,'Price Validation'!$E$2:$E$78),"Match","Mismatch") -> Mismatch | O20: Norway | P20: =SUMIF(northwind_order_details[country],$O20,northwind_order_details[Revenue]) -> 5735.15 | Q20: =AVERAGEIF(northwind_order_details[country],$O20,northwind_order_details[Revenue]) -> 358.44688 | R20: =COUNTIF(northwind_order_details[country],O20) -> 16 | S20: =ROUND(SUMIF(northwind_order_details[country],$O20,northwind_order_details[discount amount]),2) -> 0 | T20: =COUNTIFS(northwind_order_details[Type of Revenue],T$1,northwind_order_details[country],$O20) -> 1 | U20: =COUNTIFS(northwind_order_details[Type of Revenue],U$1,northwind_order_details[country],$O20) -> 5 | V20: =COUNTIFS(northwind_order_details[Type of Revenue],V$1,northwind_order_details[country],$O20) -> 10 | W20: =COUNTIFS(northwind_order_details[Price reconciliation],"Match",northwind_order_details[country],$O20) -> 8 | X20: =COUNTIFS(northwind_order_details[Price reconciliation],"Mismatch",northwind_order_details[country],$O20) -> 8
A21: 10254 | B21: 74 | C21: 8 | D21: 21 | E21: 0 | F21: =_xlfn.XLOOKUP(northwind_order_details[[#This Row],[order_id]],northwind_orders[order_id],northwind_orders[ship_country]) -> Switzerland | G21: =INDEX(northwind_orders[],MATCH(northwind_order_details[[#This Row],[order_id]], northwind_orders[order_id], 0), MATCH("employee_id", northwind_orders[#Headers], 0)) -> 5 | H21: =northwind_order_details[[#This Row],[unit_price]]*northwind_order_details[[#This Row],[quantity]] -> 168 | I21: =northwind_order_details[[#This Row],[purchase amount]]*northwind_order_details[[#This Row],[discount]] -> 0 | J21: =northwind_order_details[[#This Row],[purchase amount]]-northwind_order_details[[#This Row],[discount amount]] -> 168 | K21: =IF(northwind_order_details[[#This Row],[discount amount]]>0,"Yes","No") -> No | L21: =IF(northwind_order_details[[#This Row],[Revenue]]>1000,"High",IF(northwind_order_details[[#This Row],[Revenue]]>300,"Medium","Low")) -> Low | M21: =IF(northwind_order_details[[#This Row],[unit_price]]=_xlfn.XLOOKUP(northwind_order_details[[#This Row],[product_id]],'Price Validation'!$D$2:$D$78,'Price Validation'!$E$2:$E$78),"Match","Mismatch") -> Mismatch | O21: Argentina | P21: =SUMIF(northwind_order_details[country],$O21,northwind_order_details[Revenue]) -> 7738.1 | Q21: =AVERAGEIF(northwind_order_details[country],$O21,northwind_order_details[Revenue]) -> 257.93667 | R21: =COUNTIF(northwind_order_details[country],O21) -> 30 | S21: =ROUND(SUMIF(northwind_order_details[country],$O21,northwind_order_details[discount amount]),2) -> 0 | T21: =COUNTIFS(northwind_order_details[Type of Revenue],T$1,northwind_order_details[country],$O21) -> 1 | U21: =COUNTIFS(northwind_order_details[Type of Revenue],U$1,northwind_order_details[country],$O21) -> 8 | V21: =COUNTIFS(northwind_order_details[Type of Revenue],V$1,northwind_order_details[country],$O21) -> 21 | W21: =COUNTIFS(northwind_order_details[Price reconciliation],"Match",northwind_order_details[country],$O21) -> 11 | X21: =COUNTIFS(northwind_order_details[Price reconciliation],"Mismatch",northwind_order_details[country],$O21) -> 19
A22: 10255 | B22: 2 | C22: 15.2 | D22: 20 | E22: 0 | F22: =_xlfn.XLOOKUP(northwind_order_details[[#This Row],[order_id]],northwind_orders[order_id],northwind_orders[ship_country]) -> Switzerland | G22: =INDEX(northwind_orders[],MATCH(northwind_order_details[[#This Row],[order_id]], northwind_orders[order_id], 0), MATCH("employee_id", northwind_orders[#Headers], 0)) -> 9 | H22: =northwind_order_details[[#This Row],[unit_price]]*northwind_order_details[[#This Row],[quantity]] -> 304 | I22: =northwind_order_details[[#This Row],[purchase amount]]*northwind_order_details[[#This Row],[discount]] -> 0 | J22: =northwind_order_details[[#This Row],[purchase amount]]-northwind_order_details[[#This Row],[discount amount]] -> 304 | K22: =IF(northwind_order_details[[#This Row],[discount amount]]>0,"Yes","No") -> No | L22: =IF(northwind_order_details[[#This Row],[Revenue]]>1000,"High",IF(northwind_order_details[[#This Row],[Revenue]]>300,"Medium","Low")) -> Medium | M22: =IF(northwind_order_details[[#This Row],[unit_price]]=_xlfn.XLOOKUP(northwind_order_details[[#This Row],[product_id]],'Price Validation'!$D$2:$D$78,'Price Validation'!$E$2:$E$78),"Match","Mismatch") -> Mismatch | O22: sum | P22: =SUM(P2:P21) -> 1189875.7 | Q22: =AVERAGE(Q2:Q21) -> 503.86286 | R22: =AVERAGE(R2:R21) -> 101.35 | S22: =SUM(S2:S21) -> 79821.74 | T22: =SUM(T2:T21) -> 297 | U22: =SUM(U2:U21) -> 792 | V22: =SUM(V2:V21) -> 938 | W22: =SUM(W2:W21) -> 647 | X22: =SUM(X2:X21) -> 1380
A23: 10255 | B23: 16 | C23: 13.9 | D23: 35 | E23: 0 | F23: =_xlfn.XLOOKUP(northwind_order_details[[#This Row],[order_id]],northwind_orders[order_id],northwind_orders[ship_country]) -> Switzerland | G23: =INDEX(northwind_orders[],MATCH(northwind_order_details[[#This Row],[order_id]], northwind_orders[order_id], 0), MATCH("employee_id", northwind_orders[#Headers], 0)) -> 9 | H23: =northwind_order_details[[#This Row],[unit_price]]*northwind_order_details[[#This Row],[quantity]] -> 486.5 | I23: =northwind_order_details[[#This Row],[purchase amount]]*northwind_order_details[[#This Row],[discount]] -> 0 | J23: =northwind_order_details[[#This Row],[purchase amount]]-northwind_order_details[[#This Row],[discount amount]] -> 486.5 | K23: =IF(northwind_order_details[[#This Row],[discount amount]]>0,"Yes","No") -> No | L23: =IF(northwind_order_details[[#This Row],[Revenue]]>1000,"High",IF(northwind_order_details[[#This Row],[Revenue]]>300,"Medium","Low")) -> Medium | M23: =IF(northwind_order_details[[#This Row],[unit_price]]=_xlfn.XLOOKUP(northwind_order_details[[#This Row],[product_id]],'Price Validation'!$D$2:$D$78,'Price Validation'!$E$2:$E$78),"Match","Mismatch") -> Mismatch | Q23: avg | R23: avg
A24: 10255 | B24: 36 | C24: 15.2 | D24: 25 | E24: 0 | F24: =_xlfn.XLOOKUP(northwind_order_details[[#This Row],[order_id]],northwind_orders[order_id],northwind_orders[ship_country]) -> Switzerland | G24: =INDEX(northwind_orders[],MATCH(northwind_order_details[[#This Row],[order_id]], northwind_orders[order_id], 0), MATCH("employee_id", northwind_orders[#Headers], 0)) -> 9 | H24: =northwind_order_details[[#This Row],[unit_price]]*northwind_order_details[[#This Row],[quantity]] -> 380 | I24: =northwind_order_details[[#This Row],[purchase amount]]*northwind_order_details[[#This Row],[discount]] -> 0 | J24: =northwind_order_details[[#This Row],[purchase amount]]-northwind_order_details[[#This Row],[discount amount]] -> 380 | K24: =IF(northwind_order_details[[#This Row],[discount amount]]>0,"Yes","No") -> No | L24: =IF(northwind_order_details[[#This Row],[Revenue]]>1000,"High",IF(northwind_order_details[[#This Row],[Revenue]]>300,"Medium","Low")) -> Medium | M24: =IF(northwind_order_details[[#This Row],[unit_price]]=_xlfn.XLOOKUP(northwind_order_details[[#This Row],[product_id]],'Price Validation'!$D$2:$D$78,'Price Validation'!$E$2:$E$78),"Match","Mismatch") -> Mismatch
A25: 10255 | B25: 59 | C25: 44 | D25: 30 | E25: 0 | F25: =_xlfn.XLOOKUP(northwind_order_details[[#This Row],[order_id]],northwind_orders[order_id],northwind_orders[ship_country]) -> Switzerland | G25: =INDEX(northwind_orders[],MATCH(northwind_order_details[[#This Row],[order_id]], northwind_orders[order_id], 0), MATCH("employee_id", northwind_orders[#Headers], 0)) -> 9 | H25: =northwind_order_details[[#This Row],[unit_price]]*northwind_order_details[[#This Row],[quantity]] -> 1320 | I25: =northwind_order_details[[#This Row],[purchase amount]]*northwind_order_details[[#This Row],[discount]] -> 0 | J25: =northwind_order_details[[#This Row],[purchase amount]]-northwind_order_details[[#This Row],[discount amount]] -> 1320 | K25: =IF(northwind_order_details[[#This Row],[discount amount]]>0,"Yes","No") -> No | L25: =IF(northwind_order_details[[#This Row],[Revenue]]>1000,"High",IF(northwind_order_details[[#This Row],[Revenue]]>300,"Medium","Low")) -> High | M25: =IF(northwind_order_details[[#This Row],[unit_price]]=_xlfn.XLOOKUP(northwind_order_details[[#This Row],[product_id]],'Price Validation'!$D$2:$D$78,'Price Validation'!$E$2:$E$78),"Match","Mismatch") -> Mismatch
A26: 10256 | B26: 53 | C26: 26.2 | D26: 15 | E26: 0 | F26: =_xlfn.XLOOKUP(northwind_order_details[[#This Row],[order_id]],northwind_orders[order_id],northwind_orders[ship_country]) -> Brazil | G26: =INDEX(northwind_orders[],MATCH(northwind_order_details[[#This Row],[order_id]], northwind_orders[order_id], 0), MATCH("employee_id", northwind_orders[#Headers], 0)) -> 3 | H26: =northwind_order_details[[#This Row],[unit_price]]*northwind_order_details[[#This Row],[quantity]] -> 393 | I26: =northwind_order_details[[#This Row],[purchase amount]]*northwind_order_details[[#This Row],[discount]] -> 0 | J26: =northwind_order_details[[#This Row],[purchase amount]]-northwind_order_details[[#This Row],[discount amount]] -> 393 | K26: =IF(northwind_order_details[[#This Row],[discount amount]]>0,"Yes","No") -> No | L26: =IF(northwind_order_details[[#This Row],[Revenue]]>1000,"High",IF(northwind_order_details[[#This Row],[Revenue]]>300,"Medium","Low")) -> Medium | M26: =IF(northwind_order_details[[#This Row],[unit_price]]=_xlfn.XLOOKUP(northwind_order_details[[#This Row],[product_id]],'Price Validation'!$D$2:$D$78,'Price Validation'!$E$2:$E$78),"Match","Mismatch") -> Mismatch
A27: 10256 | B27: 77 | C27: 10.4 | D27: 12 | E27: 0 | F27: =_xlfn.XLOOKUP(northwind_order_details[[#This Row],[order_id]],northwind_orders[order_id],northwind_orders[ship_country]) -> Brazil | G27: =INDEX(northwind_orders[],MATCH(northwind_order_details[[#This Row],[order_id]], northwind_orders[order_id], 0), MATCH("employee_id", northwind_orders[#Headers], 0)) -> 3 | H27: =northwind_order_details[[#This Row],[unit_price]]*northwind_order_details[[#This Row],[quantity]] -> 124.8 | I27: =northwind_order_details[[#This Row],[purchase amount]]*northwind_order_details[[#This Row],[discount]] -> 0 | J27: =northwind_order_details[[#This Row],[purchase amount]]-northwind_order_details[[#This Row],[discount amount]] -> 124.8 | K27: =IF(northwind_order_details[[#This Row],[discount amount]]>0,"Yes","No") -> No | L27: =IF(northwind_order_details[[#This Row],[Revenue]]>1000,"High",IF(northwind_order_details[[#This Row],[Revenue]]>300,"Medium","Low")) -> Low | M27: =IF(northwind_order_details[[#This Row],[unit_price]]=_xlfn.XLOOKUP(northwind_order_details[[#This Row],[product_id]],'Price Validation'!$D$2:$D$78,'Price Validation'!$E$2:$E$78),"Match","Mismatch") -> Mismatch
A28: 10257 | B28: 27 | C28: 35.1 | D28: 25 | E28: 0 | F28: =_xlfn.XLOOKUP(northwind_order_details[[#This Row],[order_id]],northwind_orders[order_id],northwind_orders[ship_country]) -> Venezuela | G28: =INDEX(northwind_orders[],MATCH(northwind_order_details[[#This Row],[order_id]], northwind_orders[order_id], 0), MATCH("employee_id", northwind_orders[#Headers], 0)) -> 4 | H28: =northwind_order_details[[#This Row],[unit_price]]*northwind_order_details[[#This Row],[quantity]] -> 877.5 | I28: =northwind_order_details[[#This Row],[purchase amount]]*northwind_order_details[[#This Row],[discount]] -> 0 | J28: =northwind_order_details[[#This Row],[purchase amount]]-northwind_order_details[[#This Row],[discount amount]] -> 877.5 | K28: =IF(northwind_order_details[[#This Row],[discount amount]]>0,"Yes","No") -> No | L28: =IF(northwind_order_details[[#This Row],[Revenue]]>1000,"High",IF(northwind_order_details[[#This Row],[Revenue]]>300,"Medium","Low")) -> Medium | M28: =IF(northwind_order_details[[#This Row],[unit_price]]=_xlfn.XLOOKUP(northwind_order_details[[#This Row],[product_id]],'Price Validation'!$D$2:$D$78,'Price Validation'!$E$2:$E$78),"Match","Mismatch") -> Mismatch
A29: 10257 | B29: 39 | C29: 14.4 | D29: 6 | E29: 0 | F29: =_xlfn.XLOOKUP(northwind_order_details[[#This Row],[order_id]],northwind_orders[order_id],northwind_orders[ship_country]) -> Venezuela | G29: =INDEX(northwind_orders[],MATCH(northwind_order_details[[#This Row],[order_id]], northwind_orders[order_id], 0), MATCH("employee_id", northwind_orders[#Headers], 0)) -> 4 | H29: =northwind_order_details[[#This Row],[unit_price]]*northwind_order_details[[#This Row],[quantity]] -> 86.4 | I29: =northwind_order_details[[#This Row],[purchase amount]]*northwind_order_details[[#This Row],[discount]] -> 0 | J29: =northwind_order_details[[#This Row],[purchase amount]]-northwind_order_details[[#This Row],[discount amount]] -> 86.4 | K29: =IF(northwind_order_details[[#This Row],[discount amount]]>0,"Yes","No") -> No | L29: =IF(northwind_order_details[[#This Row],[Revenue]]>1000,"High",IF(northwind_order_details[[#This Row],[Revenue]]>300,"Medium","Low")) -> Low | M29: =IF(northwind_order_details[[#This Row],[unit_price]]=_xlfn.XLOOKUP(northwind_order_details[[#This Row],[product_id]],'Price Validation'!$D$2:$D$78,'Price Validation'!$E$2:$E$78),"Match","Mismatch") -> Mismatch
A30: 10257 | B30: 77 | C30: 10.4 | D30: 15 | E30: 0 | F30: =_xlfn.XLOOKUP(northwind_order_details[[#This Row],[order_id]],northwind_orders[order_id],northwind_orders[ship_country]) -> Venezuela | G30: =INDEX(northwind_orders[],MATCH(northwind_order_details[[#This Row],[order_id]], northwind_orders[order_id], 0), MATCH("employee_id", northwind_orders[#Headers], 0)) -> 4 | H30: =northwind_order_details[[#This Row],[unit_price]]*northwind_order_details[[#This Row],[quantity]] -> 156 | I30: =northwind_order_details[[#This Row],[purchase amount]]*northwind_order_details[[#This Row],[discount]] -> 0 | J30: =northwind_order_details[[#This Row],[purchase amount]]-northwind_order_details[[#This Row],[discount amount]] -> 156 | K30: =IF(northwind_order_details[[#This Row],[discount amount]]>0,"Yes","No") -> No | L30: =IF(northwind_order_details[[#This Row],[Revenue]]>1000,"High",IF(northwind_order_details[[#This Row],[Revenue]]>300,"Medium","Low")) -> Low | M30: =IF(northwind_order_details[[#This Row],[unit_price]]=_xlfn.XLOOKUP(northwind_order_details[[#This Row],[product_id]],'Price Validation'!$D$2:$D$78,'Price Validation'!$E$2:$E$78),"Match","Mismatch") -> Mismatch
A31: 10258 | B31: 2 | C31: 15.2 | D31: 50 | E31: 0.2 | F31: =_xlfn.XLOOKUP(northwind_order_details[[#This Row],[order_id]],northwind_orders[order_id],northwind_orders[ship_country]) -> Austria | G31: =INDEX(northwind_orders[],MATCH(northwind_order_details[[#This Row],[order_id]], northwind_orders[order_id], 0), MATCH("employee_id", northwind_orders[#Headers], 0)) -> 1 | H31: =northwind_order_details[[#This Row],[unit_price]]*northwind_order_details[[#This Row],[quantity]] -> 760 | I31: =northwind_order_details[[#This Row],[purchase amount]]*northwind_order_details[[#This Row],[discount]] -> 152 | J31: =northwind_order_details[[#This Row],[purchase amount]]-northwind_order_details[[#This Row],[discount amount]] -> 608 | K31: =IF(northwind_order_details[[#This Row],[discount amount]]>0,"Yes","No") -> Yes | L31: =IF(northwind_order_details[[#This Row],[Revenue]]>1000,"High",IF(northwind_order_details[[#This Row],[Revenue]]>300,"Medium","Low")) -> Medium | M31: =IF(northwind_order_details[[#This Row],[unit_price]]=_xlfn.XLOOKUP(northwind_order_details[[#This Row],[product_id]],'Price Validation'!$D$2:$D$78,'Price Validation'!$E$2:$E$78),"Match","Mismatch") -> Mismatch
A32: 10258 | B32: 5 | C32: 17 | D32: 65 | E32: 0.2 | F32: =_xlfn.XLOOKUP(northwind_order_details[[#This Row],[order_id]],northwind_orders[order_id],northwind_orders[ship_country]) -> Austria | G32: =INDEX(northwind_orders[],MATCH(northwind_order_details[[#This Row],[order_id]], northwind_orders[order_id], 0), MATCH("employee_id", northwind_orders[#Headers], 0)) -> 1 | H32: =northwind_order_details[[#This Row],[unit_price]]*northwind_order_details[[#This Row],[quantity]] -> 1105 | I32: =northwind_order_details[[#This Row],[purchase amount]]*northwind_order_details[[#This Row],[discount]] -> 221 | J32: =northwind_order_details[[#This Row],[purchase amount]]-northwind_order_details[[#This Row],[discount amount]] -> 884 | K32: =IF(northwind_order_details[[#This Row],[discount amount]]>0,"Yes","No") -> Yes | L32: =IF(northwind_order_details[[#This Row],[Revenue]]>1000,"High",IF(northwind_order_details[[#This Row],[Revenue]]>300,"Medium","Low")) -> Medium | M32: =IF(northwind_order_details[[#This Row],[unit_price]]=_xlfn.XLOOKUP(northwind_order_details[[#This Row],[product_id]],'Price Validation'!$D$2:$D$78,'Price Validation'!$E$2:$E$78),"Match","Mismatch") -> Mismatch
A33: 10258 | B33: 32 | C33: 25.6 | D33: 6 | E33: 0.2 | F33: =_xlfn.XLOOKUP(northwind_order_details[[#This Row],[order_id]],northwind_orders[order_id],northwind_orders[ship_country]) -> Austria | G33: =INDEX(northwind_orders[],MATCH(northwind_order_details[[#This Row],[order_id]], northwind_orders[order_id], 0), MATCH("employee_id", northwind_orders[#Headers], 0)) -> 1 | H33: =northwind_order_details[[#This Row],[unit_price]]*northwind_order_details[[#This Row],[quantity]] -> 153.6 | I33: =northwind_order_details[[#This Row],[purchase amount]]*northwind_order_details[[#This Row],[discount]] -> 30.72 | J33: =northwind_order_details[[#This Row],[purchase amount]]-northwind_order_details[[#This Row],[discount amount]] -> 122.88 | K33: =IF(northwind_order_details[[#This Row],[discount amount]]>0,"Yes","No") -> Yes | L33: =IF(northwind_order_details[[#This Row],[Revenue]]>1000,"High",IF(northwind_order_details[[#This Row],[Revenue]]>300,"Medium","Low")) -> Low | M33: =IF(northwind_order_details[[#This Row],[unit_price]]=_xlfn.XLOOKUP(northwind_order_details[[#This Row],[product_id]],'Price Validation'!$D$2:$D$78,'Price Validation'!$E$2:$E$78),"Match","Mismatch") -> Mismatch
A34: 10259 | B34: 21 | C34: 8 | D34: 10 | E34: 0 | F34: =_xlfn.XLOOKUP(northwind_order_details[[#This Row],[order_id]],northwind_orders[order_id],northwind_orders[ship_country]) -> Mexico | G34: =INDEX(northwind_orders[],MATCH(northwind_order_details[[#This Row],[order_id]], northwind_orders[order_id], 0), MATCH("employee_id", northwind_orders[#Headers], 0)) -> 4 | H34: =northwind_order_details[[#This Row],[unit_price]]*northwind_order_details[[#This Row],[quantity]] -> 80 | I34: =northwind_order_details[[#This Row],[purchase amount]]*northwind_order_details[[#This Row],[discount]] -> 0 | J34: =northwind_order_details[[#This Row],[purchase amount]]-northwind_order_details[[#This Row],[discount amount]] -> 80 | K34: =IF(northwind_order_details[[#This Row],[discount amount]]>0,"Yes","No") -> No | L34: =IF(northwind_order_details[[#This Row],[Revenue]]>1000,"High",IF(northwind_order_details[[#This Row],[Revenue]]>300,"Medium","Low")) -> Low | M34: =IF(northwind_order_details[[#This Row],[unit_price]]=_xlfn.XLOOKUP(northwind_order_details[[#This Row],[product_id]],'Price Validation'!$D$2:$D$78,'Price Validation'!$E$2:$E$78),"Match","Mismatch") -> Mismatch
A35: 10259 | B35: 37 | C35: 20.8 | D35: 1 | E35: 0 | F35: =_xlfn.XLOOKUP(northwind_order_details[[#This Row],[order_id]],northwind_orders[order_id],northwind_orders[ship_country]) -> Mexico | G35: =INDEX(northwind_orders[],MATCH(northwind_order_details[[#This Row],[order_id]], northwind_orders[order_id], 0), MATCH("employee_id", northwind_orders[#Headers], 0)) -> 4 | H35: =northwind_order_details[[#This Row],[unit_price]]*northwind_order_details[[#This Row],[quantity]] -> 20.8 | I35: =northwind_order_details[[#This Row],[purchase amount]]*northwind_order_details[[#This Row],[discount]] -> 0 | J35: =northwind_order_details[[#This Row],[purchase amount]]-northwind_order_details[[#This Row],[discount amount]] -> 20.8 | K35: =IF(northwind_order_details[[#This Row],[discount amount]]>0,"Yes","No") -> No | L35: =IF(northwind_order_details[[#This Row],[Revenue]]>1000,"High",IF(northwind_order_details[[#This Row],[Revenue]]>300,"Medium","Low")) -> Low | M35: =IF(northwind_order_details[[#This Row],[unit_price]]=_xlfn.XLOOKUP(northwind_order_details[[#This Row],[product_id]],'Price Validation'!$D$2:$D$78,'Price Validation'!$E$2:$E$78),"Match","Mismatch") -> Mismatch
A36: 10260 | B36: 41 | C36: 7.7 | D36: 16 | E36: 0.25 | F36: =_xlfn.XLOOKUP(northwind_order_details[[#This Row],[order_id]],northwind_orders[order_id],northwind_orders[ship_country]) -> Germany | G36: =INDEX(northwind_orders[],MATCH(northwind_order_details[[#This Row],[order_id]], northwind_orders[order_id], 0), MATCH("employee_id", northwind_orders[#Headers], 0)) -> 4 | H36: =northwind_order_details[[#This Row],[unit_price]]*northwind_order_details[[#This Row],[quantity]] -> 123.2 | I36: =northwind_order_details[[#This Row],[purchase amount]]*northwind_order_details[[#This Row],[discount]] -> 30.8 | J36: =northwind_order_details[[#This Row],[purchase amount]]-northwind_order_details[[#This Row],[discount amount]] -> 92.4 | K36: =IF(northwind_order_details[[#This Row],[discount amount]]>0,"Yes","No") -> Yes | L36: =IF(northwind_order_details[[#This Row],[Revenue]]>1000,"High",IF(northwind_order_details[[#This Row],[Revenue]]>300,"Medium","Low")) -> Low | M36: =IF(northwind_order_details[[#This Row],[unit_price]]=_xlfn.XLOOKUP(northwind_order_details[[#This Row],[product_id]],'Price Validation'!$D$2:$D$78,'Price Validation'!$E$2:$E$78),"Match","Mismatch") -> Mismatch
A37: 10260 | B37: 57 | C37: 15.6 | D37: 50 | E37: 0 | F37: =_xlfn.XLOOKUP(northwind_order_details[[#This Row],[order_id]],northwind_orders[order_id],northwind_orders[ship_country]) -> Germany | G37: =INDEX(northwind_orders[],MATCH(northwind_order_details[[#This Row],[order_id]], northwind_orders[order_id], 0), MATCH("employee_id", northwind_orders[#Headers], 0)) -> 4 | H37: =northwind_order_details[[#This Row],[unit_price]]*northwind_order_details[[#This Row],[quantity]] -> 780 | I37: =northwind_order_details[[#This Row],[purchase amount]]*northwind_order_details[[#This Row],[discount]] -> 0 | J37: =northwind_order_details[[#This Row],[purchase amount]]-northwind_order_details[[#This Row],[discount amount]] -> 780 | K37: =IF(northwind_order_details[[#This Row],[discount amount]]>0,"Yes","No") -> No | L37: =IF(northwind_order_details[[#This Row],[Revenue]]>1000,"High",IF(northwind_order_details[[#This Row],[Revenue]]>300,"Medium","Low")) -> Medium | M37: =IF(northwind_order_details[[#This Row],[unit_price]]=_xlfn.XLOOKUP(northwind_order_details[[#This Row],[product_id]],'Price Validation'!$D$2:$D$78,'Price Validation'!$E$2:$E$78),"Match","Mismatch") -> Mismatch
A38: 10260 | B38: 62 | C38: 39.4 | D38: 15 | E38: 0.25 | F38: =_xlfn.XLOOKUP(northwind_order_details[[#This Row],[order_id]],northwind_orders[order_id],northwind_orders[ship_country]) -> Germany | G38: =INDEX(northwind_orders[],MATCH(northwind_order_details[[#This Row],[order_id]], northwind_orders[order_id], 0), MATCH("employee_id", northwind_orders[#Headers], 0)) -> 4 | H38: =northwind_order_details[[#This Row],[unit_price]]*northwind_order_details[[#This Row],[quantity]] -> 591 | I38: =northwind_order_details[[#This Row],[purchase amount]]*northwind_order_details[[#This Row],[discount]] -> 147.75 | J38: =northwind_order_details[[#This Row],[purchase amount]]-northwind_order_details[[#This Row],[discount amount]] -> 443.25 | K38: =IF(northwind_order_details[[#This Row],[discount amount]]>0,"Yes","No") -> Yes | L38: =IF(northwind_order_details[[#This Row],[Revenue]]>1000,"High",IF(northwind_order_details[[#This Row],[Revenue]]>300,"Medium","Low")) -> Medium | M38: =IF(northwind_order_details[[#This Row],[unit_price]]=_xlfn.XLOOKUP(northwind_order_details[[#This Row],[product_id]],'Price Validation'!$D$2:$D$78,'Price Validation'!$E$2:$E$78),"Match","Mismatch") -> Mismatch
A39: 10260 | B39: 70 | C39: 12 | D39: 21 | E39: 0.25 | F39: =_xlfn.XLOOKUP(northwind_order_details[[#This Row],[order_id]],northwind_orders[order_id],northwind_orders[ship_country]) -> Germany | G39: =INDEX(northwind_orders[],MATCH(northwind_order_details[[#This Row],[order_id]], northwind_orders[order_id], 0), MATCH("employee_id", northwind_orders[#Headers], 0)) -> 4 | H39: =northwind_order_details[[#This Row],[unit_price]]*northwind_order_details[[#This Row],[quantity]] -> 252 | I39: =northwind_order_details[[#This Row],[purchase amount]]*northwind_order_details[[#This Row],[discount]] -> 63 | J39: =northwind_order_details[[#This Row],[purchase amount]]-northwind_order_details[[#This Row],[discount amount]] -> 189 | K39: =IF(northwind_order_details[[#This Row],[discount amount]]>0,"Yes","No") -> Yes | L39: =IF(northwind_order_details[[#This Row],[Revenue]]>1000,"High",IF(northwind_order_details[[#This Row],[Revenue]]>300,"Medium","Low")) -> Low | M39: =IF(northwind_order_details[[#This Row],[unit_price]]=_xlfn.XLOOKUP(northwind_order_details[[#This Row],[product_id]],'Price Validation'!$D$2:$D$78,'Price Validation'!$E$2:$E$78),"Match","Mismatch") -> Mismatch
A40: 10261 | B40: 21 | C40: 8 | D40: 20 | E40: 0 | F40: =_xlfn.XLOOKUP(northwind_order_details[[#This Row],[order_id]],northwind_orders[order_id],northwind_orders[ship_country]) -> Brazil | G40: =INDEX(northwind_orders[],MATCH(northwind_order_details[[#This Row],[order_id]], northwind_orders[order_id], 0), MATCH("employee_id", northwind_orders[#Headers], 0)) -> 4 | H40: =northwind_order_details[[#This Row],[unit_price]]*northwind_order_details[[#This Row],[quantity]] -> 160 | I40: =northwind_order_details[[#This Row],[purchase amount]]*northwind_order_details[[#This Row],[discount]] -> 0 | J40: =northwind_order_details[[#This Row],[purchase amount]]-northwind_order_details[[#This Row],[discount amount]] -> 160 | K40: =IF(northwind_order_details[[#This Row],[discount amount]]>0,"Yes","No") -> No | L40: =IF(northwind_order_details[[#This Row],[Revenue]]>1000,"High",IF(northwind_order_details[[#This Row],[Revenue]]>300,"Medium","Low")) -> Low | M40: =IF(northwind_order_details[[#This Row],[unit_price]]=_xlfn.XLOOKUP(northwind_order_details[[#This Row],[product_id]],'Price Validation'!$D$2:$D$78,'Price Validation'!$E$2:$E$78),"Match","Mismatch") -> Mismatch
A41: 10261 | B41: 35 | C41: 14.4 | D41: 20 | E41: 0 | F41: =_xlfn.XLOOKUP(northwind_order_details[[#This Row],[order_id]],northwind_orders[order_id],northwind_orders[ship_country]) -> Brazil | G41: =INDEX(northwind_orders[],MATCH(northwind_order_details[[#This Row],[order_id]], northwind_orders[order_id], 0), MATCH("employee_id", northwind_orders[#Headers], 0)) -> 4 | H41: =northwind_order_details[[#This Row],[unit_price]]*northwind_order_details[[#This Row],[quantity]] -> 288 | I41: =northwind_order_details[[#This Row],[purchase amount]]*northwind_order_details[[#This Row],[discount]] -> 0 | J41: =northwind_order_details[[#This Row],[purchase amount]]-northwind_order_details[[#This Row],[discount amount]] -> 288 | K41: =IF(northwind_order_details[[#This Row],[discount amount]]>0,"Yes","No") -> No | L41: =IF(northwind_order_details[[#This Row],[Revenue]]>1000,"High",IF(northwind_order_details[[#This Row],[Revenue]]>300,"Medium","Low")) -> Low | M41: =IF(northwind_order_details[[#This Row],[unit_price]]=_xlfn.XLOOKUP(northwind_order_details[[#This Row],[product_id]],'Price Validation'!$D$2:$D$78,'Price Validation'!$E$2:$E$78),"Match","Mismatch") -> Mismatch
A42: 10262 | B42: 5 | C42: 17 | D42: 12 | E42: 0.2 | F42: =_xlfn.XLOOKUP(northwind_order_details[[#This Row],[order_id]],northwind_orders[order_id],northwind_orders[ship_country]) -> USA | G42: =INDEX(northwind_orders[],MATCH(northwind_order_details[[#This Row],[order_id]], northwind_orders[order_id], 0), MATCH("employee_id", northwind_orders[#Headers], 0)) -> 8 | H42: =northwind_order_details[[#This Row],[unit_price]]*northwind_order_details[[#This Row],[quantity]] -> 204 | I42: =northwind_order_details[[#This Row],[purchase amount]]*northwind_order_details[[#This Row],[discount]] -> 40.8 | J42: =northwind_order_details[[#This Row],[purchase amount]]-northwind_order_details[[#This Row],[discount amount]] -> 163.2 | K42: =IF(northwind_order_details[[#This Row],[discount amount]]>0,"Yes","No") -> Yes | L42: =IF(northwind_order_details[[#This Row],[Revenue]]>1000,"High",IF(northwind_order_details[[#This Row],[Revenue]]>300,"Medium","Low")) -> Low | M42: =IF(northwind_order_details[[#This Row],[unit_price]]=_xlfn.XLOOKUP(northwind_order_details[[#This Row],[product_id]],'Price Validation'!$D$2:$D$78,'Price Validation'!$E$2:$E$78),"Match","Mismatch") -> Mismatch
A43: 10262 | B43: 7 | C43: 24 | D43: 15 | E43: 0 | F43: =_xlfn.XLOOKUP(northwind_order_details[[#This Row],[order_id]],northwind_orders[order_id],northwind_orders[ship_country]) -> USA | G43: =INDEX(northwind_orders[],MATCH(northwind_order_details[[#This Row],[order_id]], northwind_orders[order_id], 0), MATCH("employee_id", northwind_orders[#Headers], 0)) -> 8 | H43: =northwind_order_details[[#This Row],[unit_price]]*northwind_order_details[[#This Row],[quantity]] -> 360 | I43: =northwind_order_details[[#This Row],[purchase amount]]*northwind_order_details[[#This Row],[discount]] -> 0 | J43: =northwind_order_details[[#This Row],[purchase amount]]-northwind_order_details[[#This Row],[discount amount]] -> 360 | K43: =IF(northwind_order_details[[#This Row],[discount amount]]>0,"Yes","No") -> No | L43: =IF(northwind_order_details[[#This Row],[Revenue]]>1000,"High",IF(northwind_order_details[[#This Row],[Revenue]]>300,"Medium","Low")) -> Medium | M43: =IF(northwind_order_details[[#This Row],[unit_price]]=_xlfn.XLOOKUP(northwind_order_details[[#This Row],[product_id]],'Price Validation'!$D$2:$D$78,'Price Validation'!$E$2:$E$78),"Match","Mismatch") -> Mismatch
A44: 10262 | B44: 56 | C44: 30.4 | D44: 2 | E44: 0 | F44: =_xlfn.XLOOKUP(northwind_order_details[[#This Row],[order_id]],northwind_orders[order_id],northwind_orders[ship_country]) -> USA | G44: =INDEX(northwind_orders[],MATCH(northwind_order_details[[#This Row],[order_id]], northwind_orders[order_id], 0), MATCH("employee_id", northwind_orders[#Headers], 0)) -> 8 | H44: =northwind_order_details[[#This Row],[unit_price]]*northwind_order_details[[#This Row],[quantity]] -> 60.8 | I44: =northwind_order_details[[#This Row],[purchase amount]]*northwind_order_details[[#This Row],[discount]] -> 0 | J44: =northwind_order_details[[#This Row],[purchase amount]]-northwind_order_details[[#This Row],[discount amount]] -> 60.8 | K44: =IF(northwind_order_details[[#This Row],[discount amount]]>0,"Yes","No") -> No | L44: =IF(northwind_order_details[[#This Row],[Revenue]]>1000,"High",IF(northwind_order_details[[#This Row],[Revenue]]>300,"Medium","Low")) -> Low | M44: =IF(northwind_order_details[[#This Row],[unit_price]]=_xlfn.XLOOKUP(northwind_order_details[[#This Row],[product_id]],'Price Validation'!$D$2:$D$78,'Price Validation'!$E$2:$E$78),"Match","Mismatch") -> Mismatch
A45: 10263 | B45: 16 | C45: 13.9 | D45: 60 | E45: 0.25 | F45: =_xlfn.XLOOKUP(northwind_order_details[[#This Row],[order_id]],northwind_orders[order_id],northwind_orders[ship_country]) -> Austria | G45: =INDEX(northwind_orders[],MATCH(northwind_order_details[[#This Row],[order_id]], northwind_orders[order_id], 0), MATCH("employee_id", northwind_orders[#Headers], 0)) -> 9 | H45: =northwind_order_details[[#This Row],[unit_price]]*northwind_order_details[[#This Row],[quantity]] -> 834 | I45: =northwind_order_details[[#This Row],[purchase amount]]*northwind_order_details[[#This Row],[discount]] -> 208.5 | J45: =northwind_order_details[[#This Row],[purchase amount]]-northwind_order_details[[#This Row],[discount amount]] -> 625.5 | K45: =IF(northwind_order_details[[#This Row],[discount amount]]>0,"Yes","No") -> Yes | L45: =IF(northwind_order_details[[#This Row],[Revenue]]>1000,"High",IF(northwind_order_details[[#This Row],[Revenue]]>300,"Medium","Low")) -> Medium | M45: =IF(northwind_order_details[[#This Row],[unit_price]]=_xlfn.XLOOKUP(northwind_order_details[[#This Row],[product_id]],'Price Validation'!$D$2:$D$78,'Price Validation'!$E$2:$E$78),"Match","Mismatch") -> Mismatch
A46: 10263 | B46: 24 | C46: 3.6 | D46: 28 | E46: 0 | F46: =_xlfn.XLOOKUP(northwind_order_details[[#This Row],[order_id]],northwind_orders[order_id],northwind_orders[ship_country]) -> Austria | G46: =INDEX(northwind_orders[],MATCH(northwind_order_details[[#This Row],[order_id]], northwind_orders[order_id], 0), MATCH("employee_id", northwind_orders[#Headers], 0)) -> 9 | H46: =northwind_order_details[[#This Row],[unit_price]]*northwind_order_details[[#This Row],[quantity]] -> 100.8 | I46: =northwind_order_details[[#This Row],[purchase amount]]*northwind_order_details[[#This Row],[discount]] -> 0 | J46: =northwind_order_details[[#This Row],[purchase amount]]-northwind_order_details[[#This Row],[discount amount]] -> 100.8 | K46: =IF(northwind_order_details[[#This Row],[discount amount]]>0,"Yes","No") -> No | L46: =IF(northwind_order_details[[#This Row],[Revenue]]>1000,"High",IF(northwind_order_details[[#This Row],[Revenue]]>300,"Medium","Low")) -> Low | M46: =IF(northwind_order_details[[#This Row],[unit_price]]=_xlfn.XLOOKUP(northwind_order_details[[#This Row],[product_id]],'Price Validation'!$D$2:$D$78,'Price Validation'!$E$2:$E$78),"Match","Mismatch") -> Mismatch
A47: 10263 | B47: 30 | C47: 20.7 | D47: 60 | E47: 0.25 | F47: =_xlfn.XLOOKUP(northwind_order_details[[#This Row],[order_id]],northwind_orders[order_id],northwind_orders[ship_country]) -> Austria | G47: =INDEX(northwind_orders[],MATCH(northwind_order_details[[#This Row],[order_id]], northwind_orders[order_id], 0), MATCH("employee_id", northwind_orders[#Headers], 0)) -> 9 | H47: =northwind_order_details[[#This Row],[unit_price]]*northwind_order_details[[#This Row],[quantity]] -> 1242 | I47: =northwind_order_details[[#This Row],[purchase amount]]*northwind_order_details[[#This Row],[discount]] -> 310.5 | J47: =northwind_order_details[[#This Row],[purchase amount]]-northwind_order_details[[#This Row],[discount amount]] -> 931.5 | K47: =IF(northwind_order_details[[#This Row],[discount amount]]>0,"Yes","No") -> Yes | L47: =IF(northwind_order_details[[#This Row],[Revenue]]>1000,"High",IF(northwind_order_details[[#This Row],[Revenue]]>300,"Medium","Low")) -> Medium | M47: =IF(northwind_order_details[[#This Row],[unit_price]]=_xlfn.XLOOKUP(northwind_order_details[[#This Row],[product_id]],'Price Validation'!$D$2:$D$78,'Price Validation'!$E$2:$E$78),"Match","Mismatch") -> Mismatch
A48: 10263 | B48: 74 | C48: 8 | D48: 36 | E48: 0.25 | F48: =_xlfn.XLOOKUP(northwind_order_details[[#This Row],[order_id]],northwind_orders[order_id],northwind_orders[ship_country]) -> Austria | G48: =INDEX(northwind_orders[],MATCH(northwind_order_details[[#This Row],[order_id]], northwind_orders[order_id], 0), MATCH("employee_id", northwind_orders[#Headers], 0)) -> 9 | H48: =northwind_order_details[[#This Row],[unit_price]]*northwind_order_details[[#This Row],[quantity]] -> 288 | I48: =northwind_order_details[[#This Row],[purchase amount]]*northwind_order_details[[#This Row],[discount]] -> 72 | J48: =northwind_order_details[[#This Row],[purchase amount]]-northwind_order_details[[#This Row],[discount amount]] -> 216 | K48: =IF(northwind_order_details[[#This Row],[discount amount]]>0,"Yes","No") -> Yes | L48: =IF(northwind_order_details[[#This Row],[Revenue]]>1000,"High",IF(northwind_order_details[[#This Row],[Revenue]]>300,"Medium","Low")) -> Low | M48: =IF(northwind_order_details[[#This Row],[unit_price]]=_xlfn.XLOOKUP(northwind_order_details[[#This Row],[product_id]],'Price Validation'!$D$2:$D$78,'Price Validation'!$E$2:$E$78),"Match","Mismatch") -> Mismatch
A49: 10264 | B49: 2 | C49: 15.2 | D49: 35 | E49: 0 | F49: =_xlfn.XLOOKUP(northwind_order_details[[#This Row],[order_id]],northwind_orders[order_id],northwind_orders[ship_country]) -> Sweden | G49: =INDEX(northwind_orders[],MATCH(northwind_order_details[[#This Row],[order_id]], northwind_orders[order_id], 0), MATCH("employee_id", northwind_orders[#Headers], 0)) -> 6 | H49: =northwind_order_details[[#This Row],[unit_price]]*northwind_order_details[[#This Row],[quantity]] -> 532 | I49: =northwind_order_details[[#This Row],[purchase amount]]*northwind_order_details[[#This Row],[discount]] -> 0 | J49: =northwind_order_details[[#This Row],[purchase amount]]-northwind_order_details[[#This Row],[discount amount]] -> 532 | K49: =IF(northwind_order_details[[#This Row],[discount amount]]>0,"Yes","No") -> No | L49: =IF(northwind_order_details[[#This Row],[Revenue]]>1000,"High",IF(northwind_order_details[[#This Row],[Revenue]]>300,"Medium","Low")) -> Medium | M49: =IF(northwind_order_details[[#This Row],[unit_price]]=_xlfn.XLOOKUP(northwind_order_details[[#This Row],[product_id]],'Price Validation'!$D$2:$D$78,'Price Validation'!$E$2:$E$78),"Match","Mismatch") -> Mismatch
A50: 10264 | B50: 41 | C50: 7.7 | D50: 25 | E50: 0.15 | F50: =_xlfn.XLOOKUP(northwind_order_details[[#This Row],[order_id]],northwind_orders[order_id],northwind_orders[ship_country]) -> Sweden | G50: =INDEX(northwind_orders[],MATCH(northwind_order_details[[#This Row],[order_id]], northwind_orders[order_id], 0), MATCH("employee_id", northwind_orders[#Headers], 0)) -> 6 | H50: =northwind_order_details[[#This Row],[unit_price]]*northwind_order_details[[#This Row],[quantity]] -> 192.5 | I50: =northwind_order_details[[#This Row],[purchase amount]]*northwind_order_details[[#This Row],[discount]] -> 28.875 | J50: =northwind_order_details[[#This Row],[purchase amount]]-northwind_order_details[[#This Row],[discount amount]] -> 163.625 | K50: =IF(northwind_order_details[[#This Row],[discount amount]]>0,"Yes","No") -> Yes | L50: =IF(northwind_order_details[[#This Row],[Revenue]]>1000,"High",IF(northwind_order_details[[#This Row],[Revenue]]>300,"Medium","Low")) -> Low | M50: =IF(northwind_order_details[[#This Row],[unit_price]]=_xlfn.XLOOKUP(northwind_order_details[[#This Row],[product_id]],'Price Validation'!$D$2:$D$78,'Price Validation'!$E$2:$E$78),"Match","Mismatch") -> Mismatch
A51: 10265 | B51: 17 | C51: 31.2 | D51: 30 | E51: 0 | F51: =_xlfn.XLOOKUP(northwind_order_details[[#This Row],[order_id]],northwind_orders[order_id],northwind_orders[ship_country]) -> France | G51: =INDEX(northwind_orders[],MATCH(northwind_order_details[[#This Row],[order_id]], northwind_orders[order_id], 0), MATCH("employee_id", northwind_orders[#Headers], 0)) -> 2 | H51: =northwind_order_details[[#This Row],[unit_price]]*northwind_order_details[[#This Row],[quantity]] -> 936 | I51: =northwind_order_details[[#This Row],[purchase amount]]*northwind_order_details[[#This Row],[discount]] -> 0 | J51: =northwind_order_details[[#This Row],[purchase amount]]-northwind_order_details[[#This Row],[discount amount]] -> 936 | K51: =IF(northwind_order_details[[#This Row],[discount amount]]>0,"Yes","No") -> No | L51: =IF(northwind_order_details[[#This Row],[Revenue]]>1000,"High",IF(northwind_order_details[[#This Row],[Revenue]]>300,"Medium","Low")) -> Medium | M51: =IF(northwind_order_details[[#This Row],[unit_price]]=_xlfn.XLOOKUP(northwind_order_details[[#This Row],[product_id]],'Price Validation'!$D$2:$D$78,'Price Validation'!$E$2:$E$78),"Match","Mismatch") -> Mismatch
A52: 10265 | B52: 70 | C52: 12 | D52: 20 | E52: 0 | F52: =_xlfn.XLOOKUP(northwind_order_details[[#This Row],[order_id]],northwind_orders[order_id],northwind_orders[ship_country]) -> France | G52: =INDEX(northwind_orders[],MATCH(northwind_order_details[[#This Row],[order_id]], northwind_orders[order_id], 0), MATCH("employee_id", northwind_orders[#Headers], 0)) -> 2 | H52: =northwind_order_details[[#This Row],[unit_price]]*northwind_order_details[[#This Row],[quantity]] -> 240 | I52: =northwind_order_details[[#This Row],[purchase amount]]*northwind_order_details[[#This Row],[discount]] -> 0 | J52: =northwind_order_details[[#This Row],[purchase amount]]-northwind_order_details[[#This Row],[discount amount]] -> 240 | K52: =IF(northwind_order_details[[#This Row],[discount amount]]>0,"Yes","No") -> No | L52: =IF(northwind_order_details[[#This Row],[Revenue]]>1000,"High",IF(northwind_order_details[[#This Row],[Revenue]]>300,"Medium","Low")) -> Low | M52: =IF(northwind_order_details[[#This Row],[unit_price]]=_xlfn.XLOOKUP(northwind_order_details[[#This Row],[product_id]],'Price Validation'!$D$2:$D$78,'Price Validation'!$E$2:$E$78),"Match","Mismatch") -> Mismatch
A53: 10266 | B53: 12 | C53: 30.4 | D53: 12 | E53: 0.05 | F53: =_xlfn.XLOOKUP(northwind_order_details[[#This Row],[order_id]],northwind_orders[order_id],northwind_orders[ship_country]) -> Finland | G53: =INDEX(northwind_orders[],MATCH(northwind_order_details[[#This Row],[order_id]], northwind_orders[order_id], 0), MATCH("employee_id", northwind_orders[#Headers], 0)) -> 3 | H53: =northwind_order_details[[#This Row],[unit_price]]*northwind_order_details[[#This Row],[quantity]] -> 364.8 | I53: =northwind_order_details[[#This Row],[purchase amount]]*northwind_order_details[[#This Row],[discount]] -> 18.24 | J53: =northwind_order_details[[#This Row],[purchase amount]]-northwind_order_details[[#This Row],[discount amount]] -> 346.56 | K53: =IF(northwind_order_details[[#This Row],[discount amount]]>0,"Yes","No") -> Yes | L53: =IF(northwind_order_details[[#This Row],[Revenue]]>1000,"High",IF(northwind_order_details[[#This Row],[Revenue]]>300,"Medium","Low")) -> Medium | M53: =IF(northwind_order_details[[#This Row],[unit_price]]=_xlfn.XLOOKUP(northwind_order_details[[#This Row],[product_id]],'Price Validation'!$D$2:$D$78,'Price Validation'!$E$2:$E$78),"Match","Mismatch") -> Mismatch
A54: 10267 | B54: 40 | C54: 14.7 | D54: 50 | E54: 0 | F54: =_xlfn.XLOOKUP(northwind_order_details[[#This Row],[order_id]],northwind_orders[order_id],northwind_orders[ship_country]) -> Germany | G54: =INDEX(northwind_orders[],MATCH(northwind_order_details[[#This Row],[order_id]], northwind_orders[order_id], 0), MATCH("employee_id", northwind_orders[#Headers], 0)) -> 4 | H54: =northwind_order_details[[#This Row],[unit_price]]*northwind_order_details[[#This Row],[quantity]] -> 735 | I54: =northwind_order_details[[#This Row],[purchase amount]]*northwind_order_details[[#This Row],[discount]] -> 0 | J54: =northwind_order_details[[#This Row],[purchase amount]]-northwind_order_details[[#This Row],[discount amount]] -> 735 | K54: =IF(northwind_order_details[[#This Row],[discount amount]]>0,"Yes","No") -> No | L54: =IF(northwind_order_details[[#This Row],[Revenue]]>1000,"High",IF(northwind_order_details[[#This Row],[Revenue]]>300,"Medium","Low")) -> Medium | M54: =IF(northwind_order_details[[#This Row],[unit_price]]=_xlfn.XLOOKUP(northwind_order_details[[#This Row],[product_id]],'Price Validation'!$D$2:$D$78,'Price Validation'!$E$2:$E$78),"Match","Mismatch") -> Mismatch
A55: 10267 | B55: 59 | C55: 44 | D55: 70 | E55: 0.15 | F55: =_xlfn.XLOOKUP(northwind_order_details[[#This Row],[order_id]],northwind_orders[order_id],northwind_orders[ship_country]) -> Germany | G55: =INDEX(northwind_orders[],MATCH(northwind_order_details[[#This Row],[order_id]], northwind_orders[order_id], 0), MATCH("employee_id", northwind_orders[#Headers], 0)) -> 4 | H55: =northwind_order_details[[#This Row],[unit_price]]*northwind_order_details[[#This Row],[quantity]] -> 3080 | I55: =northwind_order_details[[#This Row],[purchase amount]]*northwind_order_details[[#This Row],[discount]] -> 462 | J55: =northwind_order_details[[#This Row],[purchase amount]]-northwind_order_details[[#This Row],[discount amount]] -> 2618 | K55: =IF(northwind_order_details[[#This Row],[discount amount]]>0,"Yes","No") -> Yes | L55: =IF(northwind_order_details[[#This Row],[Revenue]]>1000,"High",IF(northwind_order_details[[#This Row],[Revenue]]>300,"Medium","Low")) -> High | M55: =IF(northwind_order_details[[#This Row],[unit_price]]=_xlfn.XLOOKUP(northwind_order_details[[#This Row],[product_id]],'Price Validation'!$D$2:$D$78,'Price Validation'!$E$2:$E$78),"Match","Mismatch") -> Mismatch
A56: 10267 | B56: 76 | C56: 14.4 | D56: 15 | E56: 0.15 | F56: =_xlfn.XLOOKUP(northwind_order_details[[#This Row],[order_id]],northwind_orders[order_id],northwind_orders[ship_country]) -> Germany | G56: =INDEX(northwind_orders[],MATCH(northwind_order_details[[#This Row],[order_id]], northwind_orders[order_id], 0), MATCH("employee_id", northwind_orders[#Headers], 0)) -> 4 | H56: =northwind_order_details[[#This Row],[unit_price]]*northwind_order_details[[#This Row],[quantity]] -> 216 | I56: =northwind_order_details[[#This Row],[purchase amount]]*northwind_order_details[[#This Row],[discount]] -> 32.4 | J56: =northwind_order_details[[#This Row],[purchase amount]]-northwind_order_details[[#This Row],[discount amount]] -> 183.6 | K56: =IF(northwind_order_details[[#This Row],[discount amount]]>0,"Yes","No") -> Yes | L56: =IF(northwind_order_details[[#This Row],[Revenue]]>1000,"High",IF(northwind_order_details[[#This Row],[Revenue]]>300,"Medium","Low")) -> Low | M56: =IF(northwind_order_details[[#This Row],[unit_price]]=_xlfn.XLOOKUP(northwind_order_details[[#This Row],[product_id]],'Price Validation'!$D$2:$D$78,'Price Validation'!$E$2:$E$78),"Match","Mismatch") -> Mismatch
A57: 10268 | B57: 29 | C57: 99 | D57: 10 | E57: 0 | F57: =_xlfn.XLOOKUP(northwind_order_details[[#This Row],[order_id]],northwind_orders[order_id],northwind_orders[ship_country]) -> Venezuela | G57: =INDEX(northwind_orders[],MATCH(northwind_order_details[[#This Row],[order_id]], northwind_orders[order_id], 0), MATCH("employee_id", northwind_orders[#Headers], 0)) -> 8 | H57: =northwind_order_details[[#This Row],[unit_price]]*northwind_order_details[[#This Row],[quantity]] -> 990 | I57: =northwind_order_details[[#This Row],[purchase amount]]*northwind_order_details[[#This Row],[discount]] -> 0 | J57: =northwind_order_details[[#This Row],[purchase amount]]-northwind_order_details[[#This Row],[discount amount]] -> 990 | K57: =IF(northwind_order_details[[#This Row],[discount amount]]>0,"Yes","No") -> No | L57: =IF(northwind_order_details[[#This Row],[Revenue]]>1000,"High",IF(northwind_order_details[[#This Row],[Revenue]]>300,"Medium","Low")) -> Medium | M57: =IF(northwind_order_details[[#This Row],[unit_price]]=_xlfn.XLOOKUP(northwind_order_details[[#This Row],[product_id]],'Price Validation'!$D$2:$D$78,'Price Validation'!$E$2:$E$78),"Match","Mismatch") -> Mismatch
A58: 10268 | B58: 72 | C58: 27.8 | D58: 4 | E58: 0 | F58: =_xlfn.XLOOKUP(northwind_order_details[[#This Row],[order_id]],northwind_orders[order_id],northwind_orders[ship_country]) -> Venezuela | G58: =INDEX(northwind_orders[],MATCH(northwind_order_details[[#This Row],[order_id]], northwind_orders[order_id], 0), MATCH("employee_id", northwind_orders[#Headers], 0)) -> 8 | H58: =northwind_order_details[[#This Row],[unit_price]]*northwind_order_details[[#This Row],[quantity]] -> 111.2 | I58: =northwind_order_details[[#This Row],[purchase amount]]*northwind_order_details[[#This Row],[discount]] -> 0 | J58: =northwind_order_details[[#This Row],[purchase amount]]-northwind_order_details[[#This Row],[discount amount]] -> 111.2 | K58: =IF(northwind_order_details[[#This Row],[discount amount]]>0,"Yes","No") -> No | L58: =IF(northwind_order_details[[#This Row],[Revenue]]>1000,"High",IF(northwind_order_details[[#This Row],[Revenue]]>300,"Medium","Low")) -> Low | M58: =IF(northwind_order_details[[#This Row],[unit_price]]=_xlfn.XLOOKUP(northwind_order_details[[#This Row],[product_id]],'Price Validation'!$D$2:$D$78,'Price Validation'!$E$2:$E$78),"Match","Mismatch") -> Mismatch
A59: 10269 | B59: 33 | C59: 2 | D59: 60 | E59: 0.05 | F59: =_xlfn.XLOOKUP(northwind_order_details[[#This Row],[order_id]],northwind_orders[order_id],northwind_orders[ship_country]) -> USA | G59: =INDEX(northwind_orders[],MATCH(northwind_order_details[[#This Row],[order_id]], northwind_orders[order_id], 0), MATCH("employee_id", northwind_orders[#Headers], 0)) -> 5 | H59: =northwind_order_details[[#This Row],[unit_price]]*northwind_order_details[[#This Row],[quantity]] -> 120 | I59: =northwind_order_details[[#This Row],[purchase amount]]*northwind_order_details[[#This Row],[discount]] -> 6 | J59: =northwind_order_details[[#This Row],[purchase amount]]-northwind_order_details[[#This Row],[discount amount]] -> 114 | K59: =IF(northwind_order_details[[#This Row],[discount amount]]>0,"Yes","No") -> Yes | L59: =IF(northwind_order_details[[#This Row],[Revenue]]>1000,"High",IF(northwind_order_details[[#This Row],[Revenue]]>300,"Medium","Low")) -> Low | M59: =IF(northwind_order_details[[#This Row],[unit_price]]=_xlfn.XLOOKUP(northwind_order_details[[#This Row],[product_id]],'Price Validation'!$D$2:$D$78,'Price Validation'!$E$2:$E$78),"Match","Mismatch") -> Mismatch
A60: 10269 | B60: 72 | C60: 27.8 | D60: 20 | E60: 0.05 | F60: =_xlfn.XLOOKUP(northwind_order_details[[#This Row],[order_id]],northwind_orders[order_id],northwind_orders[ship_country]) -> USA | G60: =INDEX(northwind_orders[],MATCH(northwind_order_details[[#This Row],[order_id]], northwind_orders[order_id], 0), MATCH("employee_id", northwind_orders[#Headers], 0)) -> 5 | H60: =northwind_order_details[[#This Row],[unit_price]]*northwind_order_details[[#This Row],[quantity]] -> 556 | I60: =northwind_order_details[[#This Row],[purchase amount]]*northwind_order_details[[#This Row],[discount]] -> 27.8 | J60: =northwind_order_details[[#This Row],[purchase amount]]-northwind_order_details[[#This Row],[discount amount]] -> 528.2 | K60: =IF(northwind_order_details[[#This Row],[discount amount]]>0,"Yes","No") -> Yes | L60: =IF(northwind_order_details[[#This Row],[Revenue]]>1000,"High",IF(northwind_order_details[[#This Row],[Revenue]]>300,"Medium","Low")) -> Medium | M60: =IF(northwind_order_details[[#This Row],[unit_price]]=_xlfn.XLOOKUP(northwind_order_details[[#This Row],[product_id]],'Price Validation'!$D$2:$D$78,'Price Validation'!$E$2:$E$78),"Match","Mismatch") -> Mismatch
A61: 10270 | B61: 36 | C61: 15.2 | D61: 30 | E61: 0 | F61: =_xlfn.XLOOKUP(northwind_order_details[[#This Row],[order_id]],northwind_orders[order_id],northwind_orders[ship_country]) -> Finland | G61: =INDEX(northwind_orders[],MATCH(northwind_order_details[[#This Row],[order_id]], northwind_orders[order_id], 0), MATCH("employee_id", northwind_orders[#Headers], 0)) -> 1 | H61: =northwind_order_details[[#This Row],[unit_price]]*northwind_order_details[[#This Row],[quantity]] -> 456 | I61: =northwind_order_details[[#This Row],[purchase amount]]*northwind_order_details[[#This Row],[discount]] -> 0 | J61: =northwind_order_details[[#This Row],[purchase amount]]-northwind_order_details[[#This Row],[discount amount]] -> 456 | K61: =IF(northwind_order_details[[#This Row],[discount amount]]>0,"Yes","No") -> No | L61: =IF(northwind_order_details[[#This Row],[Revenue]]>1000,"High",IF(northwind_order_details[[#This Row],[Revenue]]>300,"Medium","Low")) -> Medium | M61: =IF(northwind_order_details[[#This Row],[unit_price]]=_xlfn.XLOOKUP(northwind_order_details[[#This Row],[product_id]],'Price Validation'!$D$2:$D$78,'Price Validation'!$E$2:$E$78),"Match","Mismatch") -> Mismatch
A62: 10270 | B62: 43 | C62: 36.8 | D62: 25 | E62: 0 | F62: =_xlfn.XLOOKUP(northwind_order_details[[#This Row],[order_id]],northwind_orders[order_id],northwind_orders[ship_country]) -> Finland | G62: =INDEX(northwind_orders[],MATCH(northwind_order_details[[#This Row],[order_id]], northwind_orders[order_id], 0), MATCH("employee_id", northwind_orders[#Headers], 0)) -> 1 | H62: =northwind_order_details[[#This Row],[unit_price]]*northwind_order_details[[#This Row],[quantity]] -> 920 | I62: =northwind_order_details[[#This Row],[purchase amount]]*northwind_order_details[[#This Row],[discount]] -> 0 | J62: =northwind_order_details[[#This Row],[purchase amount]]-northwind_order_details[[#This Row],[discount amount]] -> 920 | K62: =IF(northwind_order_details[[#This Row],[discount amount]]>0,"Yes","No") -> No | L62: =IF(northwind_order_details[[#This Row],[Revenue]]>1000,"High",IF(northwind_order_details[[#This Row],[Revenue]]>300,"Medium","Low")) -> Medium | M62: =IF(northwind_order_details[[#This Row],[unit_price]]=_xlfn.XLOOKUP(northwind_order_details[[#This Row],[product_id]],'Price Validation'!$D$2:$D$78,'Price Validation'!$E$2:$E$78),"Match","Mismatch") -> Mismatch
A63: 10271 | B63: 33 | C63: 2 | D63: 24 | E63: 0 | F63: =_xlfn.XLOOKUP(northwind_order_details[[#This Row],[order_id]],northwind_orders[order_id],northwind_orders[ship_country]) -> USA | G63: =INDEX(northwind_orders[],MATCH(northwind_order_details[[#This Row],[order_id]], northwind_orders[order_id], 0), MATCH("employee_id", northwind_orders[#Headers], 0)) -> 6 | H63: =northwind_order_details[[#This Row],[unit_price]]*northwind_order_details[[#This Row],[quantity]] -> 48 | I63: =northwind_order_details[[#This Row],[purchase amount]]*northwind_order_details[[#This Row],[discount]] -> 0 | J63: =northwind_order_details[[#This Row],[purchase amount]]-northwind_order_details[[#This Row],[discount amount]] -> 48 | K63: =IF(northwind_order_details[[#This Row],[discount amount]]>0,"Yes","No") -> No | L63: =IF(northwind_order_details[[#This Row],[Revenue]]>1000,"High",IF(northwind_order_details[[#This Row],[Revenue]]>300,"Medium","Low")) -> Low | M63: =IF(northwind_order_details[[#This Row],[unit_price]]=_xlfn.XLOOKUP(northwind_order_details[[#This Row],[product_id]],'Price Validation'!$D$2:$D$78,'Price Validation'!$E$2:$E$78),"Match","Mismatch") -> Mismatch
A64: 10272 | B64: 20 | C64: 64.8 | D64: 6 | E64: 0 | F64: =_xlfn.XLOOKUP(northwind_order_details[[#This Row],[order_id]],northwind_orders[order_id],northwind_orders[ship_country]) -> USA | G64: =INDEX(northwind_orders[],MATCH(northwind_order_details[[#This Row],[order_id]], northwind_orders[order_id], 0), MATCH("employee_id", northwind_orders[#Headers], 0)) -> 6 | H64: =northwind_order_details[[#This Row],[unit_price]]*northwind_order_details[[#This Row],[quantity]] -> 388.8 | I64: =northwind_order_details[[#This Row],[purchase amount]]*northwind_order_details[[#This Row],[discount]] -> 0 | J64: =northwind_order_details[[#This Row],[purchase amount]]-northwind_order_details[[#This Row],[discount amount]] -> 388.8 | K64: =IF(northwind_order_details[[#This Row],[discount amount]]>0,"Yes","No") -> No | L64: =IF(northwind_order_details[[#This Row],[Revenue]]>1000,"High",IF(northwind_order_details[[#This Row],[Revenue]]>300,"Medium","Low")) -> Medium | M64: =IF(northwind_order_details[[#This Row],[unit_price]]=_xlfn.XLOOKUP(northwind_order_details[[#This Row],[product_id]],'Price Validation'!$D$2:$D$78,'Price Validation'!$E$2:$E$78),"Match","Mismatch") -> Mismatch
A65: 10272 | B65: 31 | C65: 10 | D65: 40 | E65: 0 | F65: =_xlfn.XLOOKUP(northwind_order_details[[#This Row],[order_id]],northwind_orders[order_id],northwind_orders[ship_country]) -> USA | G65: =INDEX(northwind_orders[],MATCH(northwind_order_details[[#This Row],[order_id]], northwind_orders[order_id], 0), MATCH("employee_id", northwind_orders[#Headers], 0)) -> 6 | H65: =northwind_order_details[[#This Row],[unit_price]]*northwind_order_details[[#This Row],[quantity]] -> 400 | I65: =northwind_order_details[[#This Row],[purchase amount]]*northwind_order_details[[#This Row],[discount]] -> 0 | J65: =northwind_order_details[[#This Row],[purchase amount]]-northwind_order_details[[#This Row],[discount amount]] -> 400 | K65: =IF(northwind_order_details[[#This Row],[discount amount]]>0,"Yes","No") -> No | L65: =IF(northwind_order_details[[#This Row],[Revenue]]>1000,"High",IF(northwind_order_details[[#This Row],[Revenue]]>300,"Medium","Low")) -> Medium | M65: =IF(northwind_order_details[[#This Row],[unit_price]]=_xlfn.XLOOKUP(northwind_order_details[[#This Row],[product_id]],'Price Validation'!$D$2:$D$78,'Price Validation'!$E$2:$E$78),"Match","Mismatch") -> Mismatch
A66: 10272 | B66: 72 | C66: 27.8 | D66: 24 | E66: 0 | F66: =_xlfn.XLOOKUP(northwind_order_details[[#This Row],[order_id]],northwind_orders[order_id],northwind_orders[ship_country]) -> USA | G66: =INDEX(northwind_orders[],MATCH(northwind_order_details[[#This Row],[order_id]], northwind_orders[order_id], 0), MATCH("employee_id", northwind_orders[#Headers], 0)) -> 6 | H66: =northwind_order_details[[#This Row],[unit_price]]*northwind_order_details[[#This Row],[quantity]] -> 667.2 | I66: =northwind_order_details[[#This Row],[purchase amount]]*northwind_order_details[[#This Row],[discount]] -> 0 | J66: =northwind_order_details[[#This Row],[purchase amount]]-northwind_order_details[[#This Row],[discount amount]] -> 667.2 | K66: =IF(northwind_order_details[[#This Row],[discount amount]]>0,"Yes","No") -> No | L66: =IF(northwind_order_details[[#This Row],[Revenue]]>1000,"High",IF(northwind_order_details[[#This Row],[Revenue]]>300,"Medium","Low")) -> Medium | M66: =IF(northwind_order_details[[#This Row],[unit_price]]=_xlfn.XLOOKUP(northwind_order_details[[#This Row],[product_id]],'Price Validation'!$D$2:$D$78,'Price Validation'!$E$2:$E$78),"Match","Mismatch") -> Mismatch
A67: 10273 | B67: 10 | C67: 24.8 | D67: 24 | E67: 0.05 | F67: =_xlfn.XLOOKUP(northwind_order_details[[#This Row],[order_id]],northwind_orders[order_id],northwind_orders[ship_country]) -> Germany | G67: =INDEX(northwind_orders[],MATCH(northwind_order_details[[#This Row],[order_id]], northwind_orders[order_id], 0), MATCH("employee_id", northwind_orders[#Headers], 0)) -> 3 | H67: =northwind_order_details[[#This Row],[unit_price]]*northwind_order_details[[#This Row],[quantity]] -> 595.2 | I67: =northwind_order_details[[#This Row],[purchase amount]]*northwind_order_details[[#This Row],[discount]] -> 29.76 | J67: =northwind_order_details[[#This Row],[purchase amount]]-northwind_order_details[[#This Row],[discount amount]] -> 565.44 | K67: =IF(northwind_order_details[[#This Row],[discount amount]]>0,"Yes","No") -> Yes | L67: =IF(northwind_order_details[[#This Row],[Revenue]]>1000,"High",IF(northwind_order_details[[#This Row],[Revenue]]>300,"Medium","Low")) -> Medium | M67: =IF(northwind_order_details[[#This Row],[unit_price]]=_xlfn.XLOOKUP(northwind_order_details[[#This Row],[product_id]],'Price Validation'!$D$2:$D$78,'Price Validation'!$E$2:$E$78),"Match","Mismatch") -> Mismatch
A68: 10273 | B68: 31 | C68: 10 | D68: 15 | E68: 0.05 | F68: =_xlfn.XLOOKUP(northwind_order_details[[#This Row],[order_id]],northwind_orders[order_id],northwind_orders[ship_country]) -> Germany | G68: =INDEX(northwind_orders[],MATCH(northwind_order_details[[#This Row],[order_id]], northwind_orders[order_id], 0), MATCH("employee_id", northwind_orders[#Headers], 0)) -> 3 | H68: =northwind_order_details[[#This Row],[unit_price]]*northwind_order_details[[#This Row],[quantity]] -> 150 | I68: =northwind_order_details[[#This Row],[purchase amount]]*northwind_order_details[[#This Row],[discount]] -> 7.5 | J68: =northwind_order_details[[#This Row],[purchase amount]]-northwind_order_details[[#This Row],[discount amount]] -> 142.5 | K68: =IF(northwind_order_details[[#This Row],[discount amount]]>0,"Yes","No") -> Yes | L68: =IF(northwind_order_details[[#This Row],[Revenue]]>1000,"High",IF(northwind_order_details[[#This Row],[Revenue]]>300,"Medium","Low")) -> Low | M68: =IF(northwind_order_details[[#This Row],[unit_price]]=_xlfn.XLOOKUP(northwind_order_details[[#This Row],[product_id]],'Price Validation'!$D$2:$D$78,'Price Validation'!$E$2:$E$78),"Match","Mismatch") -> Mismatch
A69: 10273 | B69: 33 | C69: 2 | D69: 20 | E69: 0 | F69: =_xlfn.XLOOKUP(northwind_order_details[[#This Row],[order_id]],northwind_orders[order_id],northwind_orders[ship_country]) -> Germany | G69: =INDEX(northwind_orders[],MATCH(northwind_order_details[[#This Row],[order_id]], northwind_orders[order_id], 0), MATCH("employee_id", northwind_orders[#Headers], 0)) -> 3 | H69: =northwind_order_details[[#This Row],[unit_price]]*northwind_order_details[[#This Row],[quantity]] -> 40 | I69: =northwind_order_details[[#This Row],[purchase amount]]*northwind_order_details[[#This Row],[discount]] -> 0 | J69: =northwind_order_details[[#This Row],[purchase amount]]-northwind_order_details[[#This Row],[discount amount]] -> 40 | K69: =IF(northwind_order_details[[#This Row],[discount amount]]>0,"Yes","No") -> No | L69: =IF(northwind_order_details[[#This Row],[Revenue]]>1000,"High",IF(northwind_order_details[[#This Row],[Revenue]]>300,"Medium","Low")) -> Low | M69: =IF(northwind_order_details[[#This Row],[unit_price]]=_xlfn.XLOOKUP(northwind_order_details[[#This Row],[product_id]],'Price Validation'!$D$2:$D$78,'Price Validation'!$E$2:$E$78),"Match","Mismatch") -> Mismatch
A70: 10273 | B70: 40 | C70: 14.7 | D70: 60 | E70: 0.05 | F70: =_xlfn.XLOOKUP(northwind_order_details[[#This Row],[order_id]],northwind_orders[order_id],northwind_orders[ship_country]) -> Germany | G70: =INDEX(northwind_orders[],MATCH(northwind_order_details[[#This Row],[order_id]], northwind_orders[order_id], 0), MATCH("employee_id", northwind_orders[#Headers], 0)) -> 3 | H70: =northwind_order_details[[#This Row],[unit_price]]*northwind_order_details[[#This Row],[quantity]] -> 882 | I70: =northwind_order_details[[#This Row],[purchase amount]]*northwind_order_details[[#This Row],[discount]] -> 44.1 | J70: =northwind_order_details[[#This Row],[purchase amount]]-northwind_order_details[[#This Row],[discount amount]] -> 837.9 | K70: =IF(northwind_order_details[[#This Row],[discount amount]]>0,"Yes","No") -> Yes | L70: =IF(northwind_order_details[[#This Row],[Revenue]]>1000,"High",IF(northwind_order_details[[#This Row],[Revenue]]>300,"Medium","Low")) -> Medium | M70: =IF(northwind_order_details[[#This Row],[unit_price]]=_xlfn.XLOOKUP(northwind_order_details[[#This Row],[product_id]],'Price Validation'!$D$2:$D$78,'Price Validation'!$E$2:$E$78),"Match","Mismatch") -> Mismatch
A71: 10273 | B71: 76 | C71: 14.4 | D71: 33 | E71: 0.05 | F71: =_xlfn.XLOOKUP(northwind_order_details[[#This Row],[order_id]],northwind_orders[order_id],northwind_orders[ship_country]) -> Germany | G71: =INDEX(northwind_orders[],MATCH(northwind_order_details[[#This Row],[order_id]], northwind_orders[order_id], 0), MATCH("employee_id", northwind_orders[#Headers], 0)) -> 3 | H71: =northwind_order_details[[#This Row],[unit_price]]*northwind_order_details[[#This Row],[quantity]] -> 475.2 | I71: =northwind_order_details[[#This Row],[purchase amount]]*northwind_order_details[[#This Row],[discount]] -> 23.76 | J71: =northwind_order_details[[#This Row],[purchase amount]]-northwind_order_details[[#This Row],[discount amount]] -> 451.44 | K71: =IF(northwind_order_details[[#This Row],[discount amount]]>0,"Yes","No") -> Yes | L71: =IF(northwind_order_details[[#This Row],[Revenue]]>1000,"High",IF(northwind_order_details[[#This Row],[Revenue]]>300,"Medium","Low")) -> Medium | M71: =IF(northwind_order_details[[#This Row],[unit_price]]=_xlfn.XLOOKUP(northwind_order_details[[#This Row],[product_id]],'Price Validation'!$D$2:$D$78,'Price Validation'!$E$2:$E$78),"Match","Mismatch") -> Mismatch
A72: 10274 | B72: 71 | C72: 17.2 | D72: 20 | E72: 0 | F72: =_xlfn.XLOOKUP(northwind_order_details[[#This Row],[order_id]],northwind_orders[order_id],northwind_orders[ship_country]) -> France | G72: =INDEX(northwind_orders[],MATCH(northwind_order_details[[#This Row],[order_id]], northwind_orders[order_id], 0), MATCH("employee_id", northwind_orders[#Headers], 0)) -> 6 | H72: =northwind_order_details[[#This Row],[unit_price]]*northwind_order_details[[#This Row],[quantity]] -> 344 | I72: =northwind_order_details[[#This Row],[purchase amount]]*northwind_order_details[[#This Row],[discount]] -> 0 | J72: =northwind_order_details[[#This Row],[purchase amount]]-northwind_order_details[[#This Row],[discount amount]] -> 344 | K72: =IF(northwind_order_details[[#This Row],[discount amount]]>0,"Yes","No") -> No | L72: =IF(northwind_order_details[[#This Row],[Revenue]]>1000,"High",IF(northwind_order_details[[#This Row],[Revenue]]>300,"Medium","Low")) -> Medium | M72: =IF(northwind_order_details[[#This Row],[unit_price]]=_xlfn.XLOOKUP(northwind_order_details[[#This Row],[product_id]],'Price Validation'!$D$2:$D$78,'Price Validation'!$E$2:$E$78),"Match","Mismatch") -> Mismatch
A73: 10274 | B73: 72 | C73: 27.8 | D73: 7 | E73: 0 | F73: =_xlfn.XLOOKUP(northwind_order_details[[#This Row],[order_id]],northwind_orders[order_id],northwind_orders[ship_country]) -> France | G73: =INDEX(northwind_orders[],MATCH(northwind_order_details[[#This Row],[order_id]], northwind_orders[order_id], 0), MATCH("employee_id", northwind_orders[#Headers], 0)) -> 6 | H73: =northwind_order_details[[#This Row],[unit_price]]*northwind_order_details[[#This Row],[quantity]] -> 194.6 | I73: =northwind_order_details[[#This Row],[purchase amount]]*northwind_order_details[[#This Row],[discount]] -> 0 | J73: =northwind_order_details[[#This Row],[purchase amount]]-northwind_order_details[[#This Row],[discount amount]] -> 194.6 | K73: =IF(northwind_order_details[[#This Row],[discount amount]]>0,"Yes","No") -> No | L73: =IF(northwind_order_details[[#This Row],[Revenue]]>1000,"High",IF(northwind_order_details[[#This Row],[Revenue]]>300,"Medium","Low")) -> Low | M73: =IF(northwind_order_details[[#This Row],[unit_price]]=_xlfn.XLOOKUP(northwind_order_details[[#This Row],[product_id]],'Price Validation'!$D$2:$D$78,'Price Validation'!$E$2:$E$78),"Match","Mismatch") -> Mismatch
A74: 10275 | B74: 24 | C74: 3.6 | D74: 12 | E74: 0.05 | F74: =_xlfn.XLOOKUP(northwind_order_details[[#This Row],[order_id]],northwind_orders[order_id],northwind_orders[ship_country]) -> Italy | G74: =INDEX(northwind_orders[],MATCH(northwind_order_details[[#This Row],[order_id]], northwind_orders[order_id], 0), MATCH("employee_id", northwind_orders[#Headers], 0)) -> 1 | H74: =northwind_order_details[[#This Row],[unit_price]]*northwind_order_details[[#This Row],[quantity]] -> 43.2 | I74: =northwind_order_details[[#This Row],[purchase amount]]*northwind_order_details[[#This Row],[discount]] -> 2.16 | J74: =northwind_order_details[[#This Row],[purchase amount]]-northwind_order_details[[#This Row],[discount amount]] -> 41.04 | K74: =IF(northwind_order_details[[#This Row],[discount amount]]>0,"Yes","No") -> Yes | L74: =IF(northwind_order_details[[#This Row],[Revenue]]>1000,"High",IF(northwind_order_details[[#This Row],[Revenue]]>300,"Medium","Low")) -> Low | M74: =IF(northwind_order_details[[#This Row],[unit_price]]=_xlfn.XLOOKUP(northwind_order_details[[#This Row],[product_id]],'Price Validation'!$D$2:$D$78,'Price Validation'!$E$2:$E$78),"Match","Mismatch") -> Mismatch
A75: 10275 | B75: 59 | C75: 44 | D75: 6 | E75: 0.05 | F75: =_xlfn.XLOOKUP(northwind_order_details[[#This Row],[order_id]],northwind_orders[order_id],northwind_orders[ship_country]) -> Italy | G75: =INDEX(northwind_orders[],MATCH(northwind_order_details[[#This Row],[order_id]], northwind_orders[order_id], 0), MATCH("employee_id", northwind_orders[#Headers], 0)) -> 1 | H75: =northwind_order_details[[#This Row],[unit_price]]*northwind_order_details[[#This Row],[quantity]] -> 264 | I75: =northwind_order_details[[#This Row],[purchase amount]]*northwind_order_details[[#This Row],[discount]] -> 13.2 | J75: =northwind_order_details[[#This Row],[purchase amount]]-northwind_order_details[[#This Row],[discount amount]] -> 250.8 | K75: =IF(northwind_order_details[[#This Row],[discount amount]]>0,"Yes","No") -> Yes | L75: =IF(northwind_order_details[[#This Row],[Revenue]]>1000,"High",IF(northwind_order_details[[#This Row],[Revenue]]>300,"Medium","Low")) -> Low | M75: =IF(northwind_order_details[[#This Row],[unit_price]]=_xlfn.XLOOKUP(northwind_order_details[[#This Row],[product_id]],'Price Validation'!$D$2:$D$78,'Price Validation'!$E$2:$E$78),"Match","Mismatch") -> Mismatch
A76: 10276 | B76: 10 | C76: 24.8 | D76: 15 | E76: 0 | F76: =_xlfn.XLOOKUP(northwind_order_details[[#This Row],[order_id]],northwind_orders[order_id],northwind_orders[ship_country]) -> Mexico | G76: =INDEX(northwind_orders[],MATCH(northwind_order_details[[#This Row],[order_id]], northwind_orders[order_id], 0), MATCH("employee_id", northwind_orders[#Headers], 0)) -> 8 | H76: =northwind_order_details[[#This Row],[unit_price]]*northwind_order_details[[#This Row],[quantity]] -> 372 | I76: =northwind_order_details[[#This Row],[purchase amount]]*northwind_order_details[[#This Row],[discount]] -> 0 | J76: =northwind_order_details[[#This Row],[purchase amount]]-northwind_order_details[[#This Row],[discount amount]] -> 372 | K76: =IF(northwind_order_details[[#This Row],[discount amount]]>0,"Yes","No") -> No | L76: =IF(northwind_order_details[[#This Row],[Revenue]]>1000,"High",IF(northwind_order_details[[#This Row],[Revenue]]>300,"Medium","Low")) -> Medium | M76: =IF(northwind_order_details[[#This Row],[unit_price]]=_xlfn.XLOOKUP(northwind_order_details[[#This Row],[product_id]],'Price Validation'!$D$2:$D$78,'Price Validation'!$E$2:$E$78),"Match","Mismatch") -> Mismatch
A77: 10276 | B77: 13 | C77: 4.8 | D77: 10 | E77: 0 | F77: =_xlfn.XLOOKUP(northwind_order_details[[#This Row],[order_id]],northwind_orders[order_id],northwind_orders[ship_country]) -> Mexico | G77: =INDEX(northwind_orders[],MATCH(northwind_order_details[[#This Row],[order_id]], northwind_orders[order_id], 0), MATCH("employee_id", northwind_orders[#Headers], 0)) -> 8 | H77: =northwind_order_details[[#This Row],[unit_price]]*northwind_order_details[[#This Row],[quantity]] -> 48 | I77: =northwind_order_details[[#This Row],[purchase amount]]*northwind_order_details[[#This Row],[discount]] -> 0 | J77: =northwind_order_details[[#This Row],[purchase amount]]-northwind_order_details[[#This Row],[discount amount]] -> 48 | K77: =IF(northwind_order_details[[#This Row],[discount amount]]>0,"Yes","No") -> No | L77: =IF(northwind_order_details[[#This Row],[Revenue]]>1000,"High",IF(northwind_order_details[[#This Row],[Revenue]]>300,"Medium","Low")) -> Low | M77: =IF(northwind_order_details[[#This Row],[unit_price]]=_xlfn.XLOOKUP(northwind_order_details[[#This Row],[product_id]],'Price Validation'!$D$2:$D$78,'Price Validation'!$E$2:$E$78),"Match","Mismatch") -> Mismatch
A78: 10277 | B78: 28 | C78: 36.4 | D78: 20 | E78: 0 | F78: =_xlfn.XLOOKUP(northwind_order_details[[#This Row],[order_id]],northwind_orders[order_id],northwind_orders[ship_country]) -> Germany | G78: =INDEX(northwind_orders[],MATCH(northwind_order_details[[#This Row],[order_id]], northwind_orders[order_id], 0), MATCH("employee_id", northwind_orders[#Headers], 0)) -> 2 | H78: =northwind_order_details[[#This Row],[unit_price]]*northwind_order_details[[#This Row],[quantity]] -> 728 | I78: =northwind_order_details[[#This Row],[purchase amount]]*northwind_order_details[[#This Row],[discount]] -> 0 | J78: =northwind_order_details[[#This Row],[purchase amount]]-northwind_order_details[[#This Row],[discount amount]] -> 728 | K78: =IF(northwind_order_details[[#This Row],[discount amount]]>0,"Yes","No") -> No | L78: =IF(northwind_order_details[[#This Row],[Revenue]]>1000,"High",IF(northwind_order_details[[#This Row],[Revenue]]>300,"Medium","Low")) -> Medium | M78: =IF(northwind_order_details[[#This Row],[unit_price]]=_xlfn.XLOOKUP(northwind_order_details[[#This Row],[product_id]],'Price Validation'!$D$2:$D$78,'Price Validation'!$E$2:$E$78),"Match","Mismatch") -> Mismatch
A79: 10277 | B79: 62 | C79: 39.4 | D79: 12 | E79: 0 | F79: =_xlfn.XLOOKUP(northwind_order_details[[#This Row],[order_id]],northwind_orders[order_id],northwind_orders[ship_country]) -> Germany | G79: =INDEX(northwind_orders[],MATCH(northwind_order_details[[#This Row],[order_id]], northwind_orders[order_id], 0), MATCH("employee_id", northwind_orders[#Headers], 0)) -> 2 | H79: =northwind_order_details[[#This Row],[unit_price]]*northwind_order_details[[#This Row],[quantity]] -> 472.8 | I79: =northwind_order_details[[#This Row],[purchase amount]]*northwind_order_details[[#This Row],[discount]] -> 0 | J79: =northwind_order_details[[#This Row],[purchase amount]]-northwind_order_details[[#This Row],[discount amount]] -> 472.8 | K79: =IF(northwind_order_details[[#This Row],[discount amount]]>0,"Yes","No") -> No | L79: =IF(northwind_order_details[[#This Row],[Revenue]]>1000,"High",IF(northwind_order_details[[#This Row],[Revenue]]>300,"Medium","Low")) -> Medium | M79: =IF(northwind_order_details[[#This Row],[unit_price]]=_xlfn.XLOOKUP(northwind_order_details[[#This Row],[product_id]],'Price Validation'!$D$2:$D$78,'Price Validation'!$E$2:$E$78),"Match","Mismatch") -> Mismatch
A80: 10278 | B80: 44 | C80: 15.5 | D80: 16 | E80: 0 | F80: =_xlfn.XLOOKUP(northwind_order_details[[#This Row],[order_id]],northwind_orders[order_id],northwind_orders[ship_country]) -> Sweden | G80: =INDEX(northwind_orders[],MATCH(northwind_order_details[[#This Row],[order_id]], northwind_orders[order_id], 0), MATCH("employee_id", northwind_orders[#Headers], 0)) -> 8 | H80: =northwind_order_details[[#This Row],[unit_price]]*northwind_order_details[[#This Row],[quantity]] -> 248 | I80: =northwind_order_details[[#This Row],[purchase amount]]*northwind_order_details[[#This Row],[discount]] -> 0 | J80: =northwind_order_details[[#This Row],[purchase amount]]-northwind_order_details[[#This Row],[discount amount]] -> 248 | K80: =IF(northwind_order_details[[#This Row],[discount amount]]>0,"Yes","No") -> No | L80: =IF(northwind_order_details[[#This Row],[Revenue]]>1000,"High",IF(northwind_order_details[[#This Row],[Revenue]]>300,"Medium","Low")) -> Low | M80: =IF(northwind_order_details[[#This Row],[unit_price]]=_xlfn.XLOOKUP(northwind_order_details[[#This Row],[product_id]],'Price Validation'!$D$2:$D$78,'Price Validation'!$E$2:$E$78),"Match","Mismatch") -> Mismatch
A81: 10278 | B81: 59 | C81: 44 | D81: 15 | E81: 0 | F81: =_xlfn.XLOOKUP(northwind_order_details[[#This Row],[order_id]],northwind_orders[order_id],northwind_orders[ship_country]) -> Sweden | G81: =INDEX(northwind_orders[],MATCH(northwind_order_details[[#This Row],[order_id]], northwind_orders[order_id], 0), MATCH("employee_id", northwind_orders[#Headers], 0)) -> 8 | H81: =northwind_order_details[[#This Row],[unit_price]]*northwind_order_details[[#This Row],[quantity]] -> 660 | I81: =northwind_order_details[[#This Row],[purchase amount]]*northwind_order_details[[#This Row],[discount]] -> 0 | J81: =northwind_order_details[[#This Row],[purchase amount]]-northwind_order_details[[#This Row],[discount amount]] -> 660 | K81: =IF(northwind_order_details[[#This Row],[discount amount]]>0,"Yes","No") -> No | L81: =IF(northwind_order_details[[#This Row],[Revenue]]>1000,"High",IF(northwind_order_details[[#This Row],[Revenue]]>300,"Medium","Low")) -> Medium | M81: =IF(northwind_order_details[[#This Row],[unit_price]]=_xlfn.XLOOKUP(northwind_order_details[[#This Row],[product_id]],'Price Validation'!$D$2:$D$78,'Price Validation'!$E$2:$E$78),"Match","Mismatch") -> Mismatch
A82: 10278 | B82: 63 | C82: 35.1 | D82: 8 | E82: 0 | F82: =_xlfn.XLOOKUP(northwind_order_details[[#This Row],[order_id]],northwind_orders[order_id],northwind_orders[ship_country]) -> Sweden | G82: =INDEX(northwind_orders[],MATCH(northwind_order_details[[#This Row],[order_id]], northwind_orders[order_id], 0), MATCH("employee_id", northwind_orders[#Headers], 0)) -> 8 | H82: =northwind_order_details[[#This Row],[unit_price]]*northwind_order_details[[#This Row],[quantity]] -> 280.8 | I82: =northwind_order_details[[#This Row],[purchase amount]]*northwind_order_details[[#This Row],[discount]] -> 0 | J82: =northwind_order_details[[#This Row],[purchase amount]]-northwind_order_details[[#This Row],[discount amount]] -> 280.8 | K82: =IF(northwind_order_details[[#This Row],[discount amount]]>0,"Yes","No") -> No | L82: =IF(northwind_order_details[[#This Row],[Revenue]]>1000,"High",IF(northwind_order_details[[#This Row],[Revenue]]>300,"Medium","Low")) -> Low | M82: =IF(northwind_order_details[[#This Row],[unit_price]]=_xlfn.XLOOKUP(northwind_order_details[[#This Row],[product_id]],'Price Validation'!$D$2:$D$78,'Price Validation'!$E$2:$E$78),"Match","Mismatch") -> Mismatch
A83: 10278 | B83: 73 | C83: 12 | D83: 25 | E83: 0 | F83: =_xlfn.XLOOKUP(northwind_order_details[[#This Row],[order_id]],northwind_orders[order_id],northwind_orders[ship_country]) -> Sweden | G83: =INDEX(northwind_orders[],MATCH(northwind_order_details[[#This Row],[order_id]], northwind_orders[order_id], 0), MATCH("employee_id", northwind_orders[#Headers], 0)) -> 8 | H83: =northwind_order_details[[#This Row],[unit_price]]*northwind_order_details[[#This Row],[quantity]] -> 300 | I83: =northwind_order_details[[#This Row],[purchase amount]]*northwind_order_details[[#This Row],[discount]] -> 0 | J83: =northwind_order_details[[#This Row],[purchase amount]]-northwind_order_details[[#This Row],[discount amount]] -> 300 | K83: =IF(northwind_order_details[[#This Row],[discount amount]]>0,"Yes","No") -> No | L83: =IF(northwind_order_details[[#This Row],[Revenue]]>1000,"High",IF(northwind_order_details[[#This Row],[Revenue]]>300,"Medium","Low")) -> Low | M83: =IF(northwind_order_details[[#This Row],[unit_price]]=_xlfn.XLOOKUP(northwind_order_details[[#This Row],[product_id]],'Price Validation'!$D$2:$D$78,'Price Validation'!$E$2:$E$78),"Match","Mismatch") -> Mismatch
A84: 10279 | B84: 17 | C84: 31.2 | D84: 15 | E84: 0.25 | F84: =_xlfn.XLOOKUP(northwind_order_details[[#This Row],[order_id]],northwind_orders[order_id],northwind_orders[ship_country]) -> Germany | G84: =INDEX(northwind_orders[],MATCH(northwind_order_details[[#This Row],[order_id]], northwind_orders[order_id], 0), MATCH("employee_id", northwind_orders[#Headers], 0)) -> 8 | H84: =northwind_order_details[[#This Row],[unit_price]]*northwind_order_details[[#This Row],[quantity]] -> 468 | I84: =northwind_order_details[[#This Row],[purchase amount]]*northwind_order_details[[#This Row],[discount]] -> 117 | J84: =northwind_order_details[[#This Row],[purchase amount]]-northwind_order_details[[#This Row],[discount amount]] -> 351 | K84: =IF(northwind_order_details[[#This Row],[discount amount]]>0,"Yes","No") -> Yes | L84: =IF(northwind_order_details[[#This Row],[Revenue]]>1000,"High",IF(northwind_order_details[[#This Row],[Revenue]]>300,"Medium","Low")) -> Medium | M84: =IF(northwind_order_details[[#This Row],[unit_price]]=_xlfn.XLOOKUP(northwind_order_details[[#This Row],[product_id]],'Price Validation'!$D$2:$D$78,'Price Validation'!$E$2:$E$78),"Match","Mismatch") -> Mismatch
A85: 10280 | B85: 24 | C85: 3.6 | D85: 12 | E85: 0 | F85: =_xlfn.XLOOKUP(northwind_order_details[[#This Row],[order_id]],northwind_orders[order_id],northwind_orders[ship_country]) -> Sweden | G85: =INDEX(northwind_orders[],MATCH(northwind_order_details[[#This Row],[order_id]], northwind_orders[order_id], 0), MATCH("employee_id", northwind_orders[#Headers], 0)) -> 2 | H85: =northwind_order_details[[#This Row],[unit_price]]*northwind_order_details[[#This Row],[quantity]] -> 43.2 | I85: =northwind_order_details[[#This Row],[purchase amount]]*northwind_order_details[[#This Row],[discount]] -> 0 | J85: =northwind_order_details[[#This Row],[purchase amount]]-northwind_order_details[[#This Row],[discount amount]] -> 43.2 | K85: =IF(northwind_order_details[[#This Row],[discount amount]]>0,"Yes","No") -> No | L85: =IF(northwind_order_details[[#This Row],[Revenue]]>1000,"High",IF(northwind_order_details[[#This Row],[Revenue]]>300,"Medium","Low")) -> Low | M85: =IF(northwind_order_details[[#This Row],[unit_price]]=_xlfn.XLOOKUP(northwind_order_details[[#This Row],[product_id]],'Price Validation'!$D$2:$D$78,'Price Validation'!$E$2:$E$78),"Match","Mismatch") -> Mismatch
A86: 10280 | B86: 55 | C86: 19.2 | D86: 20 | E86: 0 | F86: =_xlfn.XLOOKUP(northwind_order_details[[#This Row],[order_id]],northwind_orders[order_id],northwind_orders[ship_country]) -> Sweden | G86: =INDEX(northwind_orders[],MATCH(northwind_order_details[[#This Row],[order_id]], northwind_orders[order_id], 0), MATCH("employee_id", northwind_orders[#Headers], 0)) -> 2 | H86: =northwind_order_details[[#This Row],[unit_price]]*northwind_order_details[[#This Row],[quantity]] -> 384 | I86: =northwind_order_details[[#This Row],[purchase amount]]*northwind_order_details[[#This Row],[discount]] -> 0 | J86: =northwind_order_details[[#This Row],[purchase amount]]-northwind_order_details[[#This Row],[discount amount]] -> 384 | K86: =IF(northwind_order_details[[#This Row],[discount amount]]>0,"Yes","No") -> No | L86: =IF(northwind_order_details[[#This Row],[Revenue]]>1000,"High",IF(northwind_order_details[[#This Row],[Revenue]]>300,"Medium","Low")) -> Medium | M86: =IF(northwind_order_details[[#This Row],[unit_price]]=_xlfn.XLOOKUP(northwind_order_details[[#This Row],[product_id]],'Price Validation'!$D$2:$D$78,'Price Validation'!$E$2:$E$78),"Match","Mismatch") -> Mismatch
A87: 10280 | B87: 75 | C87: 6.2 | D87: 30 | E87: 0 | F87: =_xlfn.XLOOKUP(northwind_order_details[[#This Row],[order_id]],northwind_orders[order_id],northwind_orders[ship_country]) -> Sweden | G87: =INDEX(northwind_orders[],MATCH(northwind_order_details[[#This Row],[order_id]], northwind_orders[order_id], 0), MATCH("employee_id", northwind_orders[#Headers], 0)) -> 2 | H87: =northwind_order_details[[#This Row],[unit_price]]*northwind_order_details[[#This Row],[quantity]] -> 186 | I87: =northwind_order_details[[#This Row],[purchase amount]]*northwind_order_details[[#This Row],[discount]] -> 0 | J87: =northwind_order_details[[#This Row],[purchase amount]]-northwind_order_details[[#This Row],[discount amount]] -> 186 | K87: =IF(northwind_order_details[[#This Row],[discount amount]]>0,"Yes","No") -> No | L87: =IF(northwind_order_details[[#This Row],[Revenue]]>1000,"High",IF(northwind_order_details[[#This Row],[Revenue]]>300,"Medium","Low")) -> Low | M87: =IF(northwind_order_details[[#This Row],[unit_price]]=_xlfn.XLOOKUP(northwind_order_details[[#This Row],[product_id]],'Price Validation'!$D$2:$D$78,'Price Validation'!$E$2:$E$78),"Match","Mismatch") -> Mismatch
A88: 10281 | B88: 19 | C88: 7.3 | D88: 1 | E88: 0 | F88: =_xlfn.XLOOKUP(northwind_order_details[[#This Row],[order_id]],northwind_orders[order_id],northwind_orders[ship_country]) -> Spain | G88: =INDEX(northwind_orders[],MATCH(northwind_order_details[[#This Row],[order_id]], northwind_orders[order_id], 0), MATCH("employee_id", northwind_orders[#Headers], 0)) -> 4 | H88: =northwind_order_details[[#This Row],[unit_price]]*northwind_order_details[[#This Row],[quantity]] -> 7.3 | I88: =northwind_order_details[[#This Row],[purchase amount]]*northwind_order_details[[#This Row],[discount]] -> 0 | J88: =northwind_order_details[[#This Row],[purchase amount]]-northwind_order_details[[#This Row],[discount amount]] -> 7.3 | K88: =IF(northwind_order_details[[#This Row],[discount amount]]>0,"Yes","No") -> No | L88: =IF(northwind_order_details[[#This Row],[Revenue]]>1000,"High",IF(northwind_order_details[[#This Row],[Revenue]]>300,"Medium","Low")) -> Low | M88: =IF(northwind_order_details[[#This Row],[unit_price]]=_xlfn.XLOOKUP(northwind_order_details[[#This Row],[product_id]],'Price Validation'!$D$2:$D$78,'Price Validation'!$E$2:$E$78),"Match","Mismatch") -> Mismatch
A89: 10281 | B89: 24 | C89: 3.6 | D89: 6 | E89: 0 | F89: =_xlfn.XLOOKUP(northwind_order_details[[#This Row],[order_id]],northwind_orders[order_id],northwind_orders[ship_country]) -> Spain | G89: =INDEX(northwind_orders[],MATCH(northwind_order_details[[#This Row],[order_id]], northwind_orders[order_id], 0), MATCH("employee_id", northwind_orders[#Headers], 0)) -> 4 | H89: =northwind_order_details[[#This Row],[unit_price]]*northwind_order_details[[#This Row],[quantity]] -> 21.6 | I89: =northwind_order_details[[#This Row],[purchase amount]]*northwind_order_details[[#This Row],[discount]] -> 0 | J89: =northwind_order_details[[#This Row],[purchase amount]]-northwind_order_details[[#This Row],[discount amount]] -> 21.6 | K89: =IF(northwind_order_details[[#This Row],[discount amount]]>0,"Yes","No") -> No | L89: =IF(northwind_order_details[[#This Row],[Revenue]]>1000,"High",IF(northwind_order_details[[#This Row],[Revenue]]>300,"Medium","Low")) -> Low | M89: =IF(northwind_order_details[[#This Row],[unit_price]]=_xlfn.XLOOKUP(northwind_order_details[[#This Row],[product_id]],'Price Validation'!$D$2:$D$78,'Price Validation'!$E$2:$E$78),"Match","Mismatch") -> Mismatch
A90: 10281 | B90: 35 | C90: 14.4 | D90: 4 | E90: 0 | F90: =_xlfn.XLOOKUP(northwind_order_details[[#This Row],[order_id]],northwind_orders[order_id],northwind_orders[ship_country]) -> Spain | G90: =INDEX(northwind_orders[],MATCH(northwind_order_details[[#This Row],[order_id]], northwind_orders[order_id], 0), MATCH("employee_id", northwind_orders[#Headers], 0)) -> 4 | H90: =northwind_order_details[[#This Row],[unit_price]]*northwind_order_details[[#This Row],[quantity]] -> 57.6 | I90: =northwind_order_details[[#This Row],[purchase amount]]*northwind_order_details[[#This Row],[discount]] -> 0 | J90: =northwind_order_details[[#This Row],[purchase amount]]-northwind_order_details[[#This Row],[discount amount]] -> 57.6 | K90: =IF(northwind_order_details[[#This Row],[discount amount]]>0,"Yes","No") -> No | L90: =IF(northwind_order_details[[#This Row],[Revenue]]>1000,"High",IF(northwind_order_details[[#This Row],[Revenue]]>300,"Medium","Low")) -> Low | M90: =IF(northwind_order_details[[#This Row],[unit_price]]=_xlfn.XLOOKUP(northwind_order_details[[#This Row],[product_id]],'Price Validation'!$D$2:$D$78,'Price Validation'!$E$2:$E$78),"Match","Mismatch") -> Mismatch
A91: 10282 | B91: 30 | C91: 20.7 | D91: 6 | E91: 0 | F91: =_xlfn.XLOOKUP(northwind_order_details[[#This Row],[order_id]],northwind_orders[order_id],northwind_orders[ship_country]) -> Spain | G91: =INDEX(northwind_orders[],MATCH(northwind_order_details[[#This Row],[order_id]], northwind_orders[order_id], 0), MATCH("employee_id", northwind_orders[#Headers], 0)) -> 4 | H91: =northwind_order_details[[#This Row],[unit_price]]*northwind_order_details[[#This Row],[quantity]] -> 124.2 | I91: =northwind_order_details[[#This Row],[purchase amount]]*northwind_order_details[[#This Row],[discount]] -> 0 | J91: =northwind_order_details[[#This Row],[purchase amount]]-northwind_order_details[[#This Row],[discount amount]] -> 124.2 | K91: =IF(northwind_order_details[[#This Row],[discount amount]]>0,"Yes","No") -> No | L91: =IF(northwind_order_details[[#This Row],[Revenue]]>1000,"High",IF(northwind_order_details[[#This Row],[Revenue]]>300,"Medium","Low")) -> Low | M91: =IF(northwind_order_details[[#This Row],[unit_price]]=_xlfn.XLOOKUP(northwind_order_details[[#This Row],[product_id]],'Price Validation'!$D$2:$D$78,'Price Validation'!$E$2:$E$78),"Match","Mismatch") -> Mismatch
A92: 10282 | B92: 57 | C92: 15.6 | D92: 2 | E92: 0 | F92: =_xlfn.XLOOKUP(northwind_order_details[[#This Row],[order_id]],northwind_orders[order_id],northwind_orders[ship_country]) -> Spain | G92: =INDEX(northwind_orders[],MATCH(northwind_order_details[[#This Row],[order_id]], northwind_orders[order_id], 0), MATCH("employee_id", northwind_orders[#Headers], 0)) -> 4 | H92: =northwind_order_details[[#This Row],[unit_price]]*northwind_order_details[[#This Row],[quantity]] -> 31.2 | I92: =northwind_order_details[[#This Row],[purchase amount]]*northwind_order_details[[#This Row],[discount]] -> 0 | J92: =northwind_order_details[[#This Row],[purchase amount]]-northwind_order_details[[#This Row],[discount amount]] -> 31.2 | K92: =IF(northwind_order_details[[#This Row],[discount amount]]>0,"Yes","No") -> No | L92: =IF(northwind_order_details[[#This Row],[Revenue]]>1000,"High",IF(northwind_order_details[[#This Row],[Revenue]]>300,"Medium","Low")) -> Low | M92: =IF(northwind_order_details[[#This Row],[unit_price]]=_xlfn.XLOOKUP(northwind_order_details[[#This Row],[product_id]],'Price Validation'!$D$2:$D$78,'Price Validation'!$E$2:$E$78),"Match","Mismatch") -> Mismatch
A93: 10283 | B93: 15 | C93: 12.4 | D93: 20 | E93: 0 | F93: =_xlfn.XLOOKUP(northwind_order_details[[#This Row],[order_id]],northwind_orders[order_id],northwind_orders[ship_country]) -> Venezuela | G93: =INDEX(northwind_orders[],MATCH(northwind_order_details[[#This Row],[order_id]], northwind_orders[order_id], 0), MATCH("employee_id", northwind_orders[#Headers], 0)) -> 3 | H93: =northwind_order_details[[#This Row],[unit_price]]*northwind_order_details[[#This Row],[quantity]] -> 248 | I93: =northwind_order_details[[#This Row],[purchase amount]]*northwind_order_details[[#This Row],[discount]] -> 0 | J93: =northwind_order_details[[#This Row],[purchase amount]]-northwind_order_details[[#This Row],[discount amount]] -> 248 | K93: =IF(northwind_order_details[[#This Row],[discount amount]]>0,"Yes","No") -> No | L93: =IF(northwind_order_details[[#This Row],[Revenue]]>1000,"High",IF(northwind_order_details[[#This Row],[Revenue]]>300,"Medium","Low")) -> Low | M93: =IF(northwind_order_details[[#This Row],[unit_price]]=_xlfn.XLOOKUP(northwind_order_details[[#This Row],[product_id]],'Price Validation'!$D$2:$D$78,'Price Validation'!$E$2:$E$78),"Match","Mismatch") -> Mismatch
A94: 10283 | B94: 19 | C94: 7.3 | D94: 18 | E94: 0 | F94: =_xlfn.XLOOKUP(northwind_order_details[[#This Row],[order_id]],northwind_orders[order_id],northwind_orders[ship_country]) -> Venezuela | G94: =INDEX(northwind_orders[],MATCH(northwind_order_details[[#This Row],[order_id]], northwind_orders[order_id], 0), MATCH("employee_id", northwind_orders[#Headers], 0)) -> 3 | H94: =northwind_order_details[[#This Row],[unit_price]]*northwind_order_details[[#This Row],[quantity]] -> 131.4 | I94: =northwind_order_details[[#This Row],[purchase amount]]*northwind_order_details[[#This Row],[discount]] -> 0 | J94: =northwind_order_details[[#This Row],[purchase amount]]-northwind_order_details[[#This Row],[discount amount]] -> 131.4 | K94: =IF(northwind_order_details[[#This Row],[discount amount]]>0,"Yes","No") -> No | L94: =IF(northwind_order_details[[#This Row],[Revenue]]>1000,"High",IF(northwind_order_details[[#This Row],[Revenue]]>300,"Medium","Low")) -> Low | M94: =IF(northwind_order_details[[#This Row],[unit_price]]=_xlfn.XLOOKUP(northwind_order_details[[#This Row],[product_id]],'Price Validation'!$D$2:$D$78,'Price Validation'!$E$2:$E$78),"Match","Mismatch") -> Mismatch
A95: 10283 | B95: 60 | C95: 27.2 | D95: 35 | E95: 0 | F95: =_xlfn.XLOOKUP(northwind_order_details[[#This Row],[order_id]],northwind_orders[order_id],northwind_orders[ship_country]) -> Venezuela | G95: =INDEX(northwind_orders[],MATCH(northwind_order_details[[#This Row],[order_id]], northwind_orders[order_id], 0), MATCH("employee_id", northwind_orders[#Headers], 0)) -> 3 | H95: =northwind_order_details[[#This Row],[unit_price]]*northwind_order_details[[#This Row],[quantity]] -> 952 | I95: =northwind_order_details[[#This Row],[purchase amount]]*northwind_order_details[[#This Row],[discount]] -> 0 | J95: =northwind_order_details[[#This Row],[purchase amount]]-northwind_order_details[[#This Row],[discount amount]] -> 952 | K95: =IF(northwind_order_details[[#This Row],[discount amount]]>0,"Yes","No") -> No | L95: =IF(northwind_order_details[[#This Row],[Revenue]]>1000,"High",IF(northwind_order_details[[#This Row],[Revenue]]>300,"Medium","Low")) -> Medium | M95: =IF(northwind_order_details[[#This Row],[unit_price]]=_xlfn.XLOOKUP(northwind_order_details[[#This Row],[product_id]],'Price Validation'!$D$2:$D$78,'Price Validation'!$E$2:$E$78),"Match","Mismatch") -> Mismatch
A96: 10283 | B96: 72 | C96: 27.8 | D96: 3 | E96: 0 | F96: =_xlfn.XLOOKUP(northwind_order_details[[#This Row],[order_id]],northwind_orders[order_id],northwind_orders[ship_country]) -> Venezuela | G96: =INDEX(northwind_orders[],MATCH(northwind_order_details[[#This Row],[order_id]], northwind_orders[order_id], 0), MATCH("employee_id", northwind_orders[#Headers], 0)) -> 3 | H96: =northwind_order_details[[#This Row],[unit_price]]*northwind_order_details[[#This Row],[quantity]] -> 83.4 | I96: =northwind_order_details[[#This Row],[purchase amount]]*northwind_order_details[[#This Row],[discount]] -> 0 | J96: =northwind_order_details[[#This Row],[purchase amount]]-northwind_order_details[[#This Row],[discount amount]] -> 83.4 | K96: =IF(northwind_order_details[[#This Row],[discount amount]]>0,"Yes","No") -> No | L96: =IF(northwind_order_details[[#This Row],[Revenue]]>1000,"High",IF(northwind_order_details[[#This Row],[Revenue]]>300,"Medium","Low")) -> Low | M96: =IF(northwind_order_details[[#This Row],[unit_price]]=_xlfn.XLOOKUP(northwind_order_details[[#This Row],[product_id]],'Price Validation'!$D$2:$D$78,'Price Validation'!$E$2:$E$78),"Match","Mismatch") -> Mismatch
A97: 10284 | B97: 27 | C97: 35.1 | D97: 15 | E97: 0.25 | F97: =_xlfn.XLOOKUP(northwind_order_details[[#This Row],[order_id]],northwind_orders[order_id],northwind_orders[ship_country]) -> Germany | G97: =INDEX(northwind_orders[],MATCH(northwind_order_details[[#This Row],[order_id]], northwind_orders[order_id], 0), MATCH("employee_id", northwind_orders[#Headers], 0)) -> 4 | H97: =northwind_order_details[[#This Row],[unit_price]]*northwind_order_details[[#This Row],[quantity]] -> 526.5 | I97: =northwind_order_details[[#This Row],[purchase amount]]*northwind_order_details[[#This Row],[discount]] -> 131.625 | J97: =northwind_order_details[[#This Row],[purchase amount]]-northwind_order_details[[#This Row],[discount amount]] -> 394.875 | K97: =IF(northwind_order_details[[#This Row],[discount amount]]>0,"Yes","No") -> Yes | L97: =IF(northwind_order_details[[#This Row],[Revenue]]>1000,"High",IF(northwind_order_details[[#This Row],[Revenue]]>300,"Medium","Low")) -> Medium | M97: =IF(northwind_order_details[[#This Row],[unit_price]]=_xlfn.XLOOKUP(northwind_order_details[[#This Row],[product_id]],'Price Validation'!$D$2:$D$78,'Price Validation'!$E$2:$E$78),"Match","Mismatch") -> Mismatch
A98: 10284 | B98: 44 | C98: 15.5 | D98: 21 | E98: 0 | F98: =_xlfn.XLOOKUP(northwind_order_details[[#This Row],[order_id]],northwind_orders[order_id],northwind_orders[ship_country]) -> Germany | G98: =INDEX(northwind_orders[],MATCH(northwind_order_details[[#This Row],[order_id]], northwind_orders[order_id], 0), MATCH("employee_id", northwind_orders[#Headers], 0)) -> 4 | H98: =northwind_order_details[[#This Row],[unit_price]]*northwind_order_details[[#This Row],[quantity]] -> 325.5 | I98: =northwind_order_details[[#This Row],[purchase amount]]*northwind_order_details[[#This Row],[discount]] -> 0 | J98: =northwind_order_details[[#This Row],[purchase amount]]-northwind_order_details[[#This Row],[discount amount]] -> 325.5 | K98: =IF(northwind_order_details[[#This Row],[discount amount]]>0,"Yes","No") -> No | L98: =IF(northwind_order_details[[#This Row],[Revenue]]>1000,"High",IF(northwind_order_details[[#This Row],[Revenue]]>300,"Medium","Low")) -> Medium | M98: =IF(northwind_order_details[[#This Row],[unit_price]]=_xlfn.XLOOKUP(northwind_order_details[[#This Row],[product_id]],'Price Validation'!$D$2:$D$78,'Price Validation'!$E$2:$E$78),"Match","Mismatch") -> Mismatch
A99: 10284 | B99: 60 | C99: 27.2 | D99: 20 | E99: 0.25 | F99: =_xlfn.XLOOKUP(northwind_order_details[[#This Row],[order_id]],northwind_orders[order_id],northwind_orders[ship_country]) -> Germany | G99: =INDEX(northwind_orders[],MATCH(northwind_order_details[[#This Row],[order_id]], northwind_orders[order_id], 0), MATCH("employee_id", northwind_orders[#Headers], 0)) -> 4 | H99: =northwind_order_details[[#This Row],[unit_price]]*northwind_order_details[[#This Row],[quantity]] -> 544 | I99: =northwind_order_details[[#This Row],[purchase amount]]*northwind_order_details[[#This Row],[discount]] -> 136 | J99: =northwind_order_details[[#This Row],[purchase amount]]-northwind_order_details[[#This Row],[discount amount]] -> 408 | K99: =IF(northwind_order_details[[#This Row],[discount amount]]>0,"Yes","No") -> Yes | L99: =IF(northwind_order_details[[#This Row],[Revenue]]>1000,"High",IF(northwind_order_details[[#This Row],[Revenue]]>300,"Medium","Low")) -> Medium | M99: =IF(northwind_order_details[[#This Row],[unit_price]]=_xlfn.XLOOKUP(northwind_order_details[[#This Row],[product_id]],'Price Validation'!$D$2:$D$78,'Price Validation'!$E$2:$E$78),"Match","Mismatch") -> Mismatch
A100: 10284 | B100: 67 | C100: 11.2 | D100: 5 | E100: 0.25 | F100: =_xlfn.XLOOKUP(northwind_order_details[[#This Row],[order_id]],northwind_orders[order_id],northwind_orders[ship_country]) -> Germany | G100: =INDEX(northwind_orders[],MATCH(northwind_order_details[[#This Row],[order_id]], northwind_orders[order_id], 0), MATCH("employee_id", northwind_orders[#Headers], 0)) -> 4 | H100: =northwind_order_details[[#This Row],[unit_price]]*northwind_order_details[[#This Row],[quantity]] -> 56 | I100: =northwind_order_details[[#This Row],[purchase amount]]*northwind_order_details[[#This Row],[discount]] -> 14 | J100: =northwind_order_details[[#This Row],[purchase amount]]-northwind_order_details[[#This Row],[discount amount]] -> 42 | K100: =IF(northwind_order_details[[#This Row],[discount amount]]>0,"Yes","No") -> Yes | L100: =IF(northwind_order_details[[#This Row],[Revenue]]>1000,"High",IF(northwind_order_details[[#This Row],[Revenue]]>300,"Medium","Low")) -> Low | M100: =IF(northwind_order_details[[#This Row],[unit_price]]=_xlfn.XLOOKUP(northwind_order_details[[#This Row],[product_id]],'Price Validation'!$D$2:$D$78,'Price Validation'!$E$2:$E$78),"Match","Mismatch") -> Mismatch
...

Sheet Price Validation
A1: product_id | B1: unit_price | D1: Row Labels | E1: Max of unit_price
A2: 11 | B2: 14 | D2: 1 | E2: 18
A3: 42 | B3: 9.8 | D3: 2 | E3: 19
A4: 72 | B4: 34.8 | D4: 3 | E4: 10
A5: 14 | B5: 18.6 | D5: 4 | E5: 22
A6: 51 | B6: 42.4 | D6: 5 | E6: 21.35
A7: 41 | B7: 7.7 | D7: 6 | E7: 25
A8: 51 | B8: 42.4 | D8: 7 | E8: 30
A9: 65 | B9: 16.8 | D9: 8 | E9: 40
A10: 22 | B10: 16.8 | D10: 9 | E10: 97
A11: 57 | B11: 15.6 | D11: 10 | E11: 31
A12: 65 | B12: 16.8 | D12: 11 | E12: 21
A13: 20 | B13: 64.8 | D13: 12 | E13: 38
... A78: 28 | B78: 36.4 | D78: 77 | E78: 13
A79: 62 | B79: 39.4 | D79: Grand Total | E79: 263.5
A80: 44 | B80: 15.5
A81: 59 | B81: 44
A82: 63 | B82: 35.1
A83: 73 | B83: 12
A84: 17 | B84: 31.2
A85: 24 | B85: 3.6
A86: 55 | B86: 19.2
A87: 75 | B87: 6.2
A88: 19 | B88: 7.3
A89: 24 | B89: 3.6
A90: 35 | B90: 14.4
A91: 30 | B91: 20.7
... A2028: 39 | B2028: 18
